Workbook
Name _____Jan02: [1]data!$K$3:$K$295
Name _____Jan03: [1]data!$W$3:$W$295
Name _____Job1: '[2]BP Data'!$B$5:$B$280
Name _____Jul02: [1]data!$Q$3:$Q$295
Name _____Jun02: [1]data!$P$3:$P$295
Name _____Jun03: [1]data!$AB$3:$AB$295
Name ____Jan02: [3]data!$K$3:$K$295
Name ____Jan03: [3]data!$W$3:$W$295
Name ____Jun02: [3]data!$P$3:$P$295
Name ____Jun03: [3]data!$AB$3:$AB$295
Name ____tf3: [4]Intro!$J$148
Name ____tf4: [4]Intro!$J$150
Name ____tfd1: [4]Intro!$L$141
Name ____tfd2: [4]Intro!$L$143
Name ____tfd3: [4]Intro!$L$147
Name ____tfd4: [4]Intro!$L$149
Name ____tr1: [4]Intro!$C$140
Name ____tr2: [4]Intro!$C$142
Name ____tr3: [4]Intro!$C$150
Name ____trd1: [4]Intro!$B$140
Name ____trd2: [4]Intro!$B$142
Name ____trd3: [4]Intro!$B$148
Name ___Jun02: [3]data!$P$3:$P$295
Name ___Jun03: [3]data!$AB$3:$AB$295
Name ___tf2: [4]Intro!$J$142
Name ___tf3: [4]Intro!$J$148
Name ___tf4: [4]Intro!$J$150
Name ___tfd1: [4]Intro!$L$141
Name ___tfd2: [4]Intro!$L$143
Name ___tfd3: [4]Intro!$L$147
Name ___tfd4: [4]Intro!$L$149
Name ___tr1: [4]Intro!$C$140
Name ___tr2: [4]Intro!$C$142
Name ___tr3: [4]Intro!$C$150
Name ___trd1: [4]Intro!$B$140
Name ___trd2: [4]Intro!$B$142
Name ___trd3: [4]Intro!$B$148
Name __Jun02: [6]data!$P$3:$P$295
Name __Jun03: [6]data!$AB$3:$AB$295
Name __pg18: [7]Sheet10!$A$1:$S$66
Name __pg19: [7]Sheet9!$A$1:$M$52
Name __pg2: [7]Sheet1!$A$40:$J$76
Name __pg20: [7]Sheet11!$A$1:$W$26
Name __Pg21: [7]Sheet12!$A$1
Name __pg22: [7]Sheet13!$A$3
Name __pg23: [7]sheet14!$B$8
Name __pg24: '[8]Cash flow_curv'!$A$1
Name __pg25: [7]Sheet16!$C$36
Name __pg26: [7]Sheet17!$A$4
Name __pg27: [7]Sheet18!$A$1
Name __pg28: [7]Sheet19!$A$1
Name __pg3: [7]Sheet1!$A$78:$J$108
Name __pg4: [7]Sheet1!$A$110:$J$142
Name __pg5: [7]Sheet1!$A$144:$J$165
Name __pg6: [7]Sheet1!$A$168:$J$196
Name __pg7: '[7]Sheet1(2)'!$B$1:$D$25
Name __pg8: [7]Sheet2!$A$1:$G$41
Name __pg9: [7]Sheet2!$A$45:$G$87
Name __tf1: [4]Intro!$J$140
Name __tf2: [4]Intro!$J$142

Sheet MP & Eqpt Summary
B1: =SUMPRODUCT(--(#REF!='MP & Eqpt Summary'!G1),#REF!*1) -> #REF! | G1: ='Summary-Financial'!AB2 -> xxxx | H1: Major Equipment deployment
B2: SL No | C2: Resource Code | D2: Item Code | E2: Unit | F2: Description | G2: Rate | H2: Prelims | I2: T Swamy | J2: A K Singh | K2: A Nagarajan | L2: Off Road | M2: Total | N2: Available @ site | O2: Variation
A3: GRAD | B3: 1 | C3: E | D3: GRA | E3: Day | F3: Grader | G3: =VLOOKUP(F3,'MP & Eqpt Summary 1'!$D$3:$E$61,2,0) -> 0 | H3: =VLOOKUP($F3,'MP & Eqpt Summary 1'!$D$3:$AB$81,14,0) -> 0 | M3: =SUM(H3:L3) -> 0 | N3: =VLOOKUP($F3,'MP & Eqpt Summary 1'!$D$3:$AB$81,19,0) -> 0 | O3: =N3-M3 -> 0 | P3: 0 | Q3: =P3-N3 -> 0
A4: VIBR | B4: =B3+1 -> 2 | C4: E | D4: V.ROL | E4: Day | F4: Vibratory Roller | G4: =VLOOKUP(F4,'MP & Eqpt Summary 1'!$D$3:$E$61,2,0) -> 0 | H4: =VLOOKUP($F4,'MP & Eqpt Summary 1'!$D$3:$AB$81,14,0) -> 0 | M4: =SUM(H4:L4) -> 0 | N4: =VLOOKUP($F4,'MP & Eqpt Summary 1'!$D$3:$AB$81,19,0) -> 0 | O4: =N4-M4 -> 0 | P4: 0 | Q4: =P4-N4 -> 0
A5: VIBRH | B5: =B4+1 -> 3 | C5: E | D5: V.ROL (H) | E5: Day | F5: Vibratory Roller (Hire) | G5: 0 | M5: =SUM(H5:L5) -> 0 | O5: =N5-M5 -> 0 | P5: 0 | Q5: =P5-N5 -> 0
A6: DOZ | B6: =B5+1 -> 4 | C6: E | D6: DOZ | E6: Day | F6: Bull Dozer | G6: =VLOOKUP(F6,'MP & Eqpt Summary 1'!$D$3:$E$61,2,0) -> 0 | H6: =VLOOKUP($F6,'MP & Eqpt Summary 1'!$D$3:$AB$81,14,0) -> 0 | M6: =SUM(H6:L6) -> 0 | N6: =VLOOKUP($F6,'MP & Eqpt Summary 1'!$D$3:$AB$81,19,0) -> 0 | O6: =N6-M6 -> 0 | P6: 0 | Q6: =P6-N6 -> 0
A7: SVL | B7: =B6+1 -> 5 | C7: E | D7: SHL | E7: Day | F7: Wheel Loader | G7: =VLOOKUP(F7,'MP & Eqpt Summary 1'!$D$3:$E$61,2,0) -> 0 | H7: =VLOOKUP($F7,'MP & Eqpt Summary 1'!$D$3:$AB$81,14,0) -> 0 | M7: =SUM(H7:L7) -> 0 | N7: =VLOOKUP($F7,'MP & Eqpt Summary 1'!$D$3:$AB$81,19,0) -> 0 | O7: =N7-M7 -> 0 | P7: 0 | Q7: =P7-N7 -> 0
A8: JCB | B8: =B7+1 -> 6 | C8: E | D8: BHL | E8: Day | F8: Back Hoe Loader | G8: =VLOOKUP(F8,'MP & Eqpt Summary 1'!$D$3:$E$61,2,0) -> 0 | H8: =VLOOKUP($F8,'MP & Eqpt Summary 1'!$D$3:$AB$81,14,0) -> 0 | M8: =SUM(H8:L8) -> 0 | N8: =VLOOKUP($F8,'MP & Eqpt Summary 1'!$D$3:$AB$81,19,0) -> 0 | O8: =N8-M8 -> 0 | P8: 0 | Q8: =P8-N8 -> 0
A9: JCBH | B9: =B8+1 -> 7 | C9: E | D9: BHL (H) | E9: Day | F9: Back Hoe Loader (Hire) | G9: =VLOOKUP(F9,'MP & Eqpt Summary 1'!$D$3:$E$61,2,0) -> 0 | H9: =VLOOKUP($F9,'MP & Eqpt Summary 1'!$D$3:$AB$81,14,0) -> 0 | M9: =SUM(H9:L9) -> 0 | N9: =VLOOKUP($F9,'MP & Eqpt Summary 1'!$D$3:$AB$81,19,0) -> 0 | O9: =N9-M9 -> 0 | P9: 0 | Q9: =P9-N9 -> 0
A10: Mnt | B10: =B9+1 -> 8 | C10: Manlift | D10: 50.96 | E10: 0 | F10: Manlift | G10: =VLOOKUP(F10,'MP & Eqpt Summary 1'!$D$3:$E$61,2,0) -> 0 | H10: =VLOOKUP($F10,'MP & Eqpt Summary 1'!$D$3:$AB$81,14,0) -> 0 | M10: =SUM(H10:L10) -> 0 | N10: =VLOOKUP($F10,'MP & Eqpt Summary 1'!$D$3:$AB$81,19,0) -> 0 | O10: =N10-M10 -> 0 | P10: 0 | Q10: =P10-N10 -> 0
A11: EXC | B11: =B10+1 -> 9 | C11: E | D11: EXC | E11: Day | F11: Excavator | G11: =VLOOKUP(F11,'MP & Eqpt Summary 1'!$D$3:$E$61,2,0) -> 0 | H11: =VLOOKUP($F11,'MP & Eqpt Summary 1'!$D$3:$AB$81,14,0) -> 0 | M11: =SUM(H11:L11) -> 0 | N11: =VLOOKUP($F11,'MP & Eqpt Summary 1'!$D$3:$AB$81,19,0) -> 0 | O11: =N11-M11 -> 0 | P11: 0 | Q11: =P11-N11 -> 0
A12: WATB | B12: =B11+1 -> 10 | C12: E | D12: Tanker Bra | E12: Day | F12: Brackish Water Tanker | G12: =VLOOKUP(F12,'MP & Eqpt Summary 1'!$D$3:$E$61,2,0) -> 0 | H12: =VLOOKUP($F12,'MP & Eqpt Summary 1'!$D$3:$AB$81,14,0) -> 0 | M12: =SUM(H12:L12) -> 0 | N12: =VLOOKUP($F12,'MP & Eqpt Summary 1'!$D$3:$AB$81,19,0) -> 0 | O12: =N12-M12 -> 0 | P12: 0 | Q12: =P12-N12 -> 0
A13: WATT | B13: =B12+1 -> 11 | C13: E | D13: Tanker Tra | E13: Day | F13: Trailer Tanker (Brackish) | G13: =VLOOKUP(F13,'MP & Eqpt Summary 1'!$D$3:$E$61,2,0) -> 0 | H13: =VLOOKUP($F13,'MP & Eqpt Summary 1'!$D$3:$AB$81,14,0) -> 0 | M13: =SUM(H13:L13) -> 0 | N13: =VLOOKUP($F13,'MP & Eqpt Summary 1'!$D$3:$AB$81,19,0) -> 0 | O13: =N13-M13 -> 0 | P13: 0 | Q13: =P13-N13 -> 0 | T13: =36.68+80 -> 116.68
A14: TPRTR | B14: =B13+1 -> 12 | C14: E | D14: Tipper Tra | E14: Day | F14: Trailer Tipper | G14: =VLOOKUP(F14,'MP & Eqpt Summary 1'!$D$3:$E$61,2,0) -> 0 | H14: =VLOOKUP($F14,'MP & Eqpt Summary 1'!$D$3:$AB$81,14,0) -> 0 | M14: =SUM(H14:L14) -> 0 | N14: =VLOOKUP($F14,'MP & Eqpt Summary 1'!$D$3:$AB$81,19,0) -> 0 | O14: =N14-M14 -> 0 | P14: 0 | Q14: =P14-N14 -> 0 | T14: =T13/2 -> 58.34
A15: TPR | B15: =B14+1 -> 13 | C15: E | D15: TIP | E15: Day | F15: Tipper | G15: =VLOOKUP(F15,'MP & Eqpt Summary 1'!$D$3:$E$61,2,0) -> 0 | H15: =VLOOKUP($F15,'MP & Eqpt Summary 1'!$D$3:$AB$81,14,0) -> 0 | M15: =SUM(H15:L15) -> 0 | N15: =VLOOKUP($F15,'MP & Eqpt Summary 1'!$D$3:$AB$81,19,0) -> 0 | O15: =N15-M15 -> 0 | P15: 0 | Q15: =P15-N15 -> 0
A16: BDT | B16: =B15+1 -> 14 | C16: E | D16: Tanker Bit | E16: Day | F16: Bitumen Distributor | G16: =VLOOKUP(F16,'MP & Eqpt Summary 1'!$D$3:$E$61,2,0) -> 0 | H16: =VLOOKUP($F16,'MP & Eqpt Summary 1'!$D$3:$AB$81,14,0) -> 0 | M16: =SUM(H16:L16) -> 0 | N16: =VLOOKUP($F16,'MP & Eqpt Summary 1'!$D$3:$AB$81,19,0) -> 0 | O16: =N16-M16 -> 0 | P16: 0 | Q16: =P16-N16 -> 0
A17: TR | B17: =B16+1 -> 15 | C17: E | D17: Tandem H | E17: Day | F17: Tandem Roller | G17: =VLOOKUP(F17,'MP & Eqpt Summary 1'!$D$3:$E$61,2,0) -> 0 | H17: =VLOOKUP($F17,'MP & Eqpt Summary 1'!$D$3:$AB$81,14,0) -> 0 | M17: =SUM(H17:L17) -> 0 | N17: =VLOOKUP($F17,'MP & Eqpt Summary 1'!$D$3:$AB$81,19,0) -> 0 | O17: =N17-M17 -> 0 | P17: 0 | Q17: =P17-N17 -> 0
A18: PTR | B18: =B17+1 -> 16 | C18: E | D18: PTR | E18: Day | F18: Ptr | G18: =VLOOKUP(F18,'MP & Eqpt Summary 1'!$D$3:$E$61,2,0) -> 0 | H18: =VLOOKUP($F18,'MP & Eqpt Summary 1'!$D$3:$AB$81,14,0) -> 0 | M18: =SUM(H18:L18) -> 0 | N18: =VLOOKUP($F18,'MP & Eqpt Summary 1'!$D$3:$AB$81,19,0) -> 0 | O18: =N18-M18 -> 0 | P18: 0 | Q18: =P18-N18 -> 0
A19: MTR | B19: =B18+1 -> 17 | C19: E | D19: Tandem M | E19: Day | F19: Mini Tandem Roller | G19: =VLOOKUP(F19,'MP & Eqpt Summary 1'!$D$3:$E$61,2,0) -> 0 | H19: =VLOOKUP($F19,'MP & Eqpt Summary 1'!$D$3:$AB$81,14,0) -> 0 | M19: =SUM(H19:L19) -> 0 | N19: =VLOOKUP($F19,'MP & Eqpt Summary 1'!$D$3:$AB$81,19,0) -> 0 | O19: =N19-M19 -> 0 | P19: 0 | Q19: =P19-N19 -> 0
A20: PVA | B20: =B19+1 -> 18 | C20: E | D20: PAV | E20: Day | F20: Paver Asphalt | G20: =VLOOKUP(F20,'MP & Eqpt Summary 1'!$D$3:$E$61,2,0) -> 0 | H20: =VLOOKUP($F20,'MP & Eqpt Summary 1'!$D$3:$AB$81,14,0) -> 0 | M20: =SUM(H20:L20) -> 0 | N20: =VLOOKUP($F20,'MP & Eqpt Summary 1'!$D$3:$AB$81,19,0) -> 0 | O20: =N20-M20 -> 0 | P20: 0 | Q20: =P20-N20 -> 0
A21: HIAB | B21: =B20+1 -> 19 | C21: E | D21: Hiab | E21: Day | F21: Cargo With L/E | G21: =VLOOKUP(F21,'MP & Eqpt Summary 1'!$D$3:$E$61,2,0) -> 0 | H21: =VLOOKUP($F21,'MP & Eqpt Summary 1'!$D$3:$AB$81,14,0) -> 0 | M21: =SUM(H21:L21) -> 0 | N21: =VLOOKUP($F21,'MP & Eqpt Summary 1'!$D$3:$AB$81,19,0) -> 0 | O21: =N21-M21 -> 0 | P21: 0 | Q21: =P21-N21 -> 0
A22: CRA25 | B22: =B21+1 -> 20 | C22: E | D22: CRA | E22: Day | F22: Crane | G22: =VLOOKUP(F22,'MP & Eqpt Summary 1'!$D$3:$E$61,2,0) -> 0 | H22: =VLOOKUP($F22,'MP & Eqpt Summary 1'!$D$3:$AB$81,14,0) -> 0 | M22: =SUM(H22:L22) -> 0 | N22: =VLOOKUP($F22,'MP & Eqpt Summary 1'!$D$3:$AB$81,19,0) -> 0 | O22: =N22-M22 -> 0 | P22: 0 | Q22: =P22-N22 -> 0
A23: TRH | B23: =B22+1 -> 21 | C23: E | D23: High Bed | E23: Day | F23: Trailer High Bed | G23: =VLOOKUP(F23,'MP & Eqpt Summary 1'!$D$3:$E$61,2,0) -> 0 | H23: =VLOOKUP($F23,'MP & Eqpt Summary 1'!$D$3:$AB$81,14,0) -> 0 | M23: =SUM(H23:L23) -> 0 | N23: =VLOOKUP($F23,'MP & Eqpt Summary 1'!$D$3:$AB$81,19,0) -> 0 | O23: =N23-M23 -> 0 | P23: 0 | Q23: =P23-N23 -> 0
A24: LBT | B24: =B23+1 -> 22 | F24: Low bed trailer | G24: =VLOOKUP(F24,'MP & Eqpt Summary 1'!$D$3:$E$61,2,0) -> 0 | H24: =VLOOKUP($F24,'MP & Eqpt Summary 1'!$D$3:$AB$81,14,0) -> 0 | M24: =SUM(H24:L24) -> 0 | N24: =VLOOKUP($F24,'MP & Eqpt Summary 1'!$D$3:$AB$81,19,0) -> 0 | O24: =N24-M24 -> 0
A25: LAL | B25: =B24+1 -> 23 | C25: E | D25: LA | E25: Day | F25: Loadall | G25: =VLOOKUP(F25,'MP & Eqpt Summary 1'!$D$3:$E$61,2,0) -> 0 | H25: =VLOOKUP($F25,'MP & Eqpt Summary 1'!$D$3:$AB$81,14,0) -> 0 | M25: =SUM(H25:L25) -> 0 | N25: =VLOOKUP($F25,'MP & Eqpt Summary 1'!$D$3:$AB$81,19,0) -> 0 | O25: =N25-M25 -> 0 | P25: 0 | Q25: =P25-N25 -> 0
A26: tc | B26: =B25+1 -> 24 | C26: E | D26: TC | E26: Day | F26: Tool Carrier | G26: =VLOOKUP(F26,'MP & Eqpt Summary 1'!$D$3:$E$61,2,0) -> 0 | H26: =VLOOKUP($F26,'MP & Eqpt Summary 1'!$D$3:$AB$81,14,0) -> 0 | M26: =SUM(H26:L26) -> 0 | N26: =VLOOKUP($F26,'MP & Eqpt Summary 1'!$D$3:$AB$81,19,0) -> 0 | O26: =N26-M26 -> 0 | P26: 0 | Q26: =P26-N26 -> 0
A27: SKID | B27: =B26+1 -> 25 | C27: E | D27: Skid | E27: Day | F27: Skid Loader | G27: =VLOOKUP(F27,'MP & Eqpt Summary 1'!$D$3:$E$61,2,0) -> 0 | H27: =VLOOKUP($F27,'MP & Eqpt Summary 1'!$D$3:$AB$81,14,0) -> 0 | M27: =SUM(H27:L27) -> 0 | N27: =VLOOKUP($F27,'MP & Eqpt Summary 1'!$D$3:$AB$81,19,0) -> 0 | O27: =N27-M27 -> 0 | P27: 0 | Q27: =P27-N27 -> 0
A28: PDM | B28: =B27+1 -> 26 | C28: E | D28: Guard | E28: Day | F28: Guard Rail M/C | G28: =VLOOKUP(F28,'MP & Eqpt Summary 1'!$D$3:$E$61,2,0) -> 0 | H28: =VLOOKUP($F28,'MP & Eqpt Summary 1'!$D$3:$AB$81,14,0) -> 0 | M28: =SUM(H28:L28) -> 0 | N28: =VLOOKUP($F28,'MP & Eqpt Summary 1'!$D$3:$AB$81,19,0) -> 0 | O28: =N28-M28 -> 0 | P28: 0 | Q28: =P28-N28 -> 0
A29: AC | B29: =B28+1 -> 27 | C29: E | D29: Asp Cut | E29: Day | F29: Asphalt Cutter | G29: =VLOOKUP(F29,'MP & Eqpt Summary 1'!$D$3:$E$61,2,0) -> 0 | H29: =VLOOKUP($F29,'MP & Eqpt Summary 1'!$D$3:$AB$81,14,0) -> 0 | M29: =SUM(H29:L29) -> 0 | N29: =VLOOKUP($F29,'MP & Eqpt Summary 1'!$D$3:$AB$81,19,0) -> 0 | O29: =N29-M29 -> 0 | P29: 0 | Q29: =P29-N29 -> 0
A30: PC | B30: =B29+1 -> 28 | C30: E | D30: Plate | E30: Day | F30: Plate Compactor | G30: =VLOOKUP(F30,'MP & Eqpt Summary 1'!$D$3:$E$61,2,0) -> 0 | H30: =VLOOKUP($F30,'MP & Eqpt Summary 1'!$D$3:$AB$81,14,0) -> 0 | M30: =SUM(H30:L30) -> 0 | N30: =VLOOKUP($F30,'MP & Eqpt Summary 1'!$D$3:$AB$81,19,0) -> 0 | O30: =N30-M30 -> 0 | P30: 0 | Q30: =P30-N30 -> 0
A31: VIB | B31: =B30+1 -> 29 | C31: E | D31: Vibrator | E31: Day | F31: Vibrator | G31: =VLOOKUP(F31,'MP & Eqpt Summary 1'!$D$3:$E$61,2,0) -> 0 | H31: =VLOOKUP($F31,'MP & Eqpt Summary 1'!$D$3:$AB$81,14,0) -> 0 | M31: =SUM(H31:L31) -> 0 | N31: =VLOOKUP($F31,'MP & Eqpt Summary 1'!$D$3:$AB$81,19,0) -> 0 | O31: =N31-M31 -> 0 | P31: 0 | Q31: =P31-N31 -> 0
A32: PEDR | B32: =B31+1 -> 30 | C32: E | D32: Roller Ped | E32: Day | F32: Pedestrian Roller | G32: =VLOOKUP(F32,'MP & Eqpt Summary 1'!$D$3:$E$61,2,0) -> 0 | H32: =VLOOKUP($F32,'MP & Eqpt Summary 1'!$D$3:$AB$81,14,0) -> 0 | M32: =SUM(H32:L32) -> 0 | N32: =VLOOKUP($F32,'MP & Eqpt Summary 1'!$D$3:$AB$81,19,0) -> 0 | O32: =N32-M32 -> 0 | P32: 0 | Q32: =P32-N32 -> 0
A33: BBM | B33: =B32+1 -> 31 | C33: E | D33: Bar Bend | E33: Day | F33: Bar Bending Machine | G33: =VLOOKUP(F33,'MP & Eqpt Summary 1'!$D$3:$E$61,2,0) -> 0 | H33: =VLOOKUP($F33,'MP & Eqpt Summary 1'!$D$3:$AB$81,14,0) -> 0 | M33: =SUM(H33:L33) -> 0 | N33: =VLOOKUP($F33,'MP & Eqpt Summary 1'!$D$3:$AB$81,19,0) -> 0 | O33: =N33-M33 -> 0 | P33: 0 | Q33: =P33-N33 -> 0
A34: BCM | B34: =B33+1 -> 32 | C34: E | D34: Bar Cut | E34: Day | F34: Bar Cutting Machine | G34: =VLOOKUP(F34,'MP & Eqpt Summary 1'!$D$3:$E$61,2,0) -> 0 | H34: =VLOOKUP($F34,'MP & Eqpt Summary 1'!$D$3:$AB$81,14,0) -> 0 | M34: =SUM(H34:L34) -> 0 | N34: =VLOOKUP($F34,'MP & Eqpt Summary 1'!$D$3:$AB$81,19,0) -> 0 | O34: =N34-M34 -> 0 | P34: 0 | Q34: =P34-N34 -> 0
A35: DUMP | B35: =B34+1 -> 33 | C35: E | D35: Dum | E35: Day | F35: Dumper | G35: =VLOOKUP(F35,'MP & Eqpt Summary 1'!$D$3:$E$61,2,0) -> 0 | H35: =VLOOKUP($F35,'MP & Eqpt Summary 1'!$D$3:$AB$81,14,0) -> 0 | M35: =SUM(H35:L35) -> 0 | N35: =VLOOKUP($F35,'MP & Eqpt Summary 1'!$D$3:$AB$81,19,0) -> 0 | O35: =N35-M35 -> 0 | P35: 0 | Q35: =P35-N35 -> 0
A36: PTL | B36: =B35+1 -> 34 | C36: E | D36: Tower Light | E36: Day | F36: Tower Light | G36: =VLOOKUP(F36,'MP & Eqpt Summary 1'!$D$3:$E$61,2,0) -> 0 | H36: =VLOOKUP($F36,'MP & Eqpt Summary 1'!$D$3:$AB$81,14,0) -> 0 | M36: =SUM(H36:L36) -> 0 | N36: =VLOOKUP($F36,'MP & Eqpt Summary 1'!$D$3:$AB$81,19,0) -> 0 | O36: =N36-M36 -> 0 | P36: 0 | Q36: =P36-N36 -> 0
... A40: MIXM | B40: =B39+1 -> 38 | C40: E | D40: Batch | E40: Day | F40: Weigh Batcher | G40: =VLOOKUP(F40,'MP & Eqpt Summary 1'!$D$3:$E$61,2,0) -> 0 | H40: =VLOOKUP($F40,'MP & Eqpt Summary 1'!$D$3:$AB$81,14,0) -> 0 | M40: =SUM(H40:L40) -> 0 | N40: =VLOOKUP($F40,'MP & Eqpt Summary 1'!$D$3:$AB$81,19,0) -> 0 | O40: =N40-M40 -> 0 | P40: 0 | Q40: =P40-N40 -> 0
A41: PG80 | B41: =B40+1 -> 39 | F41: Generator 1000 kva | G41: =VLOOKUP(F41,'MP & Eqpt Summary 1'!$D$3:$E$61,2,0) -> 0 | H41: =VLOOKUP($F41,'MP & Eqpt Summary 1'!$D$3:$AB$81,14,0) -> 0 | M41: =SUM(H41:L41) -> 0 | N41: =VLOOKUP($F41,'MP & Eqpt Summary 1'!$D$3:$AB$81,19,0) -> 0 | O41: =N41-M41 -> 0 | P41: #N/A | Q41: =P41-N41 -> #N/A
A42: PG50 | B42: =B41+1 -> 40 | F42: Generator upto 30 kva | G42: =VLOOKUP(F42,'MP & Eqpt Summary 1'!$D$3:$E$61,2,0) -> 0 | H42: =VLOOKUP($F42,'MP & Eqpt Summary 1'!$D$3:$AB$81,14,0) -> 0 | M42: =SUM(H42:L42) -> 0 | N42: =VLOOKUP($F42,'MP & Eqpt Summary 1'!$D$3:$AB$81,19,0) -> 0 | O42: =N42-M42 -> 0 | P42: #N/A | Q42: =P42-N42 -> #N/A
B43: =B42+1 -> 41 | F43: Generator upto 50 to 100 kva | G43: =VLOOKUP(F43,'MP & Eqpt Summary 1'!$D$3:$E$61,2,0) -> 0 | H43: =VLOOKUP($F43,'MP & Eqpt Summary 1'!$D$3:$AB$81,14,0) -> 0 | M43: =SUM(H43:L43) -> 0 | N43: =VLOOKUP($F43,'MP & Eqpt Summary 1'!$D$3:$AB$81,19,0) -> 0 | O43: =N43-M43 -> 0
B44: =B43+1 -> 42 | F44: Generator upto 150 to 250 kva | G44: =VLOOKUP(F44,'MP & Eqpt Summary 1'!$D$3:$E$61,2,0) -> 0 | H44: =VLOOKUP($F44,'MP & Eqpt Summary 1'!$D$3:$AB$81,14,0) -> 0 | M44: =SUM(H44:L44) -> 0 | N44: =VLOOKUP($F44,'MP & Eqpt Summary 1'!$D$3:$AB$81,19,0) -> 0 | O44: =N44-M44 -> 0
B45: =B44+1 -> 43 | F45: Generator 500 kva | G45: =VLOOKUP(F45,'MP & Eqpt Summary 1'!$D$3:$E$61,2,0) -> 0 | H45: =VLOOKUP($F45,'MP & Eqpt Summary 1'!$D$3:$AB$81,14,0) -> 0 | M45: =SUM(H45:L45) -> 0 | N45: =VLOOKUP($F45,'MP & Eqpt Summary 1'!$D$3:$AB$81,19,0) -> 0 | O45: =N45-M45 -> 0
A46: BBUS | B46: =B45+1 -> 44 | C46: E | D46: Bus H | E46: Day | F46: Heavy Bus | G46: =VLOOKUP(F46,'MP & Eqpt Summary 1'!$D$3:$E$61,2,0) -> 0 | H46: =VLOOKUP($F46,'MP & Eqpt Summary 1'!$D$3:$AB$81,14,0) -> 0 | M46: =SUM(H46:L46) -> 0 | N46: =VLOOKUP($F46,'MP & Eqpt Summary 1'!$D$3:$AB$81,19,0) -> 0 | O46: =N46-M46 -> 0 | P46: 0 | Q46: =P46-N46 -> 0
A47: CARGO | B47: =B46+1 -> 45 | C47: E | D47: 3 Ton | E47: Day | F47: 3 Ton Canter | G47: =VLOOKUP(F47,'MP & Eqpt Summary 1'!$D$3:$E$61,2,0) -> 0 | H47: =VLOOKUP($F47,'MP & Eqpt Summary 1'!$D$3:$AB$81,14,0) -> 0 | M47: =SUM(H47:L47) -> 0 | N47: =VLOOKUP($F47,'MP & Eqpt Summary 1'!$D$3:$AB$81,19,0) -> 0 | O47: =N47-M47 -> 0 | P47: 0 | Q47: =P47-N47 -> 0
A48: SBU | B48: =B47+1 -> 46 | C48: E | D48: Bus M | E48: Day | F48: Mini Bus | G48: =VLOOKUP(F48,'MP & Eqpt Summary 1'!$D$3:$E$61,2,0) -> 0 | H48: =VLOOKUP($F48,'MP & Eqpt Summary 1'!$D$3:$AB$81,14,0) -> 0 | M48: =SUM(H48:L48) -> 0 | N48: =VLOOKUP($F48,'MP & Eqpt Summary 1'!$D$3:$AB$81,19,0) -> 0 | O48: =N48-M48 -> 0 | P48: 0 | Q48: =P48-N48 -> 0
A49: SW | B49: =B48+1 -> 47 | C49: E | D49: WAG | E49: Day | F49: Station Wagon | G49: =VLOOKUP(F49,'MP & Eqpt Summary 1'!$D$3:$E$61,2,0) -> 0 | H49: =VLOOKUP($F49,'MP & Eqpt Summary 1'!$D$3:$AB$81,14,0) -> 0 | M49: =SUM(H49:L49) -> 0 | N49: =VLOOKUP($F49,'MP & Eqpt Summary 1'!$D$3:$AB$81,19,0) -> 0 | O49: =N49-M49 -> 0 | P49: 0 | Q49: =P49-N49 -> 0
A50: CAR | B50: =B49+1 -> 48 | C50: E | D50: CAR | E50: Day | F50: Saloon Car | G50: =VLOOKUP(F50,'MP & Eqpt Summary 1'!$D$3:$E$61,2,0) -> 0 | H50: =VLOOKUP($F50,'MP & Eqpt Summary 1'!$D$3:$AB$81,14,0) -> 0 | M50: =SUM(H50:L50) -> 0 | N50: =VLOOKUP($F50,'MP & Eqpt Summary 1'!$D$3:$AB$81,19,0) -> 0 | O50: =N50-M50 -> 0 | P50: 0 | Q50: =P50-N50 -> 0
A51: AMB | B51: =B50+1 -> 49 | C51: E | D51: AMB | E51: Day | F51: Ambulance | G51: =VLOOKUP(F51,'MP & Eqpt Summary 1'!$D$3:$E$61,2,0) -> 0 | H51: =VLOOKUP($F51,'MP & Eqpt Summary 1'!$D$3:$AB$81,14,0) -> 0 | M51: =SUM(H51:L51) -> 0 | N51: =VLOOKUP($F51,'MP & Eqpt Summary 1'!$D$3:$AB$81,19,0) -> 0 | O51: =N51-M51 -> 0 | P51: 0 | Q51: =P51-N51 -> 0
A52: PICK | B52: =B51+1 -> 50 | C52: E | D52: Pickup | E52: Day | F52: Pickup | G52: =VLOOKUP(F52,'MP & Eqpt Summary 1'!$D$3:$E$61,2,0) -> 0 | H52: =VLOOKUP($F52,'MP & Eqpt Summary 1'!$D$3:$AB$81,14,0) -> 0 | M52: =SUM(H52:L52) -> 0 | N52: =VLOOKUP($F52,'MP & Eqpt Summary 1'!$D$3:$AB$81,19,0) -> 0 | O52: =N52-M52 -> 0 | P52: 0 | Q52: =P52-N52 -> 0
A53: FL | B53: =B52+1 -> 51 | C53: E | D53: Fork | E53: Day | F53: Fork Lift | G53: =VLOOKUP(F53,'MP & Eqpt Summary 1'!$D$3:$E$61,2,0) -> 0 | H53: =VLOOKUP($F53,'MP & Eqpt Summary 1'!$D$3:$AB$81,14,0) -> 0 | M53: =SUM(H53:L53) -> 0 | N53: =VLOOKUP($F53,'MP & Eqpt Summary 1'!$D$3:$AB$81,19,0) -> 0 | O53: =N53-M53 -> 0 | P53: 0 | Q53: =P53-N53 -> 0
A54: WATP | B54: =B53+1 -> 52 | C54: E | D54: Tanker Pot | E54: Day | F54: Potable Water Tanker | G54: =VLOOKUP(F54,'MP & Eqpt Summary 1'!$D$3:$E$61,2,0) -> 0 | H54: =VLOOKUP($F54,'MP & Eqpt Summary 1'!$D$3:$AB$81,14,0) -> 0 | M54: =SUM(H54:L54) -> 0 | N54: =VLOOKUP($F54,'MP & Eqpt Summary 1'!$D$3:$AB$81,19,0) -> 0 | O54: =N54-M54 -> 0 | P54: 0 | Q54: =P54-N54 -> 0
A55: SEWT | B55: =B54+1 -> 53 | C55: E | D55: Tanker Sew | E55: Day | F55: Sewage Tanker | G55: =VLOOKUP(F55,'MP & Eqpt Summary 1'!$D$3:$E$61,2,0) -> 0 | H55: =VLOOKUP($F55,'MP & Eqpt Summary 1'!$D$3:$AB$81,14,0) -> 0 | M55: =SUM(H55:L55) -> 0 | N55: =VLOOKUP($F55,'MP & Eqpt Summary 1'!$D$3:$AB$81,19,0) -> 0 | O55: =N55-M55 -> 0 | P55: 0 | Q55: =P55-N55 -> 0
A56: FUT | B56: =B55+1 -> 54 | C56: E | D56: Fuel Tanker | E56: Day | F56: Fuel Tanker | G56: =VLOOKUP(F56,'MP & Eqpt Summary 1'!$D$3:$E$61,2,0) -> 0 | H56: =VLOOKUP($F56,'MP & Eqpt Summary 1'!$D$3:$AB$81,14,0) -> 0 | M56: =SUM(H56:L56) -> 0 | N56: =VLOOKUP($F56,'MP & Eqpt Summary 1'!$D$3:$AB$81,19,0) -> 0 | O56: =N56-M56 -> 0 | P56: 0 | Q56: =P56-N56 -> 0
A57: PUMP | B57: =B56+1 -> 55 | C57: E | D57: Dewatering Pump | E57: Day | F57: Dewatering Pump | G57: =VLOOKUP(F57,'MP & Eqpt Summary 1'!$D$3:$E$61,2,0) -> 0 | H57: =VLOOKUP($F57,'MP & Eqpt Summary 1'!$D$3:$AB$81,14,0) -> 0 | M57: =SUM(H57:L57) -> 0 | N57: =VLOOKUP($F57,'MP & Eqpt Summary 1'!$D$3:$AB$81,19,0) -> 0 | O57: =N57-M57 -> 0 | P57: 0 | Q57: =P57-N57 -> 0
... A59: WG | B59: =B58+1 -> 57 | C59: E | D59: Gen Wel | E59: Day | F59: Welding Generator | G59: =VLOOKUP(F59,'MP & Eqpt Summary 1'!$D$3:$E$61,2,0) -> 0 | H59: =VLOOKUP($F59,'MP & Eqpt Summary 1'!$D$3:$AB$81,14,0) -> 0 | M59: =SUM(H59:L59) -> 0 | N59: =VLOOKUP($F59,'MP & Eqpt Summary 1'!$D$3:$AB$81,19,0) -> 0 | O59: =N59-M59 -> 0 | P59: 0 | Q59: =P59-N59 -> 0
B60: =B59+1 -> 58 | C60: L | D60: CAR | E60: Day | F60: Carpenter E | G60: 5.9478872 | H60: =VLOOKUP($F60,'MP & Eqpt Summary 1'!$D$3:$AB$81,14,0) -> 0 | M60: =SUM(H60:L60) -> 0 | N60: =VLOOKUP($F60,'MP & Eqpt Summary 1'!$D$3:$AB$81,19,0) -> 0 | O60: =N60-M60 -> 0
B61: =B60+1 -> 59 | C61: L | D61: CAR | E61: Day | F61: Carpenter N | G61: 15.482557 | H61: =VLOOKUP($F61,'MP & Eqpt Summary 1'!$D$3:$AB$81,14,0) -> 0 | M61: =SUM(H61:L61) -> 0 | N61: =VLOOKUP($F61,'MP & Eqpt Summary 1'!$D$3:$AB$81,19,0) -> 0 | O61: =N61-M61 -> 0
B62: =B61+1 -> 60 | C62: L | D62: CH | E62: Day | F62: Chargehand | G62: 6.428108 | H62: =VLOOKUP($F62,'MP & Eqpt Summary 1'!$D$3:$AB$81,14,0) -> 0 | M62: =SUM(H62:L62) -> 0 | N62: =VLOOKUP($F62,'MP & Eqpt Summary 1'!$D$3:$AB$81,19,0) -> 0 | O62: =N62-M62 -> 0
B63: =B62+1 -> 61 | C63: L | D63: ELE | E63: Day | F63: Electrician | G63: 6.0114813 | H63: =VLOOKUP($F63,'MP & Eqpt Summary 1'!$D$3:$AB$81,14,0) -> 0 | M63: =SUM(H63:L63) -> 0 | N63: =VLOOKUP($F63,'MP & Eqpt Summary 1'!$D$3:$AB$81,19,0) -> 0 | O63: =N63-M63 -> 0
B64: =B63+1 -> 62 | C64: L | D64: HDD Ex | E64: Day | F64: Hdd Exp. | G64: =12.67 -> 12.67 | H64: =VLOOKUP($F64,'MP & Eqpt Summary 1'!$D$3:$AB$81,14,0) -> 0 | M64: =SUM(H64:L64) -> 0 | N64: =VLOOKUP($F64,'MP & Eqpt Summary 1'!$D$3:$AB$81,19,0) -> 0 | O64: =N64-M64 -> 0
B65: =B64+1 -> 63 | C65: L | D65: HDD Na | E65: Day | F65: Hdd Nat. | G65: =18.4935194297762 -> 18.493519 | H65: =VLOOKUP($F65,'MP & Eqpt Summary 1'!$D$3:$AB$81,14,0) -> 0 | M65: =SUM(H65:L65) -> 0 | N65: =VLOOKUP($F65,'MP & Eqpt Summary 1'!$D$3:$AB$81,19,0) -> 0 | O65: =N65-M65 -> 0
B66: =B65+1 -> 64 | C66: L | D66: HEL | E66: Day | F66: Helper E | G66: 5.8 | H66: =VLOOKUP($F66,'MP & Eqpt Summary 1'!$D$3:$AB$81,14,0) -> 0 | M66: =SUM(H66:L66) -> 0 | N66: =VLOOKUP($F66,'MP & Eqpt Summary 1'!$D$3:$AB$81,19,0) -> 0 | O66: =N66-M66 -> 0
B67: =B66+1 -> 65 | C67: L | D67: MAS | E67: Day | F67: Mason | G67: 5.8 | H67: =VLOOKUP($F67,'MP & Eqpt Summary 1'!$D$3:$AB$81,14,0) -> 0 | M67: =SUM(H67:L67) -> 0 | N67: =VLOOKUP($F67,'MP & Eqpt Summary 1'!$D$3:$AB$81,19,0) -> 0 | O67: =N67-M67 -> 0
B68: =B67+1 -> 66 | C68: L | D68: Hel Opt | E68: Day | F68: Helper/Optr | G68: 5.8 | M68: =SUM(H68:L68) -> 0 | O68: =N68-M68 -> 0
B69: =B68+1 -> 67 | C69: L | D69: OPT Ex | E69: Day | F69: Optr Exp. | G69: =11.64 -> 11.64 | H69: =VLOOKUP($F69,'MP & Eqpt Summary 1'!$D$3:$AB$81,14,0) -> 0 | M69: =SUM(H69:L69) -> 0 | N69: =VLOOKUP($F69,'MP & Eqpt Summary 1'!$D$3:$AB$81,19,0) -> 0 | O69: =N69-M69 -> 0
B70: =B69+1 -> 68 | C70: L | D70: OPT Na | E70: Day | F70: Optr Nat. | G70: 19.310987 | H70: =VLOOKUP($F70,'MP & Eqpt Summary 1'!$D$3:$AB$81,14,0) -> 0 | M70: =SUM(H70:L70) -> 0 | N70: =VLOOKUP($F70,'MP & Eqpt Summary 1'!$D$3:$AB$81,19,0) -> 0 | O70: =N70-M70 -> 0 | R70: =39+6 -> 45
B71: =B70+1 -> 69 | C71: L | D71: Rig | E71: Day | F71: Rigger | G71: 5.8 | H71: =VLOOKUP($F71,'MP & Eqpt Summary 1'!$D$3:$AB$81,14,0) -> 0 | M71: =SUM(H71:L71) -> 0 | N71: =VLOOKUP($F71,'MP & Eqpt Summary 1'!$D$3:$AB$81,19,0) -> 0 | O71: =N71-M71 -> 0 | R71: =R70-15 -> 30
B72: =B71+1 -> 70 | C72: L | D72: Stl Fix | E72: Day | F72: Steel Fixer E | G72: 5.9448082 | H72: =VLOOKUP($F72,'MP & Eqpt Summary 1'!$D$3:$AB$81,14,0) -> 0 | M72: =SUM(H72:L72) -> 0 | N72: =VLOOKUP($F72,'MP & Eqpt Summary 1'!$D$3:$AB$81,19,0) -> 0 | O72: =N72-M72 -> 0
B73: =B72+1 -> 71 | C73: L | D73: Stl Fix | E73: Day | F73: Steel Fixer N | G73: 17.482462 | H73: =VLOOKUP($F73,'MP & Eqpt Summary 1'!$D$3:$AB$81,14,0) -> 0 | M73: =SUM(H73:L73) -> 0 | N73: =VLOOKUP($F73,'MP & Eqpt Summary 1'!$D$3:$AB$81,19,0) -> 0 | O73: =N73-M73 -> 0
B74: =B73+1 -> 72 | C74: L | D74: WEL | E74: Day | F74: Welder | G74: 5.8645643 | H74: =VLOOKUP($F74,'MP & Eqpt Summary 1'!$D$3:$AB$81,14,0) -> 0 | M74: =SUM(H74:L74) -> 0 | N74: =VLOOKUP($F74,'MP & Eqpt Summary 1'!$D$3:$AB$81,19,0) -> 0 | O74: =N74-M74 -> 0
B75: =B74+1 -> 73 | C75: L | D75: MEC | E75: Day | F75: Mechanic | G75: 7.5 | H75: =VLOOKUP($F75,'MP & Eqpt Summary 1'!$D$3:$AB$81,14,0) -> 0 | M75: =SUM(H75:L75) -> 0 | N75: =VLOOKUP($F75,'MP & Eqpt Summary 1'!$D$3:$AB$81,19,0) -> 0 | O75: =N75-M75 -> 0
B76: =B75+1 -> 74 | C76: L | D76: PLU | E76: Day | F76: Plumber | G76: 6.3920933 | H76: =VLOOKUP($F76,'MP & Eqpt Summary 1'!$D$3:$AB$81,14,0) -> 0 | M76: =SUM(H76:L76) -> 0 | N76: =VLOOKUP($F76,'MP & Eqpt Summary 1'!$D$3:$AB$81,19,0) -> 0 | O76: =N76-M76 -> 0
B77: =B76+1 -> 75 | C77: L | D77: Watchman | E77: Day | F77: Watchman | G77: 16.243812 | H77: =VLOOKUP($F77,'MP & Eqpt Summary 1'!$D$3:$AB$81,14,0) -> 0 | M77: =SUM(H77:L77) -> 0 | N77: =VLOOKUP($F77,'MP & Eqpt Summary 1'!$D$3:$AB$81,19,0) -> 0 | O77: =N77-M77 -> 0
B78: =B77+1 -> 76 | C78: L | D78: LDD Na | E78: Day | F78: Ldd Nat. | G78: =16.6013839453948 -> 16.601384 | H78: =VLOOKUP($F78,'MP & Eqpt Summary 1'!$D$3:$AB$81,14,0) -> 0 | M78: =SUM(H78:L78) -> 0 | N78: =VLOOKUP($F78,'MP & Eqpt Summary 1'!$D$3:$AB$81,19,0) -> 0 | O78: =N78-M78 -> 0
B79: =B78+1 -> 77 | C79: S | D79: Staff | E79: Day | F79: PD | G79: 139 | M79: =SUM(M60:M78) -> 0 | N79: =SUM(N60:N78) -> 0
B80: =B79+1 -> 78 | C80: S | D80: Staff | E80: Day | F80: SPM | G80: 102.61
B81: =B80+1 -> 79 | C81: S | D81: Staff | E81: Day | F81: DQM/DCM/DPM/DMM | G81: 52.41
B82: =B81+1 -> 80 | C82: S | D82: Staff | E82: Day | F82: Planning Enginner | G82: 37.64
B83: =B82+1 -> 81 | C83: S | D83: Staff | E83: Day | F83: Engineer (Se/Mel/De) | G83: 35.8
B84: =B83+1 -> 82 | C84: S | D84: Staff | E84: Day | F84: Quantity Surveyor | G84: 33.85
B85: =B84+1 -> 83 | C85: S | D85: Staff | E85: Day | F85: Supervisor | G85: 19.38
B86: =B85+1 -> 84 | C86: S | D86: Staff | E86: Day | F86: Foreman | G86: 19.38
B87: =B86+1 -> 85 | C87: S | D87: Staff | E87: Day | F87: Lans Surveyor | G87: 25.83
B88: =B87+1 -> 86 | C88: S | D88: Staff | E88: Day | F88: Qaqc Engineer | G88: 35.61
B89: =B88+1 -> 87 | C89: S | D89: Staff | E89: Day | F89: Hse Advisor | G89: 35.61 | J89: =11+4 -> 15 | O89: Per Day
B90: =B89+1 -> 88 | C90: S | D90: Staff | E90: Day | F90: Male Nurse | G90: 19.73 | O90: =2500/26 -> 96.153846
B91: =B90+1 -> 89 | C91: S | D91: Staff | E91: Day | F91: Store Keeper | G91: 18.55
B92: =B91+1 -> 90 | C92: S | D92: Staff | E92: Day | F92: Sec/Deo | G92: 18.48
B93: =B92+1 -> 91 | C93: S | D93: Staff | E93: Day | F93: Sec/Deo - N | G93: 0
B94: =B93+1 -> 92 | C94: S | D94: Staff | E94: Day | F94: Camp Boss - Ex | G94: 18.52
B95: =B94+1 -> 93 | C95: S | D95: Staff | E95: Day | F95: Camp Boss - N | G95: 21.87
B96: =B95+1 -> 94 | C96: S | D96: Staff | E96: Day | F96: Tco - Ex | G96: 11.44
B97: =B96+1 -> 95 | C97: S | D97: Staff | E97: Day | F97: Tco - N | G97: 21.611
B98: =B97+1 -> 96 | C98: S | D98: Staff | E98: Day | F98: Draughtsman - Ex | G98: 26.83
B99: =B98+1 -> 97 | C99: S | D99: Staff | E99: Day | F99: Draughtsman - N | G99: 21.733333
B100: =B99+1 -> 98 | C100: S | D100: Staff | E100: Day | F100: Pro | G100: 27.204
B101: =B100+1 -> 99 | C101: S | D101: Staff | E101: Day | F101: Lab Technician - Ex | G101: 17.27
B102: =B101+1 -> 100 | C102: S | D102: Staff | E102: Day | F102: Lab Technician - N | G102: 0
B103: =B102+1 -> 101 | C103: SC | D103: 1501 | E103: linm | F103: Street lighting cables; trench depth 700 mm x width 300 mm | G103: 2.841
B104: =B103+1 -> 102 | C104: SC | D104: 1501FS | E104: linm | F104: Street lighting cables; trench depth 700 mm x width 300 mm | G104: 2.089
...

Sheet Sheet2
N1: As on | O1: ='Summary-Financial'!AB2 -> xxxx
N2: Time Elapsed | O2: 1
N3: Progress Achieved | O3: 0.9670153 | S3: 38.19
A4: 6155_Dualization of Barka Nakhal Road Project | N4: Shortfall | O4: =O3-O2 -> -0.032984705
A5: Cumulative | R5: As on Date (Planned) % | S5: Diff
A6: Sl No | B6: PM/CM | C6: As on Date Planned amount | D6: As on Date Planned prelims | E6: As on Date Planned Total | F6: Achieved Amount to date | G6: Prelims Income | H6: Achieved Amount to date (Incl Prelims) | I6: % Achieved | J6: Cost | K6: Prelims Cost | L6: Cost to date including prelims | M6: % of Cost | N6: Contribution | O6: Contribution % | P6: Indicate | Q6: As on Date Planned Contribution
A7: 1 | B7: T Swamy | C7: =C9+C11+C12+C13+C14+C16+C8+C15 -> 296173.75 | D7: =$F$31*M7 -> #REF! | E7: =C7+D7 -> #REF! | F7: =F9+F10+F11+F12+F16+F8+F15 -> #REF! | G7: =$F$31*M7 -> #REF! | H7: =H9+H10+H11+H12+H16+H8+H15 -> #REF! | I7: =H7/E7 -> #REF! | J7: =J9+J10+J11+J12+J16+J8+J15 -> #REF! | K7: =K9+K10+K11+K12+K16+K8+K15 -> #REF! | L7: =SUM(J7:K7) -> #REF! | M7: =J7/$J$30 -> #REF! | N7: =IFERROR(H7-L7,"") | O7: =IFERROR(N7/H7,"") | P7: =IF(N7>=1,"Profit","Loss") -> Profit | R7: =-4.15%/26*23 -> -0.036711538 | S7: =O7-R7 -> #VALUE!
A8: a | B8: Prelims Others | C8: 58423.962 | D8: =$F$31*M8 -> #REF! | E8: =C8+D8 -> #REF! | F8: =#REF! -> #REF! | G8: =$F$31*M8 -> #REF! | H8: =SUM(F8:G8) -> #REF! | I8: =H8/E8 -> #REF! | J8: =#REF! -> #REF! | K8: =$J$31*M8 -> #REF! | L8: =SUM(J8:K8) -> #REF! | M8: =J8/$J$30 -> #REF! | N8: =IFERROR(H8-L8,"") | O8: =IFERROR(N8/H8,"") | P8: =IF(N8>=1,"Profit","Loss") -> Profit | S8: =O8-R8 -> #VALUE!
A9: b | B9: Manoj | C9: 180252.24 | D9: =$F$31*M9 -> #REF! | E9: =C9+D9 -> #REF! | F9: =#REF!+F14+F13 -> #REF! | G9: =$F$31*M9 -> #REF! | H9: =SUM(F9:G9) -> #REF! | I9: =H9/E9 -> #REF! | J9: =#REF!+J14+J13-5500 -> #REF! | K9: =$J$31*M9 -> #REF! | L9: =SUM(J9:K9) -> #REF! | M9: =J9/$J$30 -> #REF! | N9: =IFERROR(H9-L9,"") | O9: =IFERROR(N9/H9,"") | P9: =IF(N9>=1,"Profit","Loss") -> Profit | Q9: =(15992/27*20)+(3834/27*20)+(28854/27*20)+Q14+(Q13*0.1) -> -14348.444 | R9: =-3%/26*23 -> -0.026538462 | S9: =O9-R9 -> #VALUE!
A10: c | B10: Nassar/Essa | C10: 0 | D10: =$F$31*M10 -> #REF! | E10: =C10+D10 -> #REF! | F10: ='Summary-Financial'!F10 -> 0 | G10: =$F$31*M10 -> #REF! | H10: =SUM(F10:G10) -> #REF! | I10: =H10/E10 -> #REF! | J10: ='Summary-Financial'!I10 -> #REF! | K10: =$J$31*M10 -> #REF! | L10: =SUM(J10:K10) -> #REF! | M10: =J10/$J$30 -> #REF! | N10: =IFERROR(H10-L10,"") | O10: =IFERROR(N10/H10,"") | P10: =IF(N10>=1,"Profit","Loss") -> Profit
A11: d | B11: Liju | C11: 14297.5 | D11: =$F$31*M11 -> #REF! | E11: =C11+D11 -> #REF! | F11: =#REF! -> #REF! | G11: =$F$31*M11 -> #REF! | H11: =SUM(F11:G11) -> #REF! | I11: =H11/E11 -> #REF! | J11: =#REF! -> #REF! | K11: =$J$31*M11 -> #REF! | L11: =SUM(J11:K11) -> #REF! | M11: =J11/$J$30 -> #REF! | N11: =IFERROR(H11-L11,"") | O11: =IFERROR(N11/H11,"") | P11: =IF(N11>=1,"Profit","Loss") -> Profit | Q11: =618/27*20 -> 457.77778 | R11: =8%/26*23 -> 0.070769231 | S11: =O11-R11 -> #VALUE!
A12: e | B12: Anish | C12: 37809.115 | D12: =$F$31*M12 -> #REF! | E12: =C12+D12 -> #REF! | F12: =#REF! -> #REF! | G12: =$F$31*M12 -> #REF! | H12: =SUM(F12:G12) -> #REF! | I12: =H12/E12 -> #REF! | J12: =#REF! -> #REF! | K12: =$J$31*M12 -> #REF! | L12: =SUM(J12:K12) -> #REF! | M12: =J12/$J$30 -> #REF! | N12: =IFERROR(H12-L12,"") | O12: =IFERROR(N12/H12,"") | P12: =IF(N12>=1,"Profit","Loss") -> Profit | Q12: =14459/27*20 -> 10710.37 | R12: =30%/26*23 -> 0.26538462 | S12: =O12-R12 -> #VALUE!
A13: f | B13: Reji/Kishor | D13: =$F$31*M13 -> #REF! | E13: =C13+D13 -> #REF! | F13: =#REF! -> #REF! | G13: =$F$31*M13 -> #REF! | H13: =SUM(F13:G13) -> #REF! | J13: =#REF! -> #REF! | K13: =$J$31*M13 -> #REF! | L13: =SUM(J13:K13) -> #REF! | M13: =J13/$J$30 -> #REF! | N13: =IFERROR(H13-L13,"") | O13: =IFERROR(N13/H13,"") | P13: =IF(N13>=1,"Profit","Loss") -> Profit | Q13: =-61864/27*20 -> -45825.185 | S13: =O13-R13 -> #VALUE!
A14: g | B14: Mustafiz/Krishna | D14: =$F$31*M14 -> #REF! | E14: =C14+D14 -> #REF! | F14: =#REF! -> #REF! | G14: =$F$31*M14 -> #REF! | H14: =SUM(F14:G14) -> #REF! | J14: =#REF!+10000 -> #REF! | K14: =$J$31*M14 -> #REF! | L14: =SUM(J14:K14) -> #REF! | M14: =J14/$J$30 -> #REF! | N14: =IFERROR(H14-L14,"") | O14: =IFERROR(N14/H14,"") | P14: =IF(N14>=1,"Profit","Loss") -> Profit | Q14: =-61864/27*20 -> -45825.185 | S14: =O14-R14 -> #VALUE!
A15: h | B15: Static Crusher | D15: =$F$31*M15 -> #REF! | E15: =C15+D15 -> #REF! | F15: ='Summary-Financial'!F15 -> #REF! | G15: =$F$31*M15 -> #REF! | H15: =SUM(F15:G15) -> #REF! | I15: =H15/E15 -> #REF! | J15: =#REF! -> #REF! | K15: =$J$31*M15 -> #REF! | L15: =SUM(J15:K15) -> #REF! | M15: =J15/$J$30 -> #REF! | N15: =IFERROR(H15-L15,"") | O15: =IFERROR(N15/H15,"") | P15: =IF(N15>=1,"Profit","Loss") -> Profit | S15: =O15-R15 -> #VALUE!
A16: i | B16: Saiful Islam | C16: 5390.9308 | D16: =$F$31*M16 -> #REF! | E16: =C16+D16 -> #REF! | F16: =#REF! -> #REF! | G16: =$F$31*M16 -> #REF! | H16: =SUM(F16:G16) -> #REF! | I16: =H16/E16 -> #REF! | J16: =#REF! -> #REF! | K16: =$J$31*M16 -> #REF! | L16: =SUM(J16:K16) -> #REF! | M16: =J16/$J$30 -> #REF! | N16: =IFERROR(H16-L16,"") | O16: =IFERROR(N16/H16,"") | P16: =IF(N16>=1,"Profit","Loss") -> Profit | Q16: =5543/27*20 -> 4105.9259 | R16: 0 | S16: =O16-R16 -> #VALUE!
A17: 2 | B17: A K Singh | C17: =C18+C19+C20+C21+C22 -> 187836.08 | D17: =$F$31*M17 -> #REF! | E17: =C17+D17 -> #REF! | F17: =F18+F19+F20+F21+F22 -> #REF! | G17: =G18+G19+G20+G21+G22 -> #REF! | H17: =SUM(F17:G17) -> #REF! | I17: =H17/E17 -> #REF! | J17: =J18+J19+J20+J21+J22 -> #REF! | K17: =$J$31*M17 -> #REF! | L17: =SUM(J17:K17) -> #REF! | M17: =J17/$J$30 -> #REF! | N17: =IFERROR(H17-L17,"") | O17: =IFERROR(N17/H17,"") | P17: =IF(N17>=1,"Profit","Loss") -> Profit | R17: =8.14%/26*23 -> 0.072007692 | S17: =O17-R17 -> #VALUE!
A18: a | B18: Paul | C18: 52902.233 | D18: =$F$31*M18 -> #REF! | E18: =C18+D18 -> #REF! | F18: =#REF! -> #REF! | G18: =$F$31*M18 -> #REF! | H18: =SUM(F18:G18) -> #REF! | I18: =H18/E18 -> #REF! | J18: =#REF! -> #REF! | K18: =$J$31*M18 -> #REF! | L18: =SUM(J18:K18) -> #REF! | M18: =J18/$J$30 -> #REF! | N18: =IFERROR(H18-L18,"") | O18: =IFERROR(N18/H18,"") | P18: =IF(N18>=1,"Profit","Loss") -> Profit | Q18: =36214/27*20 -> 26825.185 | R18: =11%/26*23 -> 0.097307692 | S18: =O18-R18 -> #VALUE!
A19: b | B19: Santhosh | C19: 0 | D19: =$F$31*M19 -> #REF! | E19: =C19+D19 -> #REF! | F19: =#REF! -> #REF! | G19: =$F$31*M19 -> #REF! | H19: =SUM(F19:G19) -> #REF! | I19: =H19/E19 -> #REF! | J19: =#REF! -> #REF! | K19: =$J$31*M19 -> #REF! | L19: =SUM(J19:K19) -> #REF! | M19: =J19/$J$30 -> #REF! | N19: =IFERROR(H19-L19,"") | O19: =IFERROR(N19/H19,"") | P19: =IF(N19>=1,"Profit","Loss") -> Profit | Q19: =6836/27*20 -> 5063.7037 | R19: =5%/26*10 -> 0.019230769 | S19: =O19-R19 -> #VALUE!
A20: c | B20: Waqas | C20: 30701.445 | D20: =$F$31*M20 -> #REF! | E20: =C20+D20 -> #REF! | F20: =#REF! -> #REF! | G20: =$F$31*M20 -> #REF! | H20: =SUM(F20:G20) -> #REF! | I20: =H20/E20 -> #REF! | J20: =#REF! -> #REF! | K20: =$J$31*M20 -> #REF! | L20: =SUM(J20:K20) -> #REF! | M20: =J20/$J$30 -> #REF! | N20: =IFERROR(H20-L20,"") | O20: =IFERROR(N20/H20,"") | P20: =IF(N20>=1,"Profit","Loss") -> Profit | Q20: =8633/27*20 -> 6394.8148 | R20: =5%/26*23 -> 0.044230769 | S20: =O20-R20 -> #VALUE!
A21: d | B21: Joynal | C21: 71310.583 | D21: =$F$31*M21 -> #REF! | E21: =C21+D21 -> #REF! | F21: =#REF! -> #REF! | G21: =$F$31*M21 -> #REF! | H21: =SUM(F21:G21) -> #REF! | I21: =H21/E21 -> #REF! | J21: =#REF!+10000 -> #REF! | K21: =$J$31*M21 -> #REF! | L21: =SUM(J21:K21) -> #REF! | M21: =J21/$J$30 -> #REF! | N21: =IFERROR(H21-L21,"") | O21: =IFERROR(N21/H21,"") | P21: =IF(N21>=1,"Profit","Loss") -> Profit | Q21: =9971/27*20 -> 7385.9259 | R21: =8%/26*23 -> 0.070769231 | S21: =O21-R21 -> #VALUE!
A22: e | B22: Baskar | C22: 32921.824 | D22: =$F$31*M22 -> #REF! | E22: =C22+D22 -> #REF! | F22: =#REF! -> #REF! | G22: =$F$31*M22 -> #REF! | H22: =SUM(F22:G22) -> #REF! | I22: =H22/E22 -> #REF! | J22: =#REF!+5000 -> #REF! | K22: =$J$31*M22 -> #REF! | L22: =SUM(J22:K22) -> #REF! | M22: =J22/$J$30 -> #REF! | N22: =IFERROR(H22-L22,"") | O22: =IFERROR(N22/H22,"") | P22: =IF(N22>=1,"Profit","Loss") -> Profit | Q22: =11498/27*20 -> 8517.037 | R22: =11%/26*23 -> 0.097307692 | S22: =O22-R22 -> #VALUE!
A23: =A17+1 -> 3 | B23: A Nagarajan | C23: =C28+C25 -> 31886.022 | D23: =D25+D27+D28 -> #REF! | E23: =C23+D23 -> #REF! | F23: =F25+F27+F28 -> #REF! | G23: =$F$31*M23 -> #REF! | H23: =SUM(F23:G23) -> #REF! | I23: =H23/E23 -> #REF! | J23: =J28+J25+J27 -> #REF! | K23: =$J$31*M23 -> #REF! | L23: =SUM(J23:K23) -> #REF! | M23: =J23/$J$30 -> #REF! | N23: =IFERROR(H23-L23,"") | O23: =IFERROR(N23/H23,"") | P23: =IF(N23>=1,"Profit","Loss") -> Profit | R23: =2%/26*23 -> 0.017692308 | S23: =O23-R23 -> #VALUE!
A24: a | B24: Jithendra | C24: 22712.885 | D24: =$F$31*M24 -> #REF! | E24: =C24+D24 -> #REF! | F24: =#REF! -> #REF! | G24: =$F$31*M24 -> #REF! | H24: =SUM(F24:G24) -> #REF! | I24: =H24/E24 -> #REF! | J24: =#REF! -> #REF! | K24: =$J$31*M24 -> #REF! | L24: =SUM(J24:K24) -> #REF! | M24: =J24/$J$30 -> #REF! | N24: =IFERROR(H24-L24,"") | O24: =IFERROR(N24/H24,"") | P24: =IF(N24>=1,"Profit","Loss") -> Profit | Q24: =21590/27*20 -> 15992.593 | R24: =23%/26*16 -> 0.14153846 | S24: =O24-R24 -> #VALUE!
A25: b | B25: Mukesh Chabra | C25: 9173.1369 | D25: =$F$31*M25 -> #REF! | E25: =C25+D25 -> #REF! | F25: ='Summary-Financial'!F25 -> #REF! | G25: =$F$31*M25 -> #REF! | H25: =SUM(F25:G25) -> #REF! | I25: =H25/E25 -> #REF! | J25: ='Summary-Financial'!I25 -> #REF! | K25: =$J$31*M25 -> #REF! | L25: =SUM(J25:K25) -> #REF! | M25: =J25/$J$30 -> #REF! | N25: =IFERROR(H25-L25,"") | O25: =IFERROR(N25/H25,"") | P25: =IF(N25>=1,"Profit","Loss") -> Profit | R25: =38%/26*23 -> 0.33615385 | S25: =O25-R25 -> #VALUE!
A26: c | B26: Nassar/Essa | C26: 0 | D26: =$F$31*M26 -> #REF! | E26: =C26+D26 -> #REF! | F26: ='Summary-Financial'!F26 -> #REF! | G26: =$F$31*M26 -> #REF! | H26: =SUM(F26:G26) -> #REF! | I26: =H26/E26 -> #REF! | J26: ='Summary-Financial'!I26 -> #REF! | K26: =$J$31*M26 -> #REF! | L26: =SUM(J26:K26) -> #REF! | M26: =J26/$J$30 -> #REF! | N26: =IFERROR(H26-L26,"") | O26: =IFERROR(N26/H26,"") | P26: =IF(N26>=1,"Profit","Loss") -> Profit
A27: d | B27: Jayan | C27: 159189.14 | D27: =$F$31*M27+D26 -> #REF! | E27: =C27+D27 -> #REF! | F27: ='Summary-Financial'!F27+F26 -> #REF! | G27: =$F$31*M27 -> #REF! | H27: =SUM(F27:G27) -> #REF! | I27: =H27/E27 -> #REF! | J27: ='Summary-Financial'!I27+J26 -> #REF! | K27: =$J$31*M27 -> #REF! | L27: =SUM(J27:K27) -> #REF! | M27: =J27/$J$30 -> #REF! | N27: =IFERROR(H27-L27,"") | O27: =IFERROR(N27/H27,"") | P27: =IF(N27>=1,"Profit","Loss") -> Profit
A28: e | B28: Mohan | C28: =0+C24 -> 22712.885 | D28: =$F$31*M28+D24 -> #REF! | E28: =C28+D28 -> #REF! | F28: =#REF!+F24 -> #REF! | G28: =$F$31*M28 -> #REF! | H28: =SUM(F28:G28) -> #REF! | I28: =H28/E28 -> #REF! | J28: =#REF!+J24 -> #REF! | K28: =$J$31*M28 -> #REF! | L28: =SUM(J28:K28) -> #REF! | M28: =J28/$J$30 -> #REF! | N28: =IFERROR(H28-L28,"") | O28: =IFERROR(N28/H28,"") | P28: =IF(N28>=1,"Profit","Loss") -> Profit | Q28: =-134/27*20 -> -99.259259 | R28: =-2%/26*23 -> -0.017692308 | S28: =O28-R28 -> #VALUE!
S29: 0
A30: Total | C30: =C23+C17+C7+C15 -> 515895.86 | F30: =F23+F17+F7 -> #REF! | G30: =G23+G17+G7 -> #REF! | H30: =H23+H17+H7 -> #REF! | J30: =J23+J17+J7 -> #REF! | K30: =K23+K17+K7 -> #REF! | L30: =L23+L17+L7 -> #REF! | M30: =J30/$J$30 -> #REF! | N30: =H30-L30 -> #REF! | O30: =IFERROR(N30/SUM(H30),0) -> 0 | P30: =IF(N30>=1,"Profit","Loss") -> #REF! | S30: =O30-R30 -> 0
A31: 1 | B31: Prelims | C31: =F31 -> 0 | F31: =PRE!I74 -> 0 | J31: =PRE!I75 -> 0 | N31: =F31-J31 -> 0 | O31: =IFERROR(N31/F31,0) -> 0 | P31: =IF(N31>=1,"Profit","Loss") -> Loss | Q31: =-61361/27*20 -> -45452.593 | R31: 0
A33: Sub Contractor
A34: 1 | B34: Sub contractor | C34: 120486.41 | F34: =DPR!N205+DPR!N206 -> 0 | H34: =F34 -> 0 | J34: =#REF!+#REF!+#REF!+#REF! -> #REF! | L34: =J34 -> #REF! | N34: =F34-L34 -> #REF! | O34: =IFERROR(N34/H34,0) -> 0 | P34: =IF(N34>=1,"Profit","Loss") -> #REF! | Q34: =23416/27*20 -> 17345.185 | R34: 0 | S34: =O34-R34 -> 0
A35: 2 | B35: PCT | C35: =DPR!H208+DPR!H209+DPR!H210 -> 0 | F35: =DPR!N208+DPR!#REF! -> #REF! | H35: =F35 -> #REF! | J35: =#REF!+#REF! -> #REF! | L35: =J35 -> #REF! | N35: =F35-L35 -> #REF! | O35: =IFERROR(N35/H35,0) -> 0 | P35: =IF(N35>=1,"Profit","Loss") -> #REF! | S35: =O35-R35 -> 0
A36: 3 | B36: Bahwan | C36: 0 | F36: =DPR!N207 -> 0 | H36: =F36 -> 0 | J36: =#REF! -> #REF! | L36: =J36 -> #REF! | N36: =F36-L36 -> #REF! | O36: =IFERROR(N36/F36,0) -> 0 | P36: =IF(N36>=1,"Profit","Loss") -> #REF! | S36: =O36-R36 -> 0
A38: Grand Total | C38: =C30+C31+C34 -> 636382.27 | F38: =F30+F31+F34+F36 -> #REF! | H38: =H30+H31+H34+H36 -> #REF! | J38: =J30+J31+J34+J36 -> #REF! | L38: =L30+L31+L34+L36 -> #REF! | N38: =H38-L38 -> #REF! | O38: =IFERROR(N38/H38,0) -> 0 | P38: =IF(N38>=1,"Profit","Loss") -> #REF! | Q38: =Q34+Q31+Q28+Q24+Q22+Q21+Q20+Q19+Q18+Q16+Q12+Q11+Q10+Q9 -> 42898.222 | R38: =2.5%/26*23 -> 0.022115385 | S38: =O38-R38 -> -0.022115385
F41: =F38-F15 -> #REF!
F43: 1616216.6

Sheet Summary-Financial
AC1: 42767 | AF1: Fuel taken | AG1: ='Summary-Financial (NEW)'!AH1 -> 0.4911
AA2: As on | AB2: ='Summary-Financial (NEW)'!AC2 -> xxxx | AC2: =EOMONTH(AB2,0) -> #VALUE! | AD2: 26 | AE2: 26
AA3: Time Elapsed | AB3: =AD2/AE2 -> 1
C4: 6155_Dualization of Barka Nakhal Road Project
C5: Cumulative | R5: For the Day
C6: Sl No | D6: PM/CM | E6: Projection Amount | F6: Achieved Amount to date | G6: Prelims Income | H6: Achieved Amount to date (Incl Prelims) | I6: Cost | J6: Prelims Cost | K6: Cost to date including prelims | L6: % of Cost | M6: % of Income | N6: Contribution | O6: Contribution % | P6: Indicate | R6: Achieved Amount to date | S6: Prelims Income | T6: Bahwan Income | U6: Achieved Amount to date (Incl Prelims) | V6: Cost | W6: Prelims Cost | X6: Cost to date including prelims | Y6: % of Cost | Z6: Contribution | AA6: Contribution % | AB6: Indicate
C7: 1 | D7: T Swamy | E7: =E9+E11+E12+E16+E8 -> #REF! | F7: =F9+F11+F12+F16+F8 -> #REF! | G7: =$F$31*L7 -> #REF! | H7: =H9+H10+H11+H12+H16+H8+H15 -> #REF! | I7: =I9+I10+I11+I12+I16+I8+I15 -> #REF! | J7: =J9+J10+J11+J12+J16+J8+J15 -> #REF! | K7: =SUM(I7:J7) -> #REF! | L7: =I7/$I$30 -> #REF! | M7: =H7/$H$30 -> #REF! | N7: =IFERROR(H7-K7,"") | O7: =IFERROR(N7/H7,"") | P7: =IF(N7>=1,"Profit","Loss") -> Profit | R7: =R9+R10+R11+R12+R16+R8+R15 -> #REF! | S7: =$R$31*Y7 -> #REF! | U7: =SUM(R7:S7) -> #REF! | V7: =V9+V10+V11+V12+V16+V8+V15 -> #REF! | W7: =$V$31*Y7 -> #REF! | X7: =SUM(V7:W7) -> #REF! | Y7: =V7/$V$30 -> #REF! | Z7: =IFERROR(U7-X7,"") | AA7: =IFERROR(Z7/U7,"") | AB7: =IF(Z7>=1,"Profit","Loss") -> Profit | AC7: =F7+H7 -> #REF!
C8: a | D8: Prelims Others | E8: =#REF! -> #REF! | F8: =#REF! -> #REF! | G8: =$F$31*L8 -> #REF! | H8: =SUM(F8:G8) -> #REF! | I8: =#REF! -> #REF! | J8: =$I$31*L8 -> #REF! | K8: =SUM(I8:J8) -> #REF! | L8: =I8/$I$30 -> #REF! | N8: =IFERROR(H8-K8,"") | O8: =IFERROR(N8/H8,"") | P8: =IF(N8>=1,"Profit","Loss") -> Profit | R8: =#REF! -> #REF! | S8: =$R$31*Y8 -> #REF! | U8: =SUM(R8:S8) -> #REF! | V8: =#REF! -> #REF! | W8: =$V$31*Y8 -> #REF! | X8: =SUM(V8:W8) -> #REF! | Y8: =V8/$V$30 -> #REF! | Z8: =IFERROR(U8-X8,"") | AA8: =IFERROR(Z8/U8,"") | AB8: =IF(Z8>=1,"Profit","Loss") -> Profit
C9: b | D9: Manoj | E9: 404132.66 | F9: =#REF!+F14+(F13*0.1) -> #REF! | G9: =$F$31*L9 -> #REF! | H9: =SUM(F9:G9) -> #REF! | I9: =#REF!+I14+(I13*0.1) -> #REF! | J9: =$I$31*L9-3000 -> #REF! | K9: =SUM(I9:J9) -> #REF! | L9: =I9/$I$30 -> #REF! | N9: =IFERROR(H9-K9,"") | O9: =IFERROR(N9/H9,"") | P9: =IF(N9>=1,"Profit","Loss") -> Profit | R9: =#REF!+R14+(R13*0.1) -> #REF! | S9: =$R$31*Y9 -> #REF! | U9: =SUM(R9:S9) -> #REF! | V9: =#REF!+V14+(V13*0.1) -> #REF! | W9: =$V$31*Y9 -> #REF! | X9: =SUM(V9:W9) -> #REF! | Y9: =V9/$V$30 -> #REF! | Z9: =IFERROR(U9-X9,"") | AA9: =IFERROR(Z9/U9,"") | AB9: =IF(Z9>=1,"Profit","Loss") -> Profit
C10: c | D10: Nassar/essa | E10: =#REF! -> #REF! | G10: =$F$31*L10 -> #REF! | I10: =#REF! -> #REF! | J10: =$I$31*L10 -> #REF! | K10: =SUM(I10:J10) -> #REF! | L10: =I10/$I$30 -> #REF! | N10: =IFERROR(H10-K10,"") | O10: =IFERROR(N10/H10,"") | P10: =IF(N10>=1,"Profit","Loss") -> Profit
C11: d | D11: Liju | E11: 13456.17 | F11: =#REF! -> #REF! | G11: =$F$31*L11 -> #REF! | H11: =SUM(F11:G11) -> #REF! | I11: =#REF! -> #REF! | J11: =$I$31*L11 -> #REF! | K11: =SUM(I11:J11) -> #REF! | L11: =I11/$I$30 -> #REF! | N11: =IFERROR(H11-K11,"") | O11: =IFERROR(N11/H11,"") | P11: =IF(N11>=1,"Profit","Loss") -> Profit | R11: =#REF! -> #REF! | S11: =$R$31*Y11 -> #REF! | U11: =SUM(R11:S11) -> #REF! | V11: =#REF! -> #REF! | W11: =$V$31*Y11 -> #REF! | X11: =SUM(V11:W11) -> #REF! | Y11: =V11/$V$30 -> #REF! | Z11: =IFERROR(U11-X11,"") | AA11: =IFERROR(Z11/U11,"") | AB11: =IF(Z11>=1,"Profit","Loss") -> Profit
C12: e | D12: Anish | E12: 89367 | F12: =#REF! -> #REF! | G12: =$F$31*L12 -> #REF! | H12: =SUM(F12:G12) -> #REF! | I12: =#REF! -> #REF! | J12: =$I$31*L12 -> #REF! | K12: =SUM(I12:J12) -> #REF! | L12: =I12/$I$30 -> #REF! | N12: =IFERROR(H12-K12,"") | O12: =IFERROR(N12/H12,"") | P12: =IF(N12>=1,"Profit","Loss") -> Profit | R12: =#REF! -> #REF! | S12: =$R$31*Y12 -> #REF! | U12: =SUM(R12:S12) -> #REF! | V12: =#REF! -> #REF! | W12: =$V$31*Y12 -> #REF! | X12: =SUM(V12:W12) -> #REF! | Y12: =V12/$V$30 -> #REF! | Z12: =IFERROR(U12-X12,"") | AA12: =IFERROR(Z12/U12,"") | AB12: =IF(Z12>=1,"Profit","Loss") -> Profit
C13: f | D13: Reji/Kishor | E13: - | F13: =#REF! -> #REF! | G13: =$F$31*L13 -> #REF! | H13: =SUM(F13:G13) -> #REF! | I13: =#REF! -> #REF! | J13: =$I$31*L13 -> #REF! | K13: =SUM(I13:J13) -> #REF! | L13: =I13/$I$30 -> #REF! | N13: =IFERROR(H13-K13,"") | O13: =IFERROR(N13/H13,"") | P13: =IF(N13>=1,"Profit","Loss") -> Profit | R13: =#REF! -> #REF! | S13: =$R$31*Y13 -> #REF! | U13: =SUM(R13:S13) -> #REF! | V13: =#REF! -> #REF! | W13: =$V$31*Y13 -> #REF! | X13: =SUM(V13:W13) -> #REF! | Y13: =V13/$V$30 -> #REF! | Z13: =IFERROR(U13-X13,"") | AA13: =IFERROR(Z13/U13,"") | AB13: =IF(Z13>=1,"Profit","Loss") -> Profit
C14: g | D14: Mustafiz/Krishna | E14: - | F14: =#REF! -> #REF! | G14: =$F$31*L14 -> #REF! | H14: =SUM(F14:G14) -> #REF! | I14: =#REF! -> #REF! | J14: =$I$31*L14 -> #REF! | K14: =SUM(I14:J14) -> #REF! | L14: =I14/$I$30 -> #REF! | N14: =IFERROR(H14-K14,"") | O14: =IFERROR(N14/H14,"") | P14: =IF(N14>=1,"Profit","Loss") -> Profit | R14: =#REF! -> #REF! | S14: =$R$31*Y14 -> #REF! | U14: =SUM(R14:S14) -> #REF! | V14: =#REF! -> #REF! | W14: =$V$31*Y14 -> #REF! | X14: =SUM(V14:W14) -> #REF! | Y14: =V14/$V$30 -> #REF! | Z14: =IFERROR(U14-X14,"") | AA14: =IFERROR(Z14/U14,"") | AB14: =IF(Z14>=1,"Profit","Loss") -> Profit
C15: h | D15: Static Crusher | F15: =#REF! -> #REF! | G15: =$F$31*L15 -> #REF! | H15: =SUM(F15:G15) -> #REF! | I15: =#REF! -> #REF! | J15: =$I$31*L15 -> #REF! | K15: =SUM(I15:J15) -> #REF! | L15: =I15/$I$30 -> #REF! | N15: =IFERROR(H15-K15,"") | O15: =IFERROR(N15/H15,"") | P15: =IF(N15>=1,"Profit","Loss") -> Profit | R15: =#REF! -> #REF! | S15: =$R$31*Y15 -> #REF! | U15: =SUM(R15:S15) -> #REF! | V15: =#REF! -> #REF! | W15: =$V$31*Y15 -> #REF! | X15: =SUM(V15:W15) -> #REF! | Y15: =V15/$V$30 -> #REF! | Z15: =IFERROR(U15-X15,"") | AA15: =IFERROR(Z15/U15,"") | AB15: =IF(Z15>=1,"Profit","Loss") -> Profit
C16: i | D16: Saiful Islam | E16: =#REF! -> #REF! | F16: =#REF! -> #REF! | G16: =$F$31*L16 -> #REF! | H16: =SUM(F16:G16) -> #REF! | I16: =#REF! -> #REF! | J16: =$I$31*L16 -> #REF! | K16: =SUM(I16:J16) -> #REF! | L16: =I16/$I$30 -> #REF! | N16: =IFERROR(H16-K16,"") | O16: =IFERROR(N16/H16,"") | P16: =IF(N16>=1,"Profit","Loss") -> Profit | R16: =#REF! -> #REF! | S16: =$R$31*Y16 -> #REF! | U16: =SUM(R16:S16) -> #REF! | V16: =#REF! -> #REF! | W16: =$V$31*Y16 -> #REF! | X16: =SUM(V16:W16) -> #REF! | Y16: =V16/$V$30 -> #REF! | Z16: =IFERROR(U16-X16,"") | AA16: =IFERROR(Z16/U16,"") | AB16: =IF(Z16>=1,"Profit","Loss") -> Profit
C17: 2 | D17: A K Singh | E17: =E18+E19+E20+E21+E22 -> #REF! | F17: =F18+F19+F20+F21+F22 -> #REF! | G17: =G18+G19+G20+G21+G22 -> #REF! | H17: =SUM(F17:G17) -> #REF! | I17: =I18+I19+I20+I21+I22 -> #REF! | J17: =$I$31*L17 -> #REF! | K17: =SUM(I17:J17) -> #REF! | L17: =I17/$I$30 -> #REF! | M17: =H17/$H$30 -> #REF! | N17: =IFERROR(H17-K17,"") | O17: =IFERROR(N17/H17,"") | P17: =IF(N17>=1,"Profit","Loss") -> Profit | R17: =R18+R19+R20+R21+R22 -> #REF! | S17: =$R$31*Y17 -> #REF! | U17: =SUM(R17:S17) -> #REF! | V17: =V18+V19+V20+V21+V22 -> #REF! | W17: =$V$31*Y17 -> #REF! | X17: =SUM(V17:W17) -> #REF! | Y17: =V17/$V$30 -> #REF! | Z17: =IFERROR(U17-X17,"") | AA17: =IFERROR(Z17/U17,"") | AB17: =IF(Z17>=1,"Profit","Loss") -> Profit | AC17: =F17+H17 -> #REF!
C18: a | D18: Paul | E18: 148678.01 | F18: =#REF! -> #REF! | G18: =$F$31*L18 -> #REF! | H18: =SUM(F18:G18) -> #REF! | I18: =#REF! -> #REF! | J18: =$I$31*L18 -> #REF! | K18: =SUM(I18:J18) -> #REF! | L18: =I18/$I$30 -> #REF! | N18: =IFERROR(H18-K18,"") | O18: =IFERROR(N18/H18,"") | P18: =IF(N18>=1,"Profit","Loss") -> Profit | R18: =#REF! -> #REF! | S18: =$R$31*Y18 -> #REF! | U18: =SUM(R18:S18) -> #REF! | V18: =#REF! -> #REF! | W18: =$V$31*Y18 -> #REF! | X18: =SUM(V18:W18) -> #REF! | Y18: =V18/$V$30 -> #REF! | Z18: =IFERROR(U18-X18,"") | AA18: =IFERROR(Z18/U18,"") | AB18: =IF(Z18>=1,"Profit","Loss") -> Profit
C19: b | D19: Santhosh | E19: =#REF! -> #REF! | F19: =#REF! -> #REF! | G19: =$F$31*L19 -> #REF! | H19: =SUM(F19:G19) -> #REF! | I19: =#REF! -> #REF! | J19: =$I$31*L19 -> #REF! | K19: =SUM(I19:J19) -> #REF! | L19: =I19/$I$30 -> #REF! | N19: =IFERROR(H19-K19,"") | O19: =IFERROR(N19/H19,"") | P19: =IF(N19>=1,"Profit","Loss") -> Profit | R19: =#REF! -> #REF! | S19: =$R$31*Y19 -> #REF! | U19: =SUM(R19:S19) -> #REF! | V19: =#REF! -> #REF! | W19: =$V$31*Y19 -> #REF! | X19: =SUM(V19:W19) -> #REF! | Y19: =V19/$V$30 -> #REF! | Z19: =IFERROR(U19-X19,"") | AA19: =IFERROR(Z19/U19,"") | AB19: =IF(Z19>=1,"Profit","Loss") -> Profit
C20: c | D20: Waqas | E20: 96203.415 | F20: =#REF! -> #REF! | G20: =$F$31*L20 -> #REF! | H20: =SUM(F20:G20) -> #REF! | I20: =#REF! -> #REF! | J20: =$I$31*L20 -> #REF! | K20: =SUM(I20:J20) -> #REF! | L20: =I20/$I$30 -> #REF! | N20: =IFERROR(H20-K20,"") | O20: =IFERROR(N20/H20,"") | P20: =IF(N20>=1,"Profit","Loss") -> Profit | R20: =#REF! -> #REF! | S20: =$R$31*Y20 -> #REF! | U20: =SUM(R20:S20) -> #REF! | V20: =#REF! -> #REF! | W20: =$V$31*Y20 -> #REF! | X20: =SUM(V20:W20) -> #REF! | Y20: =V20/$V$30 -> #REF! | Z20: =IFERROR(U20-X20,"") | AA20: =IFERROR(Z20/U20,"") | AB20: =IF(Z20>=1,"Profit","Loss") -> Profit
C21: d | D21: Joynal | E21: 103017.29 | F21: =#REF! -> #REF! | G21: =$F$31*L21 -> #REF! | H21: =SUM(F21:G21) -> #REF! | I21: =#REF! -> #REF! | J21: =$I$31*L21+1500 -> #REF! | K21: =SUM(I21:J21) -> #REF! | L21: =I21/$I$30 -> #REF! | N21: =IFERROR(H21-K21,"") | O21: =IFERROR(N21/H21,"") | P21: =IF(N21>=1,"Profit","Loss") -> Profit | R21: =#REF! -> #REF! | S21: =$R$31*Y21 -> #REF! | U21: =SUM(R21:S21) -> #REF! | V21: =#REF! -> #REF! | W21: =$V$31*Y21 -> #REF! | X21: =SUM(V21:W21) -> #REF! | Y21: =V21/$V$30 -> #REF! | Z21: =IFERROR(U21-X21,"") | AA21: =IFERROR(Z21/U21,"") | AB21: =IF(Z21>=1,"Profit","Loss") -> Profit
C22: e | D22: Baskar | E22: 77815.22 | F22: =#REF! -> #REF! | G22: =$F$31*L22 -> #REF! | H22: =SUM(F22:G22) -> #REF! | I22: =#REF!+3500 -> #REF! | J22: =$I$31*L22+1000 -> #REF! | K22: =SUM(I22:J22) -> #REF! | L22: =I22/$I$30 -> #REF! | N22: =IFERROR(H22-K22,"") | O22: =IFERROR(N22/H22,"") | P22: =IF(N22>=1,"Profit","Loss") -> Profit | R22: =#REF! -> #REF! | S22: =$R$31*Y22 -> #REF! | U22: =SUM(R22:S22) -> #REF! | V22: =#REF! -> #REF! | W22: =$V$31*Y22 -> #REF! | X22: =SUM(V22:W22) -> #REF! | Y22: =V22/$V$30 -> #REF! | Z22: =IFERROR(U22-X22,"") | AA22: =IFERROR(Z22/U22,"") | AB22: =IF(Z22>=1,"Profit","Loss") -> Profit
C23: =C17+1 -> 3 | D23: A Nagarajan | E23: =E24+E25+E27+E26+E28+E34+E36 -> #REF! | F23: =F24+F28+F25+F27+F34+F36+F26 -> #REF! | G23: =$F$31*L23 -> #REF! | H23: =SUM(F23:G23) -> #REF! | I23: =I24+I28+I25+I26 -> #REF! | J23: =$I$31*L23 -> #REF! | K23: =SUM(I23:J23) -> #REF! | L23: =I23/$I$30 -> #REF! | M23: =H23/$H$30 -> #REF! | N23: =IFERROR(H23-K23,"") | O23: =IFERROR(N23/H23,"") | P23: =IF(N23>=1,"Profit","Loss") -> Profit | R23: =R24+R28 -> #REF! | S23: =$R$31*Y23 -> #REF! | U23: =SUM(R23:S23) -> #REF! | V23: =V24+V28 -> #REF! | W23: =$V$31*Y23 -> #REF! | X23: =SUM(V23:W23) -> #REF! | Y23: =V23/$V$30 -> #REF! | Z23: =IFERROR(U23-X23,"") | AA23: =IFERROR(Z23/U23,"") | AB23: =IF(Z23>=1,"Profit","Loss") -> Profit | AC23: =F23+H23 -> #REF!
C24: a | D24: Jithender | E24: 53685 | F24: =#REF! -> #REF! | G24: =$F$31*L24 -> #REF! | H24: =SUM(F24:G24) -> #REF! | I24: =#REF!+5500 -> #REF! | J24: =$I$31*L24+7500 -> #REF! | K24: =SUM(I24:J24) -> #REF! | L24: =I24/$I$30 -> #REF! | M24: =H24/$H$30 -> #REF! | N24: =IFERROR(H24-K24,"") | O24: =IFERROR(N24/H24,"") | P24: =IF(N24>=1,"Profit","Loss") -> Profit | R24: =#REF! -> #REF! | S24: =$R$31*Y24 -> #REF! | U24: =SUM(R24:S24) -> #REF! | V24: =#REF! -> #REF! | W24: =$V$31*Y24 -> #REF! | X24: =SUM(V24:W24) -> #REF! | Y24: =V24/$V$30 -> #REF! | Z24: =IFERROR(U24-X24,"") | AA24: =IFERROR(Z24/U24,"") | AB24: =IF(Z24>=1,"Profit","Loss") -> Profit
C25: b | D25: Mukesh | E25: =#REF! -> #REF! | F25: =#REF! -> #REF! | G25: =$F$31*L25 -> #REF! | H25: =SUM(F25:G25) -> #REF! | I25: =#REF! -> #REF! | J25: =$I$31*L25 -> #REF! | K25: =SUM(I25:J25) -> #REF! | L25: =I25/$I$30 -> #REF! | N25: =IFERROR(H25-K25,"") | O25: =IFERROR(N25/H25,"") | P25: =IF(N25>=1,"Profit","Loss") -> Profit
C26: c | D26: Nassar/essa | E26: =#REF! -> #REF! | F26: =#REF! -> #REF! | G26: =$F$31*L26 -> #REF! | H26: =SUM(F26:G26) -> #REF! | I26: =#REF! -> #REF! | J26: =$I$31*L26 -> #REF! | K26: =SUM(I26:J26) -> #REF! | L26: =I26/$I$30 -> #REF! | N26: =IFERROR(H26-K26,"") | O26: =IFERROR(N26/H26,"")
C27: d | D27: Jayan | E27: 208870.46 | F27: =#REF! -> #REF! | G27: =$F$31*L27 -> #REF! | H27: =SUM(F27:G27) -> #REF! | I27: =#REF! -> #REF! | J27: =$I$31*L27-3500 -> #REF! | K27: =SUM(I27:J27) -> #REF! | L27: =I27/$I$30 -> #REF! | N27: =IFERROR(H27-K27,"") | O27: =IFERROR(N27/H27,"") | P27: =IF(N27>=1,"Profit","Loss") -> Profit | R27: =#REF!+(R30*0.9) -> #REF! | S27: =$R$31*Y27 -> #REF! | U27: =SUM(R27:S27) -> #REF! | V27: =#REF!+(V30*0.9) -> #REF! | W27: =$V$31*Y27 -> #REF! | X27: =SUM(V27:W27) -> #REF! | Y27: =V27/$V$30 -> #REF! | Z27: =IFERROR(U27-X27,"") | AA27: =IFERROR(Z27/U27,"") | AB27: =IF(Z27>=1,"Profit","Loss") -> Profit
C28: e | D28: Mohan | E28: =#REF! -> #REF! | F28: =#REF! -> #REF! | G28: =$F$31*L28 -> #REF! | H28: =SUM(F28:G28) -> #REF! | I28: =#REF!-5500 -> #REF! | J28: =$I$31*L28 -> #REF! | K28: =SUM(I28:J28) -> #REF! | L28: =I28/$I$30 -> #REF! | M28: =H28/$H$30 -> #REF! | N28: =IFERROR(H28-K28,"") | O28: =IFERROR(N28/H28,"") | P28: =IF(N28>=1,"Profit","Loss") -> Profit | R28: =#REF! -> #REF! | S28: =$R$31*Y28 -> #REF! | U28: =SUM(R28:S28) -> #REF! | V28: =#REF! -> #REF! | W28: =$V$31*Y28 -> #REF! | X28: =SUM(V28:W28) -> #REF! | Y28: =V28/$V$30 -> #REF! | Z28: =IFERROR(U28-X28,"") | AA28: =IFERROR(Z28/U28,"") | AB28: =IF(Z28>=1,"Profit","Loss") -> Profit
C30: Total | E30: =E23+E17+E7+E15+E31 -> #REF! | F30: =F23+F17+F7 -> #REF! | G30: =G23+G17+G7 -> #REF! | H30: =H23+H17+H7 -> #REF! | I30: =I23+I17+I7 -> #REF! | J30: =J23+J17+J7 -> #REF! | K30: =K23+K17+K7 -> #REF! | L30: =I30/$I$30 -> #REF! | M30: =F30/E30 -> #REF! | N30: =H30-K30 -> #REF! | O30: =IFERROR(N30/SUM(H30),0) -> 0 | P30: =IF(N30>=1,"Profit","Loss") -> #REF! | R30: =R23+R17+R7 -> #REF! | S30: =S23+S17+S7 -> #REF! | T30: =T23+T17+T7+T15 -> 0 | U30: =U23+U17+U7 -> #REF! | V30: =V23+V17+V7 -> #REF! | W30: =W23+W17+W7 -> #REF! | X30: =X23+X17+X7 -> #REF! | Y30: =V30/$V$30 -> #REF! | Z30: =U30-X30 -> #REF! | AA30: =Z30/U30 -> #REF! | AB30: =IF(Z30>=1,"Profit","Loss") -> #REF!
C31: 1 | D31: Prelims | E31: =DPR!H5 -> 0 | F31: =PRE!I74 -> 0 | I31: =PRE!I75 -> 0 | M31: =F31/E31 -> #DIV/0! | N31: =F31-I31 -> 0 | O31: =IFERROR(N31/F31,0) -> 0 | P31: =IF(N31>=1,"Profit","Loss") -> Loss | R31: =PRE!K74 -> 0 | V31: =PRE!K75 -> #REF! | Z31: =R31-V31 -> #REF! | AA31: =Z31/R31 -> #REF! | AB31: =IF(Z31>=1,"Profit","Loss") -> #REF!
C33: Sub Contractor
C34: 1 | D34: Grand Enterprizes | E34: =DPR!H205+DPR!H206 -> 0 | F34: =DPR!N205+DPR!N206 -> 0 | H34: =F34 -> 0 | I34: =#REF!+#REF!+#REF!+#REF! -> #REF! | K34: =I34 -> #REF! | M34: =F34/E34 -> #DIV/0! | N34: =F34-K34 -> #REF! | O34: =IFERROR(N34/H34,0) -> 0 | P34: =IF(N34>=1,"Profit","Loss") -> #REF! | R34: 0 | V34: 0 | Z34: =R34-U34 -> 0 | AA34: =R34-V34 -> 0
C35: 2 | D35: PCT | E35: =DPR!H208+DPR!H209+DPR!H210 -> 0 | F35: =DPR!N208+DPR!#REF! -> #REF! | H35: =F35 -> #REF! | I35: =#REF!+#REF! -> #REF! | K35: =I35 -> #REF! | N35: =F35-K35 -> #REF! | O35: =IFERROR(N35/H35,0) -> 0 | P35: =IF(N35>=1,"Profit","Loss") -> #REF!
C36: 3 | D36: Bahwan | E36: =DPR!H207 -> 0 | F36: =DPR!N207+DPR!N206 -> 0 | H36: =F36 -> 0 | I36: =#REF! -> #REF! | K36: =I36 -> #REF! | N36: =F36-K36 -> #REF! | O36: =IFERROR(N36/F36,0) -> 0 | P36: =IF(N36>=1,"Profit","Loss") -> #REF!
C38: Grand Total | E38: =E30+E31+E34+E36+E35 -> #REF! | F38: =F30+F31+F34+F36+F35 -> #REF! | H38: =H30+H31+H34+H36+H35 -> #REF! | I38: =I30+I31+I34+I36+I35 -> #REF! | K38: =K30+K31+K34+K36+K35 -> #REF! | N38: =H38-K38 -> #REF! | O38: =IFERROR(N38/H38,0) -> 0 | P38: =IF(N38>=1,"Profit","Loss") -> #REF! | R38: =R31+R23+R17+R7 -> #REF! | S38: =S31+S23+S17+S7 -> #REF! | U38: =U30+U31+U34 -> #REF! | V38: =V30+V31+V34 -> #REF! | X38: =X30+X31+X34 -> #REF! | Z38: =U38-X38 -> #REF! | AA38: =Z38/U38 -> #REF! | AB38: =IF(Z38>=1,"Profit","Loss") -> #REF!
D41: Description | E41: Cum. Amount | H41: For the Day
D42: A.Man Power: | E42: =VLOOKUP(D42,#REF!,2,0)+VLOOKUP(D42,PRE!$B$71:$E$76,2,0)+VLOOKUP(D42,#REF!,2,0)+VLOOKUP(D42,#REF!,2,0)+VLOOKUP(D42,#REF!,2,0)+VLOOKUP(D42,#REF!,2,0)+VLOOKUP(D42,#REF!,2,0)+VLOOKUP(D42,#REF!,2,0)+VLOOKUP(D42,#REF!,2,0)+VLOOKUP(D42,#REF!,2,0)+VLOOKUP(D42,#REF!,2,0)+VLOOKUP(D42,#REF!,2,0)+VLOOKUP(D42,#REF!,2,0)+VLOOKUP(D42,#REF!,2,0)+VLOOKUP(D42,#REF!,2,0)+VLOOKUP(D42,#REF!,2,0)+#REF!+#REF! -> #REF! | F42: #REF! | H42: =VLOOKUP(D42,#REF!,4,0)+VLOOKUP(D42,PRE!B71:E76,4,0)+VLOOKUP(D42,#REF!,4,0)+VLOOKUP(D42,#REF!,4,0)+VLOOKUP(D42,#REF!,4,0)+VLOOKUP(D42,#REF!,4,0)+VLOOKUP(D42,#REF!,4,0)+VLOOKUP(D42,#REF!,4,0)+VLOOKUP(D42,#REF!,4,0)+VLOOKUP(D42,#REF!,4,0)+VLOOKUP(D42,#REF!,4,0)+VLOOKUP(D42,#REF!,4,0)+VLOOKUP(D42,#REF!,4,0)+VLOOKUP(D42,#REF!,4,0)+VLOOKUP(D42,#REF!,4,0)+VLOOKUP(D42,#REF!,4,0)+#REF! -> #REF! | K42: =306256 -> 306256 | N42: =K42/27 -> 11342.815 | O42: =N42*21 -> 238199.11
D43: B.Catering/Admin: | E43: =VLOOKUP(D43,#REF!,2,0)+VLOOKUP(D43,PRE!$B$71:$E$76,2,0)+VLOOKUP(D43,#REF!,2,0)+VLOOKUP(D43,#REF!,2,0)+VLOOKUP(D43,#REF!,2,0)+VLOOKUP(D43,#REF!,2,0)+VLOOKUP(D43,#REF!,2,0)+VLOOKUP(D43,#REF!,2,0)+#REF!+VLOOKUP(D43,#REF!,2,0)+VLOOKUP(D43,#REF!,2,0)+VLOOKUP(D43,#REF!,2,0)+VLOOKUP(D43,#REF!,2,0)+VLOOKUP(D43,#REF!,2,0)+VLOOKUP(D43,#REF!,2,0)+VLOOKUP(D43,#REF!,2,0)+VLOOKUP(D43,#REF!,2,0) -> #REF! | H43: =VLOOKUP(D43,#REF!,4,0)+VLOOKUP(D43,PRE!B72:E78,4,0)+VLOOKUP(D43,#REF!,4,0)+VLOOKUP(D43,#REF!,4,0)+VLOOKUP(D43,#REF!,4,0)+VLOOKUP(D43,#REF!,4,0)+VLOOKUP(D43,#REF!,4,0)+VLOOKUP(D43,#REF!,4,0)+VLOOKUP(D43,#REF!,4,0)+VLOOKUP(D43,#REF!,4,0)+VLOOKUP(D43,#REF!,4,0)+VLOOKUP(D43,#REF!,4,0)+VLOOKUP(D43,#REF!,4,0)+VLOOKUP(D43,#REF!,4,0)+VLOOKUP(D43,#REF!,4,0)+VLOOKUP(D43,#REF!,4,0) -> #REF! | K43: 39256 | N43: =K43/27 -> 1453.9259 | O43: =N43*21 -> 30532.444
D44: C.Machinery: | E44: =VLOOKUP(D44,#REF!,2,0)+VLOOKUP(D44,PRE!$B$71:$E$76,2,0)+VLOOKUP(D44,#REF!,2,0)+VLOOKUP(D44,#REF!,2,0)+VLOOKUP(D44,#REF!,2,0)+VLOOKUP(D44,#REF!,2,0)+VLOOKUP(D44,#REF!,2,0)+VLOOKUP(D44,#REF!,2,0)+VLOOKUP(D44,#REF!,2,0)+VLOOKUP(D44,#REF!,2,0)+VLOOKUP(D44,#REF!,2,0)+VLOOKUP(D44,#REF!,2,0)+VLOOKUP(D44,#REF!,2,0)+VLOOKUP(D44,#REF!,2,0)+VLOOKUP(D44,#REF!,2,0)+VLOOKUP(D44,#REF!,2,0)+#REF!+#REF! -> #REF! | H44: =VLOOKUP(D44,#REF!,4,0)+VLOOKUP(D44,PRE!B73:E79,4,0)+VLOOKUP(D44,#REF!,4,0)+VLOOKUP(D44,#REF!,4,0)+VLOOKUP(D44,#REF!,4,0)+VLOOKUP(D44,#REF!,4,0)+VLOOKUP(D44,#REF!,4,0)+VLOOKUP(D44,#REF!,4,0)+VLOOKUP(D44,#REF!,4,0)+VLOOKUP(D44,#REF!,4,0)+VLOOKUP(D44,#REF!,4,0)+VLOOKUP(D44,#REF!,4,0)+VLOOKUP(D44,#REF!,4,0)+VLOOKUP(D44,#REF!,4,0)+VLOOKUP(D44,#REF!,4,0)+VLOOKUP(D44,#REF!,4,0)+#REF! -> #REF! | K44: =278236+10355 -> 288591 | N44: =K44/27 -> 10688.556 | O44: =N44*21 -> 224459.67
D45: D.Fuel Charge | E45: =VLOOKUP(D45,#REF!,2,0)+VLOOKUP(D45,PRE!$B$71:$E$76,2,0)+VLOOKUP(D45,#REF!,2,0)+VLOOKUP(D45,#REF!,2,0)+VLOOKUP(D45,#REF!,2,0)+VLOOKUP(D45,#REF!,2,0)+VLOOKUP(D45,#REF!,2,0)+VLOOKUP(D45,#REF!,2,0)+VLOOKUP(D45,#REF!,2,0)+VLOOKUP(D45,#REF!,2,0)+VLOOKUP(D45,#REF!,2,0)+VLOOKUP(D45,#REF!,2,0)+VLOOKUP(D45,#REF!,2,0)+VLOOKUP(D45,#REF!,2,0)+VLOOKUP(D45,#REF!,2,0)+VLOOKUP(D45,#REF!,2,0)+#REF!+#REF! -> #REF! | H45: =VLOOKUP(D45,#REF!,4,0)+VLOOKUP(D45,PRE!B74:E80,4,0)+VLOOKUP(D45,#REF!,4,0)+VLOOKUP(D45,#REF!,4,0)+VLOOKUP(D45,#REF!,4,0)+VLOOKUP(D45,#REF!,4,0)+VLOOKUP(D45,#REF!,4,0)+VLOOKUP(D45,#REF!,4,0)+VLOOKUP(D45,#REF!,4,0)+VLOOKUP(D45,#REF!,4,0)+VLOOKUP(D45,#REF!,4,0)+VLOOKUP(D45,#REF!,4,0)+VLOOKUP(D45,#REF!,4,0)+VLOOKUP(D45,#REF!,4,0)+VLOOKUP(D45,#REF!,4,0)+VLOOKUP(D45,#REF!,4,0)+#REF! -> #REF! | K45: =K44*0.53 -> 152953.23 | N45: =K45/27 -> 5664.9344 | O45: =N45*21 -> 118963.62
D46: E.Material | E46: =VLOOKUP(D46,#REF!,2,0)+VLOOKUP(D46,PRE!$B$71:$E$76,2,0)+VLOOKUP(D46,#REF!,2,0)+VLOOKUP(D46,#REF!,2,0)+VLOOKUP(D46,#REF!,2,0)+VLOOKUP(D46,#REF!,2,0)+VLOOKUP(D46,#REF!,2,0)+VLOOKUP(D46,#REF!,2,0)+VLOOKUP(D46,#REF!,2,0)+VLOOKUP(D46,#REF!,2,0)+VLOOKUP(D46,#REF!,2,0)+VLOOKUP(D46,#REF!,2,0)+VLOOKUP(D46,#REF!,2,0)+VLOOKUP(D46,#REF!,2,0)+VLOOKUP(D46,#REF!,2,0)+VLOOKUP(D46,#REF!,2,0)+#REF!+#REF! -> #REF! | H46: =VLOOKUP(D46,#REF!,4,0)+VLOOKUP(D46,PRE!B75:E81,4,0)+VLOOKUP(D46,#REF!,4,0)+VLOOKUP(D46,#REF!,4,0)+VLOOKUP(D46,#REF!,4,0)+VLOOKUP(D46,#REF!,4,0)+VLOOKUP(D46,#REF!,4,0)+VLOOKUP(D46,#REF!,4,0)+VLOOKUP(D46,#REF!,4,0)+VLOOKUP(D46,#REF!,4,0)+VLOOKUP(D46,#REF!,4,0)+VLOOKUP(D46,#REF!,4,0)+VLOOKUP(D46,#REF!,4,0)+VLOOKUP(D46,#REF!,4,0)+VLOOKUP(D46,#REF!,4,0)+VLOOKUP(D46,#REF!,4,0)+#REF! -> #REF! | K46: =485256 -> 485256 | N46: =K46/27 -> 17972.444 | O46: =N46*21 -> 377421.33
D47: F.SubContractor | E47: =#REF!+PRE!C76+#REF!+#REF!+#REF!+#REF!+#REF!+#REF!+#REF!+#REF!+#REF!+#REF!+#REF!+#REF!+#REF!+#REF!+I36+SUM(#REF!) -> #REF! | H47: =VLOOKUP(D47,#REF!,4,0)+VLOOKUP(D47,PRE!B76:E82,4,0)+VLOOKUP(D47,#REF!,4,0)+VLOOKUP(D47,#REF!,4,0)+VLOOKUP(D47,#REF!,4,0)+VLOOKUP(D47,#REF!,4,0)+VLOOKUP(D47,#REF!,4,0)+VLOOKUP(D47,#REF!,4,0)+VLOOKUP(D47,#REF!,4,0)+VLOOKUP(D47,#REF!,4,0)+VLOOKUP(D47,#REF!,4,0)+VLOOKUP(D47,#REF!,4,0)+VLOOKUP(D47,#REF!,4,0)+VLOOKUP(D47,#REF!,4,0)+VLOOKUP(D47,#REF!,4,0)+VLOOKUP(D47,#REF!,4,0) -> #REF! | N47: =K47/27 -> 0 | O47: =N47*21 -> 0
D48: G. General Expenses | E48: =PRE!C77 -> 0 | H48: =PRE!E77 -> 0 | N48: =K48/27 -> 0 | O48: =N48*21 -> 0
D49: Sub total | E49: =SUM(E42:E48) -> #REF! | H49: =SUM(H42:H48) -> #REF! | N49: =K49/27 -> 0 | O49: =N49*18 -> 0
D50: Unit over heads | E50: =#REF!+PRE!G21+#REF!+#REF!+#REF!+#REF!+#REF!+#REF!+#REF!+#REF!+#REF!+#REF!+#REF!+#REF!+#REF!+#REF! -> #REF! | H50: =#REF!+PRE!E21+#REF!+#REF!+#REF!+#REF!+#REF!+#REF!+#REF!+#REF!+#REF!+#REF!+#REF!+#REF!+#REF!+#REF! -> #REF! | O50: =N50*18 -> 0
D51: Total | E51: =E49+E50 -> #REF! | H51: =H49+H50 -> #REF!
D56: 1 | E56: =D56+1 -> 2 | F56: =E56+1 -> 3 | G56: =F56+1 -> 4 | H56: =G56+1 -> 5 | I56: =H56+1 -> 6 | J56: =I56+1 -> 7 | K56: =J56+1 -> 8 | L56: =K56+1 -> 9 | M56: =L56+1 -> 10
D64: PM/CM | E64: Projection Amount | F64: Achieved Amount to date | G64: Prelims Income | H64: Achieved Amount to date (Incl Prelims) | I64: Cost to date | J64: Prelims Cost | K64: Cost to date including prelims | L64: % of Cost | M64: % of Income | N64: Contribution | O64: Contribution %
D65: Ifithikar | E65: 69455.13 | F65: 52870.219 | G65: 26087.414 | H65: 78957.632 | I65: 58084.938 | J65: 36754.581 | K65: 94839.519 | L65: 0.37717405 | M65: 0.31216473 | N65: -15881.886 | O65: -0.20114441
D66: Gopi | E66: 97638.273 | F66: 51144.863 | G66: 13188.117 | H66: 64332.98 | I66: 29364.006 | J66: 18580.75 | K66: 47944.756 | L66: 0.19067492 | M66: 0.2543451 | N66: 16388.224 | O66: 0.25474063
D67: Anil PP | E67: 81984.653 | F67: 51770.132 | G67: 16860.861 | H67: 68630.993 | I67: 37541.554 | J67: 23755.282 | K67: 61296.837 | L67: 0.24377576 | M67: 0.27133761 | N67: 7334.1562 | O67: 0.10686362
D68: Koshy | E68: 36552 | F68: 27985.125 | G68: 13029.061 | H68: 41014.186 | I68: 29009.86 | J68: 18356.656 | K68: 47366.516 | L68: 0.18837528 | M68: 0.16215256 | N68: -6352.3299 | O68: -0.15488128
D70: Ifithikar | E70: =E7-E65 -> #REF! | F70: =F7-F65 -> #REF! | G70: =G7-G65 -> #REF! | H70: =H7-H65 -> #REF! | I70: =I7-I65 -> #REF! | J70: =J7-J65 -> #REF! | K70: =K7-K65 -> #REF! | L70: =L7-L65 -> #REF! | ... O70: =O7-O65 -> #VALUE!
D71: Gopi | E71: =#REF!-E66 -> #REF! | F71: =#REF!-F66 -> #REF! | G71: =#REF!-G66 -> #REF! | H71: =#REF!-H66 -> #REF! | I71: =#REF!-I66 -> #REF! | J71: =#REF!-J66 -> #REF! | K71: =#REF!-K66 -> #REF! | L71: =#REF!-L66 -> #REF! | ... O71: =#REF!-O66 -> #REF!
D72: Anil PP | E72: =E17-E67 -> #REF! | F72: =F17-F67 -> #REF! | G72: =G17-G67 -> #REF! | H72: =H17-H67 -> #REF! | I72: =I17-I67 -> #REF! | J72: =J17-J67 -> #REF! | K72: =K17-K67 -> #REF! | L72: =L17-L67 -> #REF! | ... O72: =O17-O67 -> #VALUE!
D73: Koshy | E73: =E23-E68 -> #REF! | F73: =F23-F68 -> #REF! | G73: =G23-G68 -> #REF! | H73: =H23-H68 -> #REF! | I73: =I23-I68 -> #REF! | J73: =J23-J68 -> #REF! | K73: =K23-K68 -> #REF! | L73: =L23-L68 -> #REF! | ... O73: =O23-O68 -> #VALUE!
H74: =SUM(H70:H73) -> #REF! | I74: =H74-U30 -> #REF! | K74: =SUM(K70:K73) -> #REF! | L74: =K74-X30 -> #REF!
D75: Ifithikar | H75: =H70-U7 -> #REF! | K75: =K70-X7 -> #REF!
D76: Gopi | H76: =H71-#REF! -> #REF! | K76: =K71-#REF! -> #REF!
D77: Anil PP | H77: =H72-U17 -> #REF! | K77: =K72-X17 -> #REF!
D78: Koshy | H78: =H73-U23 -> #REF! | K78: =K73-X23 -> #REF!

Sheet Summary-Financial (NEW)
AD1: 42948 | AG1: Fuel taken | AH1: 0.4911
R2: 0.009 | AB2: As on | AC2: xxxx | AD2: =EOMONTH(AC2,0) -> #VALUE! | AE2: =AE3 -> 29 | AF2: 25 | AI2: 31
AB3: Time Elapsed | AC3: 0 | AE3: 29
C4: Project:
C5: Cumulative | T5: For the Day
C6: Sl No | D6: PM/CM | E6: Plan Amount | F6: Achieved Amount to date | G6: Prelims Income | H6: Achieved Amount to date (Incl Prelims) | I6: Cost | J6: Prelims Cost | K6: Cost to date including prelims | L6: % of Cost | M6: % of Income | N6: Planned Contribution | O6: Contribution | P6: Contribution % | Q6: Indicate | T6: Achieved Amount to date | U6: Prelims Income | V6: Achieved Amount to date (Incl Prelims) | W6: Cost | X6: Prelims Cost | Y6: Cost to date including prelims | Z6: % of Cost | AA6: Contribution | AB6: Contribution % | AC6: Indicate
C7: 1 | D7: Site Manager 1 | E7: =SUM(E8:E13) -> 0 | F7: =SUM(F8:F13) -> 0 | G7: =SUM(G8:G13) -> 0 | H7: =SUM(F7:G7) -> 0 | I7: =I8+I9+I10+I11+I12+I13 -> 0 | J7: =J8+J9+J10+J11+J12+J13 -> 0 | K7: =SUM(I7:J7) -> 0 | L7: =IFERROR(I7/$I$28,0) -> 0 | M7: =IFERROR(H7/$H$28,0) -> 0 | N7: =2131.98168179438+10000 -> 12131.982 | O7: 13000 | P7: =IFERROR(O7/H7,"") | Q7: =IF(O7>=1,"Profit","Loss") -> Profit | R7: =H7*$R$2 -> 0 | T7: =SUM(T8:T12) -> 0 | U7: =SUM(U8:U12) -> 0 | V7: =SUM(T7:U7) -> 0 | W7: =SUM(W8:W12) -> 0 | X7: =SUM(X8:X12) -> 0 | Y7: =SUM(W7:X7) -> 0 | Z7: =IFERROR(W7/$W$28,0) -> 0 | AA7: =IFERROR(V7-Y7,"") -> 0 | AB7: =IFERROR(AA7/V7,"") | AC7: =IF(AA7>=1,"Profit","Loss") -> Loss | AK7: =O7/#REF! -> #REF! | AL7: =O7/$H$35 -> #DIV/0! | AM7: =N7/$H$28 -> #DIV/0!
C8: a | D8: Preliminaries | E8: =DPR!H14+DPR!H18+DPR!H19 -> 0 | F8: =DPR!N14+DPR!N18+DPR!N19 -> 0 | G8: =$F$29*L8 -> 0 | H8: =SUM(F8:G8) -> 0 | J8: =IFERROR($I$29*L8,0) -> 0 | K8: =SUM(I8:J8) -> 0 | L8: =IFERROR(I8/$I$28,0) -> 0 | N8: 90.419192 | O8: =IFERROR(H8-K8,"") -> 0 | P8: =IFERROR(O8/H8,"") | Q8: =IF(O8>=1,"Profit","Loss") -> Loss | R8: =H8*$R$2 -> 0 | U8: =$T$29*Z8 -> 0 | V8: =SUM(T8:U8) -> 0 | X8: =$W$29*Z8 -> 0 | Y8: =SUM(W8:X8) -> 0 | Z8: =IFERROR(W8/$W$28,0) -> 0 | AA8: =IFERROR(V8-Y8,"") -> 0 | AB8: =IFERROR(AA8/V8,"") | AC8: =IF(AA8>=1,"Profit","Loss") -> Loss | AK8: =O8/#REF! -> #REF! | AL8: =O8/$H$35 -> #DIV/0! | AM8: =N8/$H$28 -> #DIV/0!
C9: b | D9: xxxx | F9: =DPR!P215 -> 0 | G9: =$F$29*L9 -> 0 | H9: =SUM(F9:G9) -> 0 | J9: =IFERROR($I$29*L9,0) -> 0 | K9: =SUM(I9:J9) -> 0 | L9: =IFERROR(I9/$I$28,0) -> 0 | N9: 435.78181 | O9: =IFERROR(H9-K9,"") -> 0 | P9: =IFERROR(O9/H9,"") | Q9: =IF(O9>=1,"Profit","Loss") -> Loss | R9: =H9*$R$2 -> 0 | U9: =$T$29*Z9 -> 0 | V9: =SUM(T9:U9) -> 0 | X9: =$W$29*Z9 -> 0 | Y9: =SUM(W9:X9) -> 0 | Z9: =IFERROR(W9/$W$28,0) -> 0 | AA9: =IFERROR(V9-Y9,"") -> 0 | AB9: =IFERROR(AA9/V9,"") | AC9: =IF(AA9>=1,"Profit","Loss") -> Loss | AK9: =O9/#REF! -> #REF! | AL9: =O9/$H$35 -> #DIV/0! | AM9: =N9/$H$28 -> #DIV/0!
C10: c | D10: xxxx | F10: =DPR!Q215 -> 0 | G10: =$F$29*L10 -> 0 | H10: =SUM(F10:G10) -> 0 | J10: =IFERROR($I$29*L10,0) -> 0 | K10: =SUM(I10:J10) -> 0 | L10: =IFERROR(I10/$I$28,0) -> 0 | N10: 211.30837 | O10: =IFERROR(H10-K10,"") -> 0 | P10: =IFERROR(O10/H10,"") | Q10: =IF(O10>=1,"Profit","Loss") -> Loss | R10: =H10*$R$2 -> 0 | U10: =$T$29*Z10 -> 0 | V10: =SUM(T10:U10) -> 0 | X10: =$W$29*Z10 -> 0 | Y10: =SUM(W10:X10) -> 0 | Z10: =IFERROR(W10/$W$28,0) -> 0 | AA10: =IFERROR(V10-Y10,"") -> 0 | AB10: =IFERROR(AA10/V10,"") | AC10: =IF(AA10>=1,"Profit","Loss") -> Loss | AK10: =O10/#REF! -> #REF! | AL10: =O10/$H$35 -> #DIV/0! | AM10: =N10/$H$28 -> #DIV/0!
C11: d | D11: xxxx | F11: 0 | G11: =$F$29*L11 -> 0 | H11: =SUM(F11:G11) -> 0 | J11: =IFERROR($I$29*L11,0) -> 0 | K11: =SUM(I11:J11) -> 0 | L11: =IFERROR(I11/$I$28,0) -> 0 | N11: 1387.1193 | O11: =IFERROR(H11-K11,"") -> 0 | P11: =IFERROR(O11/H11,"") | Q11: =IF(O11>=1,"Profit","Loss") -> Loss | R11: =H11*$R$2 -> 0 | U11: =$T$29*Z11 -> 0 | V11: =SUM(T11:U11) -> 0 | X11: =$W$29*Z11 -> 0 | Y11: =SUM(W11:X11) -> 0 | Z11: =IFERROR(W11/$W$28,0) -> 0 | AA11: =IFERROR(V11-Y11,"") -> 0 | AB11: =IFERROR(AA11/V11,"") | AC11: =IF(AA11>=1,"Profit","Loss") -> Loss | AK11: =O11/#REF! -> #REF! | AL11: =O11/$H$35 -> #DIV/0! | AM11: =N11/$H$28 -> #DIV/0!
C12: e | D12: xxxx | F12: 0 | G12: =$F$29*L12 -> 0 | H12: =SUM(F12:G12) -> 0 | J12: =IFERROR($I$29*L12,0) -> 0 | K12: =SUM(I12:J12) -> 0 | L12: =IFERROR(I12/$I$28,0) -> 0 | N12: 1.1200604 | O12: =IFERROR(H12-K12,"") -> 0 | P12: =IFERROR(O12/H12,"") | Q12: =IF(O12>=1,"Profit","Loss") -> Loss | R12: =H12*$R$2 -> 0 | U12: =$T$29*Z12 -> 0 | V12: =SUM(T12:U12) -> 0 | X12: =$W$29*Z12 -> 0 | Y12: =SUM(W12:X12) -> 0 | Z12: =IFERROR(W12/$W$28,0) -> 0 | AA12: =IFERROR(V12-Y12,"") -> 0 | AB12: =IFERROR(AA12/V12,"") | AC12: =IF(AA12>=1,"Profit","Loss") -> Loss | AK12: =O12/#REF! -> #REF! | AL12: =O12/$H$35 -> #DIV/0! | AM12: =N12/$H$28 -> #DIV/0!
C13: f | D13: xxxx | F13: 0 | G13: =$F$29*L13 -> 0 | H13: =SUM(F13:G13) -> 0 | J13: =IFERROR($I$29*L13,0) -> 0 | K13: =SUM(I13:J13) -> 0 | L13: =IFERROR(I13/$I$28,0) -> 0 | N13: 6.23295 | O13: =IFERROR(H13-K13,"") -> 0 | P13: =IFERROR(O13/H13,"") | Q13: =IF(O13>=1,"Profit","Loss") -> Loss | R13: =H13*$R$2 -> 0 | U13: =$T$29*Z13 -> 0 | V13: =SUM(T13:U13) -> 0 | X13: =$W$29*Z13 -> 0 | Y13: =SUM(W13:X13) -> 0 | Z13: =IFERROR(W13/$W$28,0) -> 0 | AA13: =IFERROR(V13-Y13,"") -> 0 | AB13: =IFERROR(AA13/V13,"") | AC13: =IF(AA13>=1,"Profit","Loss") -> Loss | AK13: =O13/#REF! -> #REF! | AL13: =O13/$H$35 -> #DIV/0! | AM13: =N13/$H$28 -> #DIV/0!
C14: 2 | D14: Site Manager 2 | E14: =SUM(E15:E22) -> 0 | F14: =SUM(F15:F22) -> 0 | G14: =SUM(G15:G22) -> 0 | H14: =SUM(F14:G14) -> 0 | I14: =SUM(I15:I22) -> 0 | J14: =SUM(J15:J22) -> 0 | K14: =SUM(I14:J14) -> 0 | L14: =IFERROR(I14/$I$28,0) -> 0 | N14: =1755.07822362555+25000 -> 26755.078 | O14: =IFERROR(H14-K14,"") -> 0 | P14: =IFERROR(O14/H14,"") | Q14: =IF(O14>=1,"Profit","Loss") -> Loss | R14: =H14*$R$2 -> 0 | T14: =SUM(T15:T22) -> 0 | U14: =SUM(U15:U22) -> 0 | V14: =SUM(T14:U14) -> 0 | W14: =SUM(W15:W22) -> 0 | X14: =SUM(X15:X22) -> 0 | Y14: =SUM(W14:X14) -> 0 | Z14: =IFERROR(W14/$W$28,0) -> 0 | AA14: =IFERROR(V14-Y14,"") -> 0 | AB14: =IFERROR(AA14/V14,"") | AC14: =IF(AA14>=1,"Profit","Loss") -> Loss | AK14: =O14/#REF! -> #REF! | AL14: =O14/$H$35 -> #DIV/0! | AM14: =N14/$H$28 -> #DIV/0!
C15: a | D15: xxxx | G15: =$F$29*L15 -> 0 | H15: =SUM(F15:G15) -> 0 | J15: =IFERROR($I$29*L15,0) -> 0 | K15: =SUM(I15:J15) -> 0 | L15: =IFERROR(I15/$I$28,0) -> 0 | N15: 335.68109 | O15: =IFERROR(H15-K15,"") -> 0 | P15: =IFERROR(O15/H15,"") | Q15: =IF(O15>=1,"Profit","Loss") -> Loss | R15: =H15*$R$2 -> 0 | U15: =$T$29*Z15 -> 0 | V15: =SUM(T15:U15) -> 0 | X15: =$W$29*Z15 -> 0 | Y15: =SUM(W15:X15) -> 0 | Z15: =IFERROR(W15/$W$28,0) -> 0 | AA15: =IFERROR(V15-Y15,"") -> 0 | AB15: =IFERROR(AA15/V15,"") | AC15: =IF(AA15>=1,"Profit","Loss") -> Loss | AK15: =O15/#REF! -> #REF! | AL15: =O15/$H$35 -> #DIV/0! | AM15: =N15/$H$28 -> #DIV/0!
C16: b | D16: xxxx | G16: =$F$29*L16 -> 0 | H16: =SUM(F16:G16) -> 0 | J16: =IFERROR($I$29*L16,0) -> 0 | K16: =SUM(I16:J16) -> 0 | L16: =IFERROR(I16/$I$28,0) -> 0 | N16: 442.27762 | O16: =IFERROR(H16-K16,"") -> 0 | P16: =IFERROR(O16/H16,"") | Q16: =IF(O16>=1,"Profit","Loss") -> Loss | R16: =H16*$R$2 -> 0 | U16: =$T$29*Z16 -> 0 | V16: =SUM(T16:U16) -> 0 | X16: =$W$29*Z16 -> 0 | Y16: =SUM(W16:X16) -> 0 | Z16: =IFERROR(W16/$W$28,0) -> 0 | AA16: =IFERROR(V16-Y16,"") -> 0 | AB16: =IFERROR(AA16/V16,"") | AC16: =IF(AA16>=1,"Profit","Loss") -> Loss | AK16: =O16/#REF! -> #REF! | AL16: =O16/$H$35 -> #DIV/0! | AM16: =N16/$H$28 -> #DIV/0!
C17: c | D17: xxxx | G17: =$F$29*L17 -> 0 | H17: =SUM(F17:G17) -> 0 | J17: =IFERROR($I$29*L17,0) -> 0 | K17: =SUM(I17:J17) -> 0 | L17: =IFERROR(I17/$I$28,0) -> 0 | N17: 35.444981 | O17: =IFERROR(H17-K17,"") -> 0 | P17: =IFERROR(O17/H17,"") | Q17: =IF(O17>=1,"Profit","Loss") -> Loss | R17: =H17*$R$2 -> 0 | U17: =$T$29*Z17 -> 0 | V17: =SUM(T17:U17) -> 0 | X17: =$W$29*Z17 -> 0 | Y17: =SUM(W17:X17) -> 0 | Z17: =IFERROR(W17/$W$28,0) -> 0 | AA17: =IFERROR(V17-Y17,"") -> 0 | AB17: =IFERROR(AA17/V17,"") | AK17: =O17/#REF! -> #REF! | AL17: =O17/$H$35 -> #DIV/0! | AM17: =N17/$H$28 -> #DIV/0!
C18: d | D18: xxxx | G18: =$F$29*L18 -> 0 | H18: =SUM(F18:G18) -> 0 | J18: =IFERROR($I$29*L18,0) -> 0 | K18: =SUM(I18:J18) -> 0 | L18: =IFERROR(I18/$I$28,0) -> 0 | N18: 98.628151 | O18: =IFERROR(H18-K18,"") -> 0 | P18: =IFERROR(O18/H18,"") | Q18: =IF(O18>=1,"Profit","Loss") -> Loss | R18: =H18*$R$2 -> 0 | U18: =$T$29*Z18 -> 0 | V18: =SUM(T18:U18) -> 0 | X18: =$W$29*Z18 -> 0 | Y18: =SUM(W18:X18) -> 0 | Z18: =IFERROR(W18/$W$28,0) -> 0 | AA18: =IFERROR(V18-Y18,"") -> 0 | AB18: =IFERROR(AA18/V18,"") | AK18: =O18/#REF! -> #REF! | AL18: =O18/$H$35 -> #DIV/0! | AM18: =N18/$H$28 -> #DIV/0!
C19: e | D19: xxxx | G19: =$F$29*L19 -> 0 | H19: =SUM(F19:G19) -> 0 | J19: =IFERROR($I$29*L19,0) -> 0 | K19: =SUM(I19:J19) -> 0 | L19: =IFERROR(I19/$I$28,0) -> 0 | N19: 767.72531 | O19: =IFERROR(H19-K19,"") -> 0 | P19: =IFERROR(O19/H19,"") | Q19: =IF(O19>=1,"Profit","Loss") -> Loss | R19: =H19*$R$2 -> 0 | U19: =$T$29*Z19 -> 0 | V19: =SUM(T19:U19) -> 0 | X19: =$W$29*Z19 -> 0 | Y19: =SUM(W19:X19) -> 0 | Z19: =IFERROR(W19/$W$28,0) -> 0 | AA19: =IFERROR(V19-Y19,"") -> 0 | AB19: =IFERROR(AA19/V19,"") | AC19: =IF(AA19>=1,"Profit","Loss") -> Loss | AK19: =O19/#REF! -> #REF! | AL19: =O19/$H$35 -> #DIV/0! | AM19: =N19/$H$28 -> #DIV/0!
C20: f | D20: xxxx | G20: =$F$29*L20 -> 0 | H20: =SUM(F20:G20) -> 0 | J20: =IFERROR($I$29*L20,0) -> 0 | K20: =SUM(I20:J20) -> 0 | L20: =IFERROR(I20/$I$28,0) -> 0 | N20: 21.034334 | O20: =IFERROR(H20-K20,"") -> 0 | P20: =IFERROR(O20/H20,"") | Q20: =IF(O20>=1,"Profit","Loss") -> Loss | R20: =H20*$R$2 -> 0 | U20: =$T$29*Z20 -> 0 | V20: =SUM(T20:U20) -> 0 | X20: =$W$29*Z20 -> 0 | Y20: =SUM(W20:X20) -> 0 | Z20: =IFERROR(W20/$W$28,0) -> 0 | AA20: =IFERROR(V20-Y20,"") -> 0 | AB20: =IFERROR(AA20/V20,"") | AK20: =O20/#REF! -> #REF! | AL20: =O20/$H$35 -> #DIV/0! | AM20: =N20/$H$28 -> #DIV/0!
C21: g | D21: xxxx | G21: =$F$29*L21 -> 0 | H21: =SUM(F21:G21) -> 0 | J21: =IFERROR($I$29*L21,0) -> 0 | K21: =SUM(I21:J21) -> 0 | L21: =IFERROR(I21/$I$28,0) -> 0 | N21: 37.366737 | O21: =IFERROR(H21-K21,"") -> 0 | P21: =IFERROR(O21/H21,"") | Q21: =IF(O21>=1,"Profit","Loss") -> Loss | R21: =H21*$R$2 -> 0 | U21: =$T$29*Z21 -> 0 | V21: =SUM(T21:U21) -> 0 | X21: =$W$29*Z21 -> 0 | Y21: =SUM(W21:X21) -> 0 | Z21: =IFERROR(W21/$W$28,0) -> 0 | AA21: =IFERROR(V21-Y21,"") -> 0 | AB21: =IFERROR(AA21/V21,"") | AC21: =IF(AA21>=1,"Profit","Loss") -> Loss | AK21: =O21/#REF! -> #REF! | AL21: =O21/$H$35 -> #DIV/0! | AM21: =N21/$H$28 -> #DIV/0!
C22: h | D22: xxxx | G22: =$F$29*L22 -> 0 | H22: =SUM(F22:G22) -> 0 | J22: =IFERROR($I$29*L22,0) -> 0 | K22: =SUM(I22:J22) -> 0 | L22: =IFERROR(I22/$I$28,0) -> 0 | N22: 16.92 | O22: =IFERROR(H22-K22,"") -> 0 | P22: =IFERROR(O22/H22,"") | Q22: =IF(O22>=1,"Profit","Loss") -> Loss | R22: =H22*$R$2 -> 0 | U22: =$T$29*Z22 -> 0 | V22: =SUM(T22:U22) -> 0 | X22: =$W$29*Z22 -> 0 | Y22: =SUM(W22:X22) -> 0 | Z22: =IFERROR(W22/$W$28,0) -> 0 | AA22: =IFERROR(V22-Y22,"") -> 0 | AB22: =IFERROR(AA22/V22,"") | AC22: =IF(AA22>=1,"Profit","Loss") -> Loss | AK22: =O22/#REF! -> #REF! | AL22: =O22/$H$35 -> #DIV/0! | AM22: =N22/$H$28 -> #DIV/0!
C23: =C14+1 -> 3 | D23: Site Manager 3 | E23: =SUM(E24:E27) -> 0 | F23: =SUM(F24:F27) -> 0 | G23: =SUM(G24:G27) -> 0 | H23: =SUM(F23:G23) -> 0 | I23: =SUM(I24:I27) -> 0 | J23: =SUM(J24:J27) -> 0 | K23: =SUM(I23:J23) -> 0 | L23: =IFERROR(I23/$I$28,0) -> 0 | N23: =1989.85058807419+10000 -> 11989.851 | O23: =IFERROR(H23-K23,"") -> 0 | P23: =IFERROR(O23/H23,"") | Q23: =IF(O23>=1,"Profit","Loss") -> Loss | R23: =H23*$R$2 -> 0 | T23: =SUM(T24:T27) -> 0 | U23: =SUM(U24:U27) -> 0 | V23: =SUM(T23:U23) -> 0 | W23: =SUM(W24:W27) -> 0 | X23: =SUM(X24:X27) -> 0 | Y23: =SUM(W23:X23) -> 0 | Z23: =IFERROR(W23/$W$28,0) -> 0 | AA23: =IFERROR(V23-Y23,"") -> 0 | AB23: =IFERROR(AA23/V23,"") | AC23: =IF(AA23>=1,"Profit","Loss") -> Loss | AK23: =O23/#REF! -> #REF! | AL23: =O23/$H$35 -> #DIV/0! | AM23: =N23/$H$28 -> #DIV/0!
C24: a | D24: xxxx | G24: =$F$29*L24 -> 0 | H24: =SUM(F24:G24) -> 0 | J24: =IFERROR($I$29*L24,0) -> 0 | K24: =SUM(I24:J24) -> 0 | L24: =IFERROR(I24/$I$28,0) -> 0 | N24: 190.46189 | O24: =IFERROR(H24-K24,"") -> 0 | P24: =IFERROR(O24/H24,"") | Q24: =IF(O24>=1,"Profit","Loss") -> Loss | R24: =H24*$R$2 -> 0 | U24: =$T$29*Z24 -> 0 | V24: =SUM(T24:U24) -> 0 | X24: =$W$29*Z24 -> 0 | Y24: =SUM(W24:X24) -> 0 | Z24: =IFERROR(W24/$W$28,0) -> 0 | AA24: =IFERROR(V24-Y24,"") -> 0 | AB24: =IFERROR(AA24/V24,"") | AC24: =IF(AA24>=1,"Profit","Loss") -> Loss
C25: b | D25: xxxx | G25: =$F$29*L25 -> 0 | H25: =SUM(F25:G25) -> 0 | J25: =IFERROR($I$29*L25,0) -> 0 | K25: =SUM(I25:J25) -> 0 | L25: =IFERROR(I25/$I$28,0) -> 0 | N25: 1362.1283 | O25: =IFERROR(H25-K25,"") -> 0 | P25: =IFERROR(O25/H25,"") | Q25: =IF(O25>=1,"Profit","Loss") -> Loss | R25: =H25*$R$2 -> 0 | U25: =$T$29*Z25 -> 0 | V25: =SUM(T25:U25) -> 0 | X25: =$W$29*Z25 -> 0 | Y25: =SUM(W25:X25) -> 0 | Z25: =IFERROR(W25/$W$28,0) -> 0 | AA25: =IFERROR(V25-Y25,"") -> 0 | AB25: =IFERROR(AA25/V25,"") | AC25: =IF(AA25>=1,"Profit","Loss") -> Loss
C26: d | D26: xxxx | G26: =$F$29*L26 -> 0 | H26: =SUM(F26:G26) -> 0 | J26: =IFERROR($I$29*L26,0) -> 0 | K26: =SUM(I26:J26) -> 0 | L26: =IFERROR(I26/$I$28,0) -> 0 | N26: 189.30921 | O26: =IFERROR(H26-K26,"") -> 0 | P26: =IFERROR(O26/H26,"") | Q26: =IF(O26>=1,"Profit","Loss") -> Loss | R26: =H26*$R$2 -> 0 | U26: =$T$29*Z26 -> 0 | V26: =SUM(T26:U26) -> 0 | X26: =$W$29*Z26 -> 0 | Y26: =SUM(W26:X26) -> 0 | Z26: =IFERROR(W26/$W$28,0) -> 0 | AA26: =IFERROR(V26-Y26,"") -> 0 | AB26: =IFERROR(AA26/V26,"") | AC26: =IF(AA26>=1,"Profit","Loss") -> Loss
C27: e | D27: xxxx | G27: =$F$29*L27 -> 0 | H27: =SUM(F27:G27) -> 0 | J27: =IFERROR($I$29*L27,0) -> 0 | K27: =SUM(I27:J27) -> 0 | L27: =IFERROR(I27/$I$28,0) -> 0 | N27: 247.95122 | O27: =IFERROR(H27-K27,"") -> 0 | P27: =IFERROR(O27/H27,"") | Q27: =IF(O27>=1,"Profit","Loss") -> Loss | R27: =H27*$R$2 -> 0 | U27: =$T$29*Z27 -> 0 | V27: =SUM(T27:U27) -> 0 | X27: =$W$29*Z27 -> 0 | Y27: =SUM(W27:X27) -> 0 | Z27: =IFERROR(W27/$W$28,0) -> 0 | AA27: =IFERROR(V27-Y27,"") -> 0 | AB27: =IFERROR(AA27/V27,"") | AC27: =IF(AA27>=1,"Profit","Loss") -> Loss
C28: Total | E28: =E23+E14+E7 -> 0 | F28: =F23+F14+F7 -> 0 | G28: =G23+G14+G7 -> 0 | H28: =H23+H14+H7 -> 0 | I28: =I7+I14+I23 -> 0 | J28: =J7+J14+J23 -> 0 | K28: =K7+K14+K23 -> 0 | L28: =IFERROR(I28/$I$28,0) -> 0 | M28: =IFERROR(F28/E28,0) -> 0 | O28: =H28-K28 -> 0 | P28: =IFERROR(O28/SUM(H28),0) -> 0 | Q28: =IF(O28>=1,"Profit","Loss") -> Loss | T28: =T7+T14+T23 -> 0 | U28: =U7+U14+U23 -> 0 | V28: =V7+V14+V23 -> 0 | W28: =W7+W14+W23 -> 0 | X28: =X7+X14+X23 -> 0 | Y28: =Y7+Y14+Y23 -> 0 | Z28: =IFERROR(W28/$W$28,0) -> 0 | AA28: =V28-Y28 -> 0 | AB28: =IFERROR(AA28/V28,0) -> 0 | AC28: =IF(AA28>=1,"Profit","Loss") -> Loss
C29: 1 | D29: Prelims | E29: =DPR!H13 -> 0 | F29: =DPR!N13 -> 0 | M29: =IFERROR(F29/E29,0) -> 0 | O29: =F29-I29 -> 0 | P29: =IFERROR(O29/F29,0) -> 0 | Q29: =IF(O29>=1,"Profit","Loss") -> Loss | T29: =PRE!K74 -> 0 | AA29: =T29-W29 -> 0 | AB29: =IFERROR(AA29/T29,0) -> 0 | AC29: =IF(AA29>=1,"Profit","Loss") -> Loss
C31: Sub Contractor
C32: 1 | D32: Sub-contractor 1 | E32: =DPR!H205+DPR!H206 -> 0 | H32: =F32 -> 0 | K32: =I32 -> 0 | O32: =F32-K32 -> 0 | P32: =IFERROR(O32/F32,0) -> 0 | Q32: =IF(O32>=1,"Profit","Loss") -> Loss | V32: =T32 -> 0 | Y32: =W32 -> 0 | AA32: =V32-Y32 -> 0 | AB32: =IFERROR(AA32/V32,"") | AC32: =IF(AA32>=1,"Profit","Loss") -> Loss
C33: 2 | D33: Sub-contractor 2 | E33: =DPR!H207 -> 0 | F33: =DPR!N207 -> 0 | H33: =F33 -> 0 | K33: =I33 -> 0 | O33: =F33-K33 -> 0 | P33: =IFERROR(O33/F33,0) -> 0 | Q33: =IF(O33>=1,"Profit","Loss") -> Loss | V33: =T33 -> 0 | Y33: =W33 -> 0 | AA33: =V33-Y33 -> 0 | AB33: =IFERROR(AA33/V33,"") | AC33: =IF(AA33>=1,"Profit","Loss") -> Loss
C34: 3 | D34: Sub-contractor 3 | H34: =F34 -> 0 | K34: =I34 -> 0 | O34: =F34-K34 -> 0 | P34: =IFERROR(O34/F34,0) -> 0 | Q34: =IF(O34>=1,"Profit","Loss") -> Loss | V34: =T34 -> 0 | Y34: =W34 -> 0 | AA34: =V34-Y34 -> 0 | AB34: =IFERROR(AA34/V34,"") | AC34: =IF(AA34>=1,"Profit","Loss") -> Loss
C35: Grand Total | E35: =E28+E29+E32+E33 -> 0 | F35: =F28+F29+F32+F33+F34 -> 0 | H35: =H28+H29+H32+H33+H34 -> 0 | I35: =I28+I29+I32+I33+I34 -> 0 | K35: =K28+K29+K32+K33+K34 -> 0 | O35: =H35-K35 -> 0 | P35: =IFERROR(O35/H35,0) -> 0 | Q35: =IF(O35>=1,"Profit","Loss") -> Loss | R35: =O35/H35 -> #DIV/0! | V35: =V28+V29+V32+V33+V34 -> 0 | Y35: =Y28+Y29+Y32+Y33+Y34 -> 0 | AA35: =V35-Y35 -> 0 | AB35: =IFERROR(AA35/V35,0) -> 0 | AC35: =IF(AA35>=1,"Profit","Loss") -> Loss
D38: Description | E38: Projected Cost | F38: Actual Cost till date | G38: Actual Cost for the Day
D39: A.Man Power:
D40: B.Catering/Admin:
D41: C.Machinery:
D42: D.Fuel Charge | V42: =45000/11 -> 4090.9091
D43: E.Material
D44: F.SubContractor
D45: G. General Expenses
D46: H.Production Cost
D47: Total | E47: =SUM(E39:E45) -> 0 | F47: =SUM(F39:F46) -> 0 | G47: =SUM(G39:G46) -> 0
Y53: =5083+1821+1530+182+21632+26334+6448 -> 63030
D54: 1 | E54: =D54+1 -> 2 | F54: =E54+1 -> 3 | G54: =F54+1 -> 4 | H54: =G54+1 -> 5 | I54: =H54+1 -> 6 | J54: =I54+1 -> 7 | K54: =J54+1 -> 8 | L54: =K54+1 -> 9 | M54: =L54+1 -> 10
AA60: =7/27 -> 0.25925926
J65: 291301.9
J66: 0
J67: 15346.27 | P67: =500*2*26 -> 26000
J68: 143045.45 | K68: =J68/J65 -> 0.49105568 | P68: =P67/(500*9) -> 5.7777778

Sheet DPR
J2: =+SUM(J3:L3) -> 0
J3: =SUMPRODUCT(J5:J214,$F$5:$F$214) -> 0 | K3: =SUMPRODUCT(K5:K214,$F$5:$F$214) -> 0 | L3: =SUMPRODUCT(L5:L214,$F$5:$F$214) -> 0 | N3: ='[19]Utilities (reji)'!$AO$51 -> 0 | O3: F O R T H E M O N T H | S3: F O R T H E D A Y
B4: Code | C4: BOQ # | D4: Description | E4: Unit | F4: Unit Rate (R.O) | G4: Plan qty | H4: Plan- Amount | I4: xxxx | J4: xxxx | K4: xxxx | L4: xxxx | M4: Achieved Qty | N4: Achieved Amount | O4: xxxx | P4: xxxx | Q4: xxxx | R4: xxxx | S4: xxxx | T4: xxxx | U4: xxxx | V4: xxxx
A5: =G5+I5 -> 0 | B5: 1 | C5: 1 | D5: Preliminaries | H5: =G5*F5 -> 0 | M5: =SUM(O5:R5) -> 0 | N5: =+M5*F5 -> 0
A6: =G6+I6 -> 0 | C6: 1.3.5(i)a | D6: Soil Investigation and report | E6: LS | H6: =G6*F6 -> 0 | M6: =SUM(O6:R6) -> 0 | N6: =+M6*F6 -> 0
A7: =G7+I7 -> 0 | C7: 1.3.5(i)b | D7: Setting up at bore hole position for test up to 30m | E7: Nr. | H7: =G7*F7 -> 0 | M7: =SUM(O7:R7) -> 0 | N7: =+M7*F7 -> 0
A8: =G8+I8 -> 0 | C8: 1.3.5(i)c | D8: Setting up at bore hole position for test up to 10m | E8: Nr. | H8: =G8*F8 -> 0 | M8: =SUM(O8:R8) -> 0 | N8: =+M8*F8 -> 0
A9: =G9+I9 -> 0 | C9: 1.3.5(i)d | D9: Rotary core drilling up to 30m deep | E9: lin.m. | H9: =G9*F9 -> 0 | M9: =SUM(O9:R9) -> 0 | N9: =+M9*F9 -> 0
A10: =G10+I10 -> 0 | C10: 1.3.5(i)e | D10: Establish Location and excavate test pit 3m deep | E10: Nr. | H10: =G10*F10 -> 0 | M10: =SUM(O10:R10) -> 0 | N10: =+M10*F10 -> 0
A11: =G11+I11 -> 0 | C11: 1.3.5(ii) | D11: Design and approvel of IC construction | E11: LS | H11: =G11*F11 -> 0 | M11: =SUM(O11:R11) -> 0 | N11: =+M11*F11 -> 0
A12: =G12+I12 -> 0 | C12: 1.4.3(i) | D12: Mobilization and demobilization | E12: LS | H12: =G12*F12 -> 0 | M12: =SUM(O12:R12) -> 0 | N12: =+M12*F12 -> 0
A13: =G13+I13 -> 0 | C13: 1.4.3(ii) | D13: Maintenance of Contractor's site facilities | E13: Month | H13: =G13*F13 -> 0 | M13: =SUM(O13:R13) -> 0 | N13: =+M13*F13 -> 0
A14: =G14+I14 -> 0 | C14: 1.7.6(i)a | D14: Maintenance and Protection of Traffic | E14: Month | H14: =G14*F14 -> 0 | M14: =SUM(O14:R14) -> 0 | N14: =+M14*F14 -> 0
A15: =G15+I15 -> 0 | C15: 1.7.6(ii) | D15: Sub-base on diversions | E15: Cum | H15: =G15*F15 -> 0 | M15: =SUM(O15:R15) -> 0 | N15: =+M15*F15 -> 0
A16: =G16+I16 -> 0 | C16: 1.7.6(iii) | D16: Bituminous base course on diversions | E16: Cum | H16: =G16*F16 -> 0 | M16: =SUM(O16:R16) -> 0 | N16: =+M16*F16 -> 0
A17: =G17+I17 -> 0 | C17: 1.7.6(iv) | D17: Prime coat | E17: Kg | H17: =G17*F17 -> 0 | M17: =SUM(O17:R17) -> 0 | N17: =+M17*F17 -> 0
... A35: =G35+I35 -> 0 | C35: 2.3.6(i) | D35: Unclassified excavation | E35: Cum | H35: =G35*F35 -> 0 | M35: =SUM(O35:R35) -> 0 | N35: =+M35*F35 -> 0
C36: 2.3.6(i)a | D36: Unclassified excavation | E36: Cum | H36: =G36*F36 -> 0 | M36: =SUM(O36:R36) -> 0 | N36: =+M36*F36 -> 0
A37: =G37+I37 -> 0 | C37: 2.4.6(i)a1 | D37: Borrow excavation to embankment-Extraction and screening | E37: Cum | H37: =G37*F37 -> 0 | M37: =SUM(O37:R37) -> 0 | N37: =+M37*F37 -> 0
C38: 2.4.6(i)a2 | D38: Borrow excavation to embankment-Transportation | E38: Cum | H38: =G38*F38 -> 0 | M38: =SUM(O38:R38) -> 0 | N38: =+M38*F38 -> 0
A39: =G39+I39 -> 0 | C39: 2.4.6(i)a3 | D39: Borrow excavation to Embankment-Hauling and compaction | E39: Cum | H39: =G39*F39 -> 0 | M39: =SUM(O39:R39) -> 0 | N39: =+M39*F39 -> 0
A40: =G40+I40 -> 0 | C40: 2.6.6(i) | D40: Subgrade preparation in cut | E40: Sqm | H40: =G40*F40 -> 0 | M40: =SUM(O40:R40) -> 0 | N40: =+M40*F40 -> 0
A41: =G41+I41 -> 0 | C41: 2.7.6(i) | D41: Unclassified structural excavation (depth 0m to 2.0m) (Excavation) | E41: Cum | H41: =G41*F41 -> 0 | M41: =SUM(O41:R41) -> 0 | N41: =+M41*F41 -> 0
A42: =G42+I42 -> 0 | D42: Unclassified structural excavation (depth 0m to 2.0m) (Backfilling) | E42: Cum | H42: =G42*F42 -> 0 | M42: =SUM(O42:R42) -> 0 | N42: =+M42*F42 -> 0
A43: =G43+I43 -> 0 | C43: 2.7.6(ii) | D43: Unclassified structural excavation (depth >2.0m to <4.0m) | E43: Cum | H43: =G43*F43 -> 0 | M43: =SUM(O43:R43) -> 0 | N43: =+M43*F43 -> 0
A44: =G44+I44 -> 0 | C44: 2.7.6(iii) | D44: Unclassified structural excavation (depth ≥ 4.0m) | E44: Cum | H44: =G44*F44 -> 0 | M44: =SUM(O44:R44) -> 0 | N44: =+M44*F44 -> 0
A45: =G45+I45 -> 0 | C45: 2.7.6(iv) | D45: Unclassified structural excavation (under water) | E45: Cum | H45: =G45*F45 -> 0 | M45: =SUM(O45:R45) -> 0 | N45: =+M45*F45 -> 0
A46: =G46+I46 -> 0 | C46: 2.8.6(i) | D46: Trench excavation and Backfill depth (depth 0 to 2.0m) | E46: Cum | H46: =G46*F46 -> 0 | M46: =SUM(O46:R46) -> 0 | N46: =+M46*F46 -> 0
A47: =G47+I47 -> 0 | C47: 2.8.6(ii) | D47: Trench excavation and Backfill depth (depth > 2.0m to ≤ 3.0m) | E47: Cum | H47: =G47*F47 -> 0 | M47: =SUM(O47:R47) -> 0 | N47: =+M47*F47 -> 0
A48: =G48+I48 -> 0 | C48: 3.2.6(ii)1 | D48: GSB (Class B)-Extraction and Screening | E48: Cum | H48: =G48*F48 -> 0 | M48: =SUM(O48:R48) -> 0 | N48: =+M48*F48 -> 0
A49: =G49+I49 -> 0 | C49: 3.2.6(ii)2 | D49: GSB (Class B)-Transportation | E49: Cum | H49: =G49*F49 -> 0 | M49: =SUM(O49:R49) -> 0 | N49: =+M49*F49 -> 0
C50: 3.2.6(ii)3 | D50: GSB (Class B)-Hauling and compaction | E50: Cum | H50: =G50*F50 -> 0 | M50: =SUM(O50:R50) -> 0 | N50: =+M50*F50 -> 0
A51: =G51+I51 -> 0 | C51: 3.3.6(ii)1 | D51: ABC (Class A)-Extraction and Screening | E51: Cum | H51: =G51*F51 -> 0 | M51: =SUM(O51:R51) -> 0 | N51: =+M51*F51 -> 0
A52: =G52+I52 -> 0 | C52: 3.3.6(ii)2 | D52: ABC (Class A)-Crushing | E52: Cum | H52: =G52*F52 -> 0 | M52: =SUM(O52:R52) -> 0 | N52: =+M52*F52 -> 0
A53: =G53+I53 -> 0 | C53: 3.3.6(ii)3 | D53: ABC (Class A)-Production, Hauling and Compaction | E53: Cum | H53: =G53*F53 -> 0 | M53: =SUM(O53:R53) -> 0 | N53: =+M53*F53 -> 0
A54: =G54+I54 -> 0 | D54: ABC (Class A)-Crushing & Transportation (Al Adrak Material) | E54: cum | H54: =G54*F54 -> 0 | M54: =SUM(O54:R54) -> 0 | N54: =+M54*F54 -> 0
A55: =G55+I55 -> 0 | D55: ABC (Class A)-Production, Hauling and Compaction | E55: Cum | H55: =G55*F55 -> 0 | M55: =SUM(O55:R55) -> 0 | N55: =+M55*F55 -> 0
A56: =G56+I56 -> 0 | C56: 4.2.8(i) | D56: Bituminous prime coat | E56: Kg | H56: =G56*F56 -> 0 | M56: =SUM(O56:R56) -> 0 | N56: =+M56*F56 -> 0
A57: =G57+I57 -> 0 | C57: 4.2.8(ii) | D57: Bituminous tack coat | E57: Kg | H57: =G57*F57 -> 0 | M57: =SUM(O57:R57) -> 0 | N57: =+M57*F57 -> 0
A58: =G58+I58 -> 0 | C58: 4.4.14(i) | D58: BBC - Production, Laying and Compaction (Class B) | E58: Cum | H58: =G58*F58 -> 0 | M58: =SUM(O58:R58) -> 0 | N58: =+M58*F58 -> 0
A59: =G59+I59 -> 0 | C59: 4.5.14(ii) | D59: BWC - Production, laying and Compaction (Class B) | E59: Cum | H59: =G59*F59 -> 0 | M59: =SUM(O59:R59) -> 0 | N59: =+M59*F59 -> 0
A60: =G60+I60 -> 0 | C60: 4.9.10(i) | D60: Surface milling (up to 50mm thick) | E60: Sqm | H60: =G60*F60 -> 0 | M60: =SUM(O60:R60) -> 0 | N60: =+M60*F60 -> 0
A61: =G61+I61 -> 0 | C61: 4.10.6(i) | D61: Pavement Widening including unclassified excavation, sub grade preparation, aggregate base course, bituminous wearing course, including saw cutting & abutting, stepping as necessary, etc. all as per drawing, specification,carting away debris and making good to match with existing. | E61: Sqm | H61: =G61*F61 -> 0 | M61: =SUM(O61:R61) -> 0 | N61: =+M61*F61 -> 0
A62: =G62+I62 -> 0 | C62: 4.12.10(i) | D62: International roughness index. (IRI) | E62: lin.m. | H62: =G62*F62 -> 0 | M62: =SUM(O62:R62) -> 0 | N62: =+M62*F62 -> 0
A63: =G63+I63 -> 0 | C63: 5.1.7(i)a | D63: Concrete (Class15),blinding for culverts,Bridges, retaining walls,under/overpass foundations, mass concrete etc. | E63: Cum | H63: =G63*F63 -> 0 | M63: =SUM(O63:R63) -> 0 | N63: =+M63*F63 -> 0
A64: =G64+I64 -> 0 | C64: 5.1.7(i)b | D64: Concrete Class30, for Box culvert barrel, wing walls, apron slab, cut off walls, headwalls etc | E64: Cum | H64: =G64*F64 -> 0 | M64: =SUM(O64:R64) -> 0 | N64: =+M64*F64 -> 0
A65: =G65+I65 -> 0 | C65: 5.1.7(i)c | D65: Concrete Class30, for retaining walls at bridge and for underpass/overpass etc(Provisional) | E65: Cum | H65: =G65*F65 -> 0 | M65: =SUM(O65:R65) -> 0 | N65: =+M65*F65 -> 0
A66: =G66+I66 -> 0 | C66: 5.1.7(i)d | D66: Concrete (class30), for Bridge foundation and Underpass/overpass, abutments, pier heads, return walls, approach slab, sump pits, columns etc.. | E66: Cum | H66: =G66*F66 -> 0 | M66: =SUM(O66:R66) -> 0 | N66: =+M66*F66 -> 0
A67: =G67+I67 -> 0 | C67: 5.1.7(i)e | D67: Concrete (class35),for Bridge deck slab, cross heads, plinths, diaphragm beam, walkways, stair case steps and ramps, roof beams etc. | E67: Cum | H67: =G67*F67 -> 0 | M67: =SUM(O67:R67) -> 0 | N67: =+M67*F67 -> 0
... A89: =G89+I89 -> 0 | C89: 8.3.6(i)a | D89: Manhole chamber 1000mm x 1000mm internal size and depth up to 1200mm in concrete class 30 at roundabout including DI cover. | E89: Nr | H89: =G89*F89 -> 0 | M89: =SUM(O89:R89) -> 0 | N89: =+M89*F89 -> 0
A90: =G90+I90 -> 0 | D90: Manhole chamber 700mm x 700mm internal size and depth minimum 1200mm, in concrete class 30 at median including DI cover and gratings. Casting | E90: Nr | H90: =G90*F90 -> 0 | M90: =SUM(O90:R90) -> 0 | N90: =+M90*F90 -> 0
A91: =G91+I91 -> 0 | C91: 8.3.6(i)b | D91: Manhole chamber 700mm x 700mm internal size and depth minimum 1200mm, in concrete class 30 at median including DI cover and gratings. Errection | E91: Nr | H91: =G91*F91 -> 0 | M91: =SUM(O91:R91) -> 0 | N91: =+M91*F91 -> 0
A92: =G92+I92 -> 0 | C92: 8.3.6(i)c-1 | D92: Manhole chamber 600mm x 600mm internal size and depth minimum 1200mm, in concrete class 30 at median including DI cover and gratings. Casting | E92: Nr | H92: =G92*F92 -> 0 | M92: =SUM(O92:R92) -> 0 | N92: =+M92*F92 -> 0
A93: =G93+I93 -> 0 | C93: 8.3.6(i)c | D93: Manhole chamber 600mm x 600mm internal size and depth minimum 1200mm, in concrete class 30 at median including DI cover and gratings. Errection | E93: Nr | H93: =G93*F93 -> 0 | M93: =SUM(O93:R93) -> 0 | N93: =+M93*F93 -> 0
A94: =G94+I94 -> 0 | C94: 8.3.6(ii)a | D94: Drain out let chamber 450 mm x 450 mm in-place to bridge deck include heavy duty steel grating assembly as detailed in the drawings. | E94: Nr | H94: =G94*F94 -> 0 | M94: =SUM(O94:R94) -> 0 | N94: =+M94*F94 -> 0
A95: =G95+I95 -> 0 | C95: 8.3.6(ii)b | D95: Sump pit chamber 800mm x 800mm x 800mm internal size in concrete class 30 at underpass including D.I gratings. | E95: lin.m. | H95: =G95*F95 -> 0 | M95: =SUM(O95:R95) -> 0 | N95: =+M95*F95 -> 0
A96: =G96+I96 -> 0 | C96: 8.4.6(ii)a | D96: 75mm dia UPVC drainage pipes through abutment curtain wall | E96: lin.m. | H96: =G96*F96 -> 0 | M96: =SUM(O96:R96) -> 0 | N96: =+M96*F96 -> 0
A97: =G97+I97 -> 0 | C97: 8.4.6(ii)b | D97: 110mm dia UPVC drainage pipes through internal diaphragms | E97: lin.m. | H97: =G97*F97 -> 0 | M97: =SUM(O97:R97) -> 0 | N97: =+M97*F97 -> 0
A98: =G98+I98 -> 0 | C98: 8.4.6(ii)c | D98: 150mm dia UPVC drainage pipes for drainage from underpass sump pits. | E98: lin.m. | H98: =G98*F98 -> 0 | M98: =SUM(O98:R98) -> 0 | N98: =+M98*F98 -> 0
A99: =G99+I99 -> 0 | C99: 8.4.6(ii)d | D99: 50mm dia non-metallic weep holes through abutment | E99: lin.m. | H99: =G99*F99 -> 0 | M99: =SUM(O99:R99) -> 0 | N99: =+M99*F99 -> 0
A100: =G100+I100 -> 0 | C100: 8.4.6(ii)e | D100: 3000mm x 600mm x 600mm drainage pit with selected stone filled and rapped in 700g/m2 geotextile membrane including all excavation, backfilling all as per drawing and as approved by the Engineer for underpass drainage. | E100: Nr | H100: =G100*F100 -> 0 | M100: =SUM(O100:R100) -> 0 | N100: =+M100*F100 -> 0
A101: =G101+I101 -> 0 | C101: 10.1.6(i) | D101: Setting up at each pile 900mm & 1000mm diameter -pile location | E101: nr. | H101: =G101*F101 -> 0 | M101: =SUM(O101:R101) -> 0 | N101: =+M101*F101 -> 0
A102: =G102+I102 -> 0 | C102: 10.1.6(ii) | D102: Piling , 1000 mm diameter for Pier Foundation up to 15 m | E102: lin.m. | H102: =G102*F102 -> 0 | M102: =SUM(O102:R102) -> 0 | N102: =+M102*F102 -> 0
... A152: =G152+I152 -> 0 | C152: 14.1.7(v)a | D152: Sign post support assembly, including foundation( Single) Casting 35% | E152: nr. | H152: =G152*F152 -> 0 | M152: =SUM(O152:R152) -> 0 | N152: =+M152*F152 -> 0
D153: Sign post support assembly, including foundation( Single) Errecation 65% | E153: nr | H153: =G153*F153 -> 0 | M153: =SUM(O153:R153) -> 0 | N153: =+M153*F153 -> 0
A154: =G154+I154 -> 0 | C154: 14.1.7(v)b | D154: Sign post support assembly, including foundations( Double) | E154: nr. | H154: =G154*F154 -> 0 | M154: =SUM(O154:R154) -> 0 | N154: =+M154*F154 -> 0
A155: =G155+I155 -> 0 | C155: 14.1.7(v)c | D155: Sign post support assembly, including foundations( four post 150mm dia ) | E155: nr. | H155: =G155*F155 -> 0 | M155: =SUM(O155:R155) -> 0 | N155: =+M155*F155 -> 0
A156: =G156+I156 -> 0 | C156: 14.1.7(viii)a | D156: Removable type 75mm dia G.I Bollards 1200mm high painted red and white at median opening including foundation concrete, locking arrangements with S.S. Chain etc complete as per details. | E156: nr. | H156: =G156*F156 -> 0 | M156: =SUM(O156:R156) -> 0 | N156: =+M156*F156 -> 0
A157: =G157+I157 -> 0 | C157: 14.1.7(viii)b | D157: Removable type 225mm dia decorative G.I Bollards, 850mm high painted black at access road to Royal camp including foundation concrete, locking arrangements with S.S. Chain etc complete as per details. | E157: nr. | H157: =G157*F157 -> 0 | M157: =SUM(O157:R157) -> 0 | N157: =+M157*F157 -> 0
A158: =G158+I158 -> 0 | C158: 14.1.7(viii)c | D158: Debris Collecting 150mm dia G.I Bollards at culvert inlets including foundation concrete, reinforcement, painting etc complete as per details. | E158: nr. | H158: =G158*F158 -> 0 | M158: =SUM(O158:R158) -> 0 | N158: =+M158*F158 -> 0
A159: =G159+I159 -> 0 | C159: 14.2.6(i) | D159: Traffic lines continuous or broken for both white and yellow (mechanical applied) | E159: sq.m | H159: =G159*F159 -> 0 | M159: =SUM(O159:R159) -> 0 | N159: =+M159*F159 -> 0
A160: =G160+I160 -> 0 | C160: 14.2.6(iii) | D160: Special markings for cheveron,directional arrow.(hand applied) | E160: sq.m | H160: =G160*F160 -> 0 | M160: =SUM(O160:R160) -> 0 | N160: =+M160*F160 -> 0
A161: =G161+I161 -> 0 | C161: 14.2.6(iv) | D161: Curb painting | E161: sq.m | H161: =G161*F161 -> 0 | M161: =SUM(O161:R161) -> 0 | N161: =+M161*F161 -> 0
A162: =G162+I162 -> 0 | C162: 14.2.6(v) | D162: Removal of road marking | E162: sq.m | H162: =G162*F162 -> 0 | M162: =SUM(O162:R162) -> 0 | N162: =+M162*F162 -> 0
A163: =G163+I163 -> 0 | C163: 14.3.6(i)a | D163: Reflecting road studs (one side red) | E163: nr. | H163: =G163*F163 -> 0 | M163: =SUM(O163:R163) -> 0 | N163: =+M163*F163 -> 0
A164: =G164+I164 -> 0 | C164: 14.3.6(i)b | D164: Reflecting road studs (both side red) | E164: nr. | H164: =G164*F164 -> 0 | M164: =SUM(O164:R164) -> 0 | N164: =+M164*F164 -> 0
A165: =G165+I165 -> 0 | C165: 14.3.6(i)c | D165: Reflecting road studs at rumble strips (one side red) | E165: nr. | H165: =G165*F165 -> 0 | M165: =SUM(O165:R165) -> 0 | N165: =+M165*F165 -> 0
... A214: =G214+I214 -> 0 | C214: 18.3.6(i)d | D214: Service ducts one 300 mm uPVC one way | E214: lin.m | H214: =G214*F214 -> 0 | M214: =SUM(O214:R214) -> 0 | N214: =+M214*F214 -> 0
D215: Total Amount | H215: =SUM(H5:H214) -> 0 | I215: =SUM(I5:I214) -> 0 | J215: =SUM(J5:J214) -> 0 | K215: =SUM(K5:K214) -> 0 | L215: =SUM(L5:L214) -> 0 | N215: =SUM(N5:N214) -> 0 | O215: =SUMPRODUCT(O5:O214,$F$5:$F$214) -> 0 | P215: =SUMPRODUCT(P5:P214,$F$5:$F$214) -> 0 | Q215: =SUMPRODUCT(Q5:Q214,$F$5:$F$214) -> 0 | R215: =SUMPRODUCT(R5:R214,$F$5:$F$214) -> 0 | S215: =SUMPRODUCT(S5:S214,$F$5:$F$214) -> 0 | T215: =SUMPRODUCT(T5:T214,$F$5:$F$214) -> 0 | U215: =SUMPRODUCT(U5:U214,$F$5:$F$214) -> 0 | V215: =SUMPRODUCT(V5:V214,$F$5:$F$214) -> 0
K217: 0
N219: =N215-N217 -> 0
C222: 1 | D222: =C222+1 -> 2 | E222: =D222+1 -> 3 | F222: =E222+1 -> 4 | G222: =F222+1 -> 5 | H222: =G222+1 -> 6 | I222: =H222+1 -> 7 | J222: =I222+1 -> 8 | K222: =J222+1 -> 9 | L222: =K222+1 -> 10 | M222: =#REF!+1 -> #REF! | N222: =M222+1 -> #REF!

Sheet Anbazhagan-TS
L1: =PRE!N1 -> 29 | S1: date 1 | U1: date 2 | W1: date 3 | Y1: date 4 | AA1: date 5 | AC1: date 6 | AE1: date 7 | AG1: date 8 | AI1: date 9 | AK1: date 10 | AM1: date 11 | AO1: date 12 | AQ1: date 13 | AS1: date 14 | AU1: date 15 | AW1: date 16 | AY1: date 17 | BA1: date 18 | BC1: date 19 | BE1: date 20 | BG1: date 21 | BI1: date 22 | BK1: date 23 | BM1: date 24 | BO1: date 25 | BQ1: date 26 | BS1: date 27 | BU1: date 28 | BW1: date 29 | BY1: date 30 | CA1: date 31
B2: Project: | G2: Costing Report | Q2: Upto | R2: xxxx | S2: date 1 | T2: =S2 -> date 1 | U2: date 2 | V2: =U2 -> date 2 | W2: date 3 | X2: =W2 -> date 3 | Y2: date 4 | Z2: =Y2 -> date 4 | AA2: date 5 | AB2: =AA2 -> date 5 | AC2: date 6 | AD2: =AC2 -> date 6 | AE2: date 7 | AF2: =AE2 -> date 7 | AG2: date 8 | AH2: =AG2 -> date 8 | AI2: date 9 | AJ2: =AI2 -> date 9 | AK2: date 10 | AL2: =AK2 -> date 10 | AM2: date 11 | AN2: =AM2 -> date 11 | AO2: date 12 | AP2: =AO2 -> date 12 | AQ2: date 13 | AR2: =AQ2 -> date 13 | AS2: date 14 | AT2: =AS2 -> date 14 | AU2: date 15 | AV2: =AU2 -> date 15 | AW2: date 16 | AX2: =AW2 -> date 16 | AY2: date 17 | AZ2: =AY2 -> date 17 | BA2: date 18 | BB2: =BA2 -> date 18 | BC2: date 19 | BD2: =BC2 -> date 19 | BE2: date 20 | BF2: =BE2 -> date 20 | BG2: date 21 | BH2: =BG2 -> date 21 | BI2: date 22 | BJ2: =BI2 -> date 22 | BK2: date 23 | BL2: =BK2 -> date 23 | BM2: date 24 | BN2: =BM2 -> date 24 | BO2: date 25 | BP2: =BO2 -> date 25 | BQ2: date 26 | BR2: =BQ2 -> date 26 | BS2: date 27 | BT2: =BS2 -> date 27 | BU2: date 28 | BV2: =BU2 -> date 28 | BW2: date 29 | BX2: =BW2 -> date 29 | BY2: date 30 | BZ2: =BY2 -> date 30 | CA2: date 31 | CB2: =CA2 -> date 31
B3: Project Manager : | K3: Worked days | L3: xxxx
B4: E.Material | H4: F.SubContractor | N4: A.Man Power: | S4: Day | T4: Night | U4: Day | V4: Night | W4: Day | X4: Night | Y4: Day | Z4: Night | AA4: Day | AB4: Night | AC4: Day | AD4: Night | AE4: Day | AF4: Night | AG4: Day | AH4: Night | AI4: Day | AJ4: Night | AK4: Day | AL4: Night | AM4: Day | AN4: Night | AO4: Day | AP4: Night | AQ4: Day | AR4: Night | AS4: Day | AT4: Night | AU4: Day | AV4: Night | AW4: Day | AX4: Night | AY4: Day | AZ4: Night | BA4: Day | BB4: Night | BC4: Day | BD4: Night | BE4: Day | BF4: Night | BG4: Day | BH4: Night | BI4: Day | BJ4: Night | BK4: Day | BL4: Night | BM4: Day | BN4: Night | BO4: Day | BP4: Night | BQ4: Day | BR4: Night | BS4: Day | BT4: Night | BU4: Day | BV4: Night | BW4: Day | BX4: Night | BY4: Day | BZ4: Night | CA4: Day | CB4: Night
A5: BOQ # | B5: Decsription | C5: Unit | D5: Rate | E5: For the day | F5: Quantity | G5: Total Amount | H5: Decsription | I5: Unit | J5: Rate | K5: For the day | L5: Quantity | M5: Total Amount | N5: Decsription | O5: Rate | P5: Nos | Q5: For the day | R5: Total Amount
B6: Royalty Charges | C6: Cum | E6: =E32+E36+E39+E53 -> 0 | F6: =H32+H36+H39+H53 -> 0 | G6: =D6*F6 -> 0 | H6: Relocate existing Electrical H.T | I6: lin.m | M6: =J6*L6 -> 0 | N6: Helper E | P6: =SUMPRODUCT(($S$2:$CB$2<=$R$2)*1,($S$4:$CB$4=$S$4)*1,S6:CB6)+SUMPRODUCT(($S$2:$CB$2<=$R$2)*1,($S$4:$CB$4=$T$4)*1,S6:CB6) -> 0 | Q6: =SUMPRODUCT(($S$2:$CB$2=$R$2)*1,($S$4:$CB$4=$S$4)*1,S6:CB6)+SUMPRODUCT(($S$2:$CB$2=$R$2)*1,($S$4:$CB$4=$T$4)*1,S6:CB6) -> 0 | R6: =O6*P6 -> 0 | S6: =SUMIF('Anbazhagan-TS-1'!$C$74:$C$93,$N6,'Anbazhagan-TS-1'!F$74:F$93) -> 0 | T6: =SUMIF('Anbazhagan-TS-1'!$C$74:$C$93,$N6,'Anbazhagan-TS-1'!G$74:G$93) -> 0 | U6: =SUMIF('Anbazhagan-TS-1'!$C$74:$C$93,$N6,'Anbazhagan-TS-1'!H$74:H$93) -> 0 | V6: =SUMIF('Anbazhagan-TS-1'!$C$74:$C$93,$N6,'Anbazhagan-TS-1'!I$74:I$93) -> 0 | W6: =SUMIF('Anbazhagan-TS-1'!$C$74:$C$93,$N6,'Anbazhagan-TS-1'!J$74:J$93) -> 0 | X6: =SUMIF('Anbazhagan-TS-1'!$C$74:$C$93,$N6,'Anbazhagan-TS-1'!K$74:K$93) -> 0 | Y6: =SUMIF('Anbazhagan-TS-1'!$C$74:$C$93,$N6,'Anbazhagan-TS-1'!L$74:L$93) -> 0 | Z6: =SUMIF('Anbazhagan-TS-1'!$C$74:$C$93,$N6,'Anbazhagan-TS-1'!M$74:M$93) -> 0 | ... CB6: =SUMIF('Anbazhagan-TS-1'!$C$74:$C$93,$N6,'Anbazhagan-TS-1'!BO$74:BO$93) -> 0
B7: Prime Coat (MC 70 or Eqv.) | C7: Kg | E7: =E40 -> 0 | F7: =H40 -> 0 | G7: =D7*F7 -> 0 | H7: Relocate existing Telephone | I7: lin.m | M7: =J7*L7 -> 0 | N7: Steel Fixer E | P7: =SUMPRODUCT(($S$2:$CB$2<=$R$2)*1,($S$4:$CB$4=$S$4)*1,S7:CB7)+SUMPRODUCT(($S$2:$CB$2<=$R$2)*1,($S$4:$CB$4=$T$4)*1,S7:CB7) -> 0 | Q7: =SUMPRODUCT(($S$2:$CB$2=$R$2)*1,($S$4:$CB$4=$S$4)*1,S7:CB7)+SUMPRODUCT(($S$2:$CB$2=$R$2)*1,($S$4:$CB$4=$T$4)*1,S7:CB7) -> 0 | R7: =O7*P7 -> 0 | S7: =SUMIF('Anbazhagan-TS-1'!$C$74:$C$93,$N7,'Anbazhagan-TS-1'!F$74:F$93) -> 0 | T7: =SUMIF('Anbazhagan-TS-1'!$C$74:$C$93,$N7,'Anbazhagan-TS-1'!G$74:G$93) -> 0 | U7: =SUMIF('Anbazhagan-TS-1'!$C$74:$C$93,$N7,'Anbazhagan-TS-1'!H$74:H$93) -> 0 | V7: =SUMIF('Anbazhagan-TS-1'!$C$74:$C$93,$N7,'Anbazhagan-TS-1'!I$74:I$93) -> 0 | W7: =SUMIF('Anbazhagan-TS-1'!$C$74:$C$93,$N7,'Anbazhagan-TS-1'!J$74:J$93) -> 0 | X7: =SUMIF('Anbazhagan-TS-1'!$C$74:$C$93,$N7,'Anbazhagan-TS-1'!K$74:K$93) -> 0 | Y7: =SUMIF('Anbazhagan-TS-1'!$C$74:$C$93,$N7,'Anbazhagan-TS-1'!L$74:L$93) -> 0 | Z7: =SUMIF('Anbazhagan-TS-1'!$C$74:$C$93,$N7,'Anbazhagan-TS-1'!M$74:M$93) -> 0 | ... CB7: =SUMIF('Anbazhagan-TS-1'!$C$74:$C$93,$N7,'Anbazhagan-TS-1'!BO$74:BO$93) -> 0
B8: Tack Coat | C8: Kg | G8: =D8*F8 -> 0 | H8: Water | I8: Trip | M8: =J8*L8 -> 0 | N8: Carpenter E | P8: =SUMPRODUCT(($S$2:$CB$2<=$R$2)*1,($S$4:$CB$4=$S$4)*1,S8:CB8)+SUMPRODUCT(($S$2:$CB$2<=$R$2)*1,($S$4:$CB$4=$T$4)*1,S8:CB8) -> 0 | Q8: =SUMPRODUCT(($S$2:$CB$2=$R$2)*1,($S$4:$CB$4=$S$4)*1,S8:CB8)+SUMPRODUCT(($S$2:$CB$2=$R$2)*1,($S$4:$CB$4=$T$4)*1,S8:CB8) -> 0 | R8: =O8*P8 -> 0 | S8: =SUMIF('Anbazhagan-TS-1'!$C$74:$C$93,$N8,'Anbazhagan-TS-1'!F$74:F$93) -> 0 | T8: =SUMIF('Anbazhagan-TS-1'!$C$74:$C$93,$N8,'Anbazhagan-TS-1'!G$74:G$93) -> 0 | U8: =SUMIF('Anbazhagan-TS-1'!$C$74:$C$93,$N8,'Anbazhagan-TS-1'!H$74:H$93) -> 0 | V8: =SUMIF('Anbazhagan-TS-1'!$C$74:$C$93,$N8,'Anbazhagan-TS-1'!I$74:I$93) -> 0 | W8: =SUMIF('Anbazhagan-TS-1'!$C$74:$C$93,$N8,'Anbazhagan-TS-1'!J$74:J$93) -> 0 | X8: =SUMIF('Anbazhagan-TS-1'!$C$74:$C$93,$N8,'Anbazhagan-TS-1'!K$74:K$93) -> 0 | Y8: =SUMIF('Anbazhagan-TS-1'!$C$74:$C$93,$N8,'Anbazhagan-TS-1'!L$74:L$93) -> 0 | Z8: =SUMIF('Anbazhagan-TS-1'!$C$74:$C$93,$N8,'Anbazhagan-TS-1'!M$74:M$93) -> 0 | ... CB8: =SUMIF('Anbazhagan-TS-1'!$C$74:$C$93,$N8,'Anbazhagan-TS-1'!BO$74:BO$93) -> 0
B9: Asphalt (In-house) - BBC | C9: MT | E9: =E42*2.45 -> 0 | F9: =H42*2.45 -> 0 | G9: =D9*F9 -> 0 | N9: Mason | P9: =SUMPRODUCT(($S$2:$CB$2<=$R$2)*1,($S$4:$CB$4=$S$4)*1,S9:CB9)+SUMPRODUCT(($S$2:$CB$2<=$R$2)*1,($S$4:$CB$4=$T$4)*1,S9:CB9) -> 0 | Q9: =SUMPRODUCT(($S$2:$CB$2=$R$2)*1,($S$4:$CB$4=$S$4)*1,S9:CB9)+SUMPRODUCT(($S$2:$CB$2=$R$2)*1,($S$4:$CB$4=$T$4)*1,S9:CB9) -> 0 | R9: =O9*P9 -> 0 | S9: =SUMIF('Anbazhagan-TS-1'!$C$74:$C$93,$N9,'Anbazhagan-TS-1'!F$74:F$93) -> 0 | T9: =SUMIF('Anbazhagan-TS-1'!$C$74:$C$93,$N9,'Anbazhagan-TS-1'!G$74:G$93) -> 0 | U9: =SUMIF('Anbazhagan-TS-1'!$C$74:$C$93,$N9,'Anbazhagan-TS-1'!H$74:H$93) -> 0 | V9: =SUMIF('Anbazhagan-TS-1'!$C$74:$C$93,$N9,'Anbazhagan-TS-1'!I$74:I$93) -> 0 | W9: =SUMIF('Anbazhagan-TS-1'!$C$74:$C$93,$N9,'Anbazhagan-TS-1'!J$74:J$93) -> 0 | X9: =SUMIF('Anbazhagan-TS-1'!$C$74:$C$93,$N9,'Anbazhagan-TS-1'!K$74:K$93) -> 0 | Y9: =SUMIF('Anbazhagan-TS-1'!$C$74:$C$93,$N9,'Anbazhagan-TS-1'!L$74:L$93) -> 0 | Z9: =SUMIF('Anbazhagan-TS-1'!$C$74:$C$93,$N9,'Anbazhagan-TS-1'!M$74:M$93) -> 0 | ... CB9: =SUMIF('Anbazhagan-TS-1'!$C$74:$C$93,$N9,'Anbazhagan-TS-1'!BO$74:BO$93) -> 0
B10: Asphalt (In-house) - BWC | C10: MT | E10: =E43*2.45 -> 0 | F10: =H43*2.45 -> 0 | G10: =D10*F10 -> 0 | N10: Hdd Exp. | P10: =SUMPRODUCT(($S$2:$CB$2<=$R$2)*1,($S$4:$CB$4=$S$4)*1,S10:CB10)+SUMPRODUCT(($S$2:$CB$2<=$R$2)*1,($S$4:$CB$4=$T$4)*1,S10:CB10) -> 0 | Q10: =SUMPRODUCT(($S$2:$CB$2=$R$2)*1,($S$4:$CB$4=$S$4)*1,S10:CB10)+SUMPRODUCT(($S$2:$CB$2=$R$2)*1,($S$4:$CB$4=$T$4)*1,S10:CB10) -> 0 | R10: =O10*P10 -> 0 | S10: =SUMIF('Anbazhagan-TS-1'!$C$74:$C$93,$N10,'Anbazhagan-TS-1'!F$74:F$93) -> 0 | T10: =SUMIF('Anbazhagan-TS-1'!$C$74:$C$93,$N10,'Anbazhagan-TS-1'!G$74:G$93) -> 0 | U10: =SUMIF('Anbazhagan-TS-1'!$C$74:$C$93,$N10,'Anbazhagan-TS-1'!H$74:H$93) -> 0 | V10: =SUMIF('Anbazhagan-TS-1'!$C$74:$C$93,$N10,'Anbazhagan-TS-1'!I$74:I$93) -> 0 | W10: =SUMIF('Anbazhagan-TS-1'!$C$74:$C$93,$N10,'Anbazhagan-TS-1'!J$74:J$93) -> 0 | X10: =SUMIF('Anbazhagan-TS-1'!$C$74:$C$93,$N10,'Anbazhagan-TS-1'!K$74:K$93) -> 0 | Y10: =SUMIF('Anbazhagan-TS-1'!$C$74:$C$93,$N10,'Anbazhagan-TS-1'!L$74:L$93) -> 0 | Z10: =SUMIF('Anbazhagan-TS-1'!$C$74:$C$93,$N10,'Anbazhagan-TS-1'!M$74:M$93) -> 0 | ... CB10: =SUMIF('Anbazhagan-TS-1'!$C$74:$C$93,$N10,'Anbazhagan-TS-1'!BO$74:BO$93) -> 0
B11: From Store | C11: LS | E11: =F11/L1 -> 0 | G11: =D11*F11 -> 0 | N11: Hdd Nat. | P11: =(SUMPRODUCT(($S$2:$CB$2<=$R$2)*1,($S$4:$CB$4=$S$4)*1,S11:CB11)+SUMPRODUCT(($S$2:$CB$2<=$R$2)*1,($S$4:$CB$4=$T$4)*1,S11:CB11)) -> 0 | Q11: =SUMPRODUCT(($S$2:$CB$2=$R$2)*1,($S$4:$CB$4=$S$4)*1,S11:CB11)+SUMPRODUCT(($S$2:$CB$2=$R$2)*1,($S$4:$CB$4=$T$4)*1,S11:CB11) -> 0 | R11: =O11*P11 -> 0 | S11: =SUMIF('Anbazhagan-TS-1'!$C$74:$C$93,$N11,'Anbazhagan-TS-1'!F$74:F$93) -> 0 | T11: =SUMIF('Anbazhagan-TS-1'!$C$74:$C$93,$N11,'Anbazhagan-TS-1'!G$74:G$93) -> 0 | U11: =SUMIF('Anbazhagan-TS-1'!$C$74:$C$93,$N11,'Anbazhagan-TS-1'!H$74:H$93) -> 0 | V11: =SUMIF('Anbazhagan-TS-1'!$C$74:$C$93,$N11,'Anbazhagan-TS-1'!I$74:I$93) -> 0 | W11: =SUMIF('Anbazhagan-TS-1'!$C$74:$C$93,$N11,'Anbazhagan-TS-1'!J$74:J$93) -> 0 | X11: =SUMIF('Anbazhagan-TS-1'!$C$74:$C$93,$N11,'Anbazhagan-TS-1'!K$74:K$93) -> 0 | Y11: =SUMIF('Anbazhagan-TS-1'!$C$74:$C$93,$N11,'Anbazhagan-TS-1'!L$74:L$93) -> 0 | Z11: =SUMIF('Anbazhagan-TS-1'!$C$74:$C$93,$N11,'Anbazhagan-TS-1'!M$74:M$93) -> 0 | ... CB11: =SUMIF('Anbazhagan-TS-1'!$C$74:$C$93,$N11,'Anbazhagan-TS-1'!BO$74:BO$93) -> 0
B12: Sand Cost | C12: Cum | E12: =(E42+E43)*A12 -> 0 | F12: =(H42+H43)*A12 -> 0 | G12: =D12*F12 -> 0 | N12: Optr Exp. | P12: =SUMPRODUCT(($S$2:$CB$2<=$R$2)*1,($S$4:$CB$4=$S$4)*1,S12:CB12)+SUMPRODUCT(($S$2:$CB$2<=$R$2)*1,($S$4:$CB$4=$T$4)*1,S12:CB12) -> 0 | Q12: =SUMPRODUCT(($S$2:$CB$2=$R$2)*1,($S$4:$CB$4=$S$4)*1,S12:CB12)+SUMPRODUCT(($S$2:$CB$2=$R$2)*1,($S$4:$CB$4=$T$4)*1,S12:CB12) -> 0 | R12: =O12*P12 -> 0 | S12: =SUMIF('Anbazhagan-TS-1'!$C$74:$C$93,$N12,'Anbazhagan-TS-1'!F$74:F$93) -> 0 | T12: =SUMIF('Anbazhagan-TS-1'!$C$74:$C$93,$N12,'Anbazhagan-TS-1'!G$74:G$93) -> 0 | U12: =SUMIF('Anbazhagan-TS-1'!$C$74:$C$93,$N12,'Anbazhagan-TS-1'!H$74:H$93) -> 0 | V12: =SUMIF('Anbazhagan-TS-1'!$C$74:$C$93,$N12,'Anbazhagan-TS-1'!I$74:I$93) -> 0 | W12: =SUMIF('Anbazhagan-TS-1'!$C$74:$C$93,$N12,'Anbazhagan-TS-1'!J$74:J$93) -> 0 | X12: =SUMIF('Anbazhagan-TS-1'!$C$74:$C$93,$N12,'Anbazhagan-TS-1'!K$74:K$93) -> 0 | Y12: =SUMIF('Anbazhagan-TS-1'!$C$74:$C$93,$N12,'Anbazhagan-TS-1'!L$74:L$93) -> 0 | Z12: =SUMIF('Anbazhagan-TS-1'!$C$74:$C$93,$N12,'Anbazhagan-TS-1'!M$74:M$93) -> 0 | ... CB12: =SUMIF('Anbazhagan-TS-1'!$C$74:$C$93,$N12,'Anbazhagan-TS-1'!BO$74:BO$93) -> 0
B13: Aggregate cost (BNRP) | C13: Cum | E13: =E39*$A$13 -> 0 | F13: =H39*$A$13 -> 0 | G13: =D13*F13 -> 0 | N13: Optr Nat. | P13: =SUMPRODUCT(($S$2:$CB$2<=$R$2)*1,($S$4:$CB$4=$S$4)*1,S13:CB13)+SUMPRODUCT(($S$2:$CB$2<=$R$2)*1,($S$4:$CB$4=$T$4)*1,S13:CB13) -> 0 | Q13: =SUMPRODUCT(($S$2:$CB$2=$R$2)*1,($S$4:$CB$4=$S$4)*1,S13:CB13)+SUMPRODUCT(($S$2:$CB$2=$R$2)*1,($S$4:$CB$4=$T$4)*1,S13:CB13) -> 0 | R13: =O13*P13 -> 0 | S13: =SUMIF('Anbazhagan-TS-1'!$C$74:$C$93,$N13,'Anbazhagan-TS-1'!F$74:F$93) -> 0 | T13: =SUMIF('Anbazhagan-TS-1'!$C$74:$C$93,$N13,'Anbazhagan-TS-1'!G$74:G$93) -> 0 | U13: =SUMIF('Anbazhagan-TS-1'!$C$74:$C$93,$N13,'Anbazhagan-TS-1'!H$74:H$93) -> 0 | V13: =SUMIF('Anbazhagan-TS-1'!$C$74:$C$93,$N13,'Anbazhagan-TS-1'!I$74:I$93) -> 0 | W13: =SUMIF('Anbazhagan-TS-1'!$C$74:$C$93,$N13,'Anbazhagan-TS-1'!J$74:J$93) -> 0 | X13: =SUMIF('Anbazhagan-TS-1'!$C$74:$C$93,$N13,'Anbazhagan-TS-1'!K$74:K$93) -> 0 | Y13: =SUMIF('Anbazhagan-TS-1'!$C$74:$C$93,$N13,'Anbazhagan-TS-1'!L$74:L$93) -> 0 | Z13: =SUMIF('Anbazhagan-TS-1'!$C$74:$C$93,$N13,'Anbazhagan-TS-1'!M$74:M$93) -> 0 | ... CB13: =SUMIF('Anbazhagan-TS-1'!$C$74:$C$93,$N13,'Anbazhagan-TS-1'!BO$74:BO$93) -> 0
G14: =D14*F14 -> 0 | N14: Ldd Nat. | P14: =SUMPRODUCT(($S$2:$CB$2<=$R$2)*1,($S$4:$CB$4=$S$4)*1,S14:CB14)+SUMPRODUCT(($S$2:$CB$2<=$R$2)*1,($S$4:$CB$4=$T$4)*1,S14:CB14) -> 0 | Q14: =SUMPRODUCT(($S$2:$CB$2=$R$2)*1,($S$4:$CB$4=$S$4)*1,S14:CB14)+SUMPRODUCT(($S$2:$CB$2=$R$2)*1,($S$4:$CB$4=$T$4)*1,S14:CB14) -> 0 | R14: =O14*P14 -> 0 | S14: =SUMIF('Anbazhagan-TS-1'!$C$74:$C$93,$N14,'Anbazhagan-TS-1'!F$74:F$93) -> 0 | T14: =SUMIF('Anbazhagan-TS-1'!$C$74:$C$93,$N14,'Anbazhagan-TS-1'!G$74:G$93) -> 0 | U14: =SUMIF('Anbazhagan-TS-1'!$C$74:$C$93,$N14,'Anbazhagan-TS-1'!H$74:H$93) -> 0 | V14: =SUMIF('Anbazhagan-TS-1'!$C$74:$C$93,$N14,'Anbazhagan-TS-1'!I$74:I$93) -> 0 | W14: =SUMIF('Anbazhagan-TS-1'!$C$74:$C$93,$N14,'Anbazhagan-TS-1'!J$74:J$93) -> 0 | X14: =SUMIF('Anbazhagan-TS-1'!$C$74:$C$93,$N14,'Anbazhagan-TS-1'!K$74:K$93) -> 0 | Y14: =SUMIF('Anbazhagan-TS-1'!$C$74:$C$93,$N14,'Anbazhagan-TS-1'!L$74:L$93) -> 0 | Z14: =SUMIF('Anbazhagan-TS-1'!$C$74:$C$93,$N14,'Anbazhagan-TS-1'!M$74:M$93) -> 0 | ... CB14: =SUMIF('Anbazhagan-TS-1'!$C$74:$C$93,$N14,'Anbazhagan-TS-1'!BO$74:BO$93) -> 0
G15: =D15*F15 -> 0 | N15: Chargehand | P15: =SUMPRODUCT(($S$2:$CB$2<=$R$2)*1,($S$4:$CB$4=$S$4)*1,S15:CB15)+SUMPRODUCT(($S$2:$CB$2<=$R$2)*1,($S$4:$CB$4=$T$4)*1,S15:CB15) -> 0 | Q15: =SUMPRODUCT(($S$2:$CB$2=$R$2)*1,($S$4:$CB$4=$S$4)*1,S15:CB15)+SUMPRODUCT(($S$2:$CB$2=$R$2)*1,($S$4:$CB$4=$T$4)*1,S15:CB15) -> 0 | R15: =O15*P15 -> 0 | S15: =SUMIF('Anbazhagan-TS-1'!$C$74:$C$93,$N15,'Anbazhagan-TS-1'!F$74:F$93) -> 0 | T15: =SUMIF('Anbazhagan-TS-1'!$C$74:$C$93,$N15,'Anbazhagan-TS-1'!G$74:G$93) -> 0 | U15: =SUMIF('Anbazhagan-TS-1'!$C$74:$C$93,$N15,'Anbazhagan-TS-1'!H$74:H$93) -> 0 | V15: =SUMIF('Anbazhagan-TS-1'!$C$74:$C$93,$N15,'Anbazhagan-TS-1'!I$74:I$93) -> 0 | W15: =SUMIF('Anbazhagan-TS-1'!$C$74:$C$93,$N15,'Anbazhagan-TS-1'!J$74:J$93) -> 0 | X15: =SUMIF('Anbazhagan-TS-1'!$C$74:$C$93,$N15,'Anbazhagan-TS-1'!K$74:K$93) -> 0 | Y15: =SUMIF('Anbazhagan-TS-1'!$C$74:$C$93,$N15,'Anbazhagan-TS-1'!L$74:L$93) -> 0 | Z15: =SUMIF('Anbazhagan-TS-1'!$C$74:$C$93,$N15,'Anbazhagan-TS-1'!M$74:M$93) -> 0 | ... CB15: =SUMIF('Anbazhagan-TS-1'!$C$74:$C$93,$N15,'Anbazhagan-TS-1'!BO$74:BO$93) -> 0
G16: =D16*F16 -> 0 | R16: =O16*P16 -> 0 | S16: =SUMIF('Anbazhagan-TS-1'!$C$74:$C$93,$N16,'Anbazhagan-TS-1'!F$74:F$93) -> 0 | T16: =SUMIF('Anbazhagan-TS-1'!$C$74:$C$93,$N16,'Anbazhagan-TS-1'!G$74:G$93) -> 0 | U16: =SUMIF('Anbazhagan-TS-1'!$C$74:$C$93,$N16,'Anbazhagan-TS-1'!H$74:H$93) -> 0 | V16: =SUMIF('Anbazhagan-TS-1'!$C$74:$C$93,$N16,'Anbazhagan-TS-1'!I$74:I$93) -> 0 | W16: =SUMIF('Anbazhagan-TS-1'!$C$74:$C$93,$N16,'Anbazhagan-TS-1'!J$74:J$93) -> 0 | X16: =SUMIF('Anbazhagan-TS-1'!$C$74:$C$93,$N16,'Anbazhagan-TS-1'!K$74:K$93) -> 0 | Y16: =SUMIF('Anbazhagan-TS-1'!$C$74:$C$93,$N16,'Anbazhagan-TS-1'!L$74:L$93) -> 0 | Z16: =SUMIF('Anbazhagan-TS-1'!$C$74:$C$93,$N16,'Anbazhagan-TS-1'!M$74:M$93) -> 0 | ... CB16: =SUMIF('Anbazhagan-TS-1'!$C$74:$C$93,$N16,'Anbazhagan-TS-1'!BO$74:BO$93) -> 0
G17: =D17*F17 -> 0
G18: =D18*F18 -> 0
G19: =D19*F19 -> 0
G20: =D20*F20 -> 0
G21: =D21*F21 -> 0
G22: =D22*F22 -> 0
G23: =D23*F23 -> 0
B24: Unit Over Heads | C24: LS | D24: 0.0172 | E24: =E60*D24 -> 0 | F24: =I60 -> 0 | G24: =D24*F24 -> 0 | N24: Staff | O24: 1
B25: Total | E25: =SUMPRODUCT(E5:E23,D5:D23)+E24 -> 0 | G25: =SUM(G6:G15) -> 0 | H25: Total | K25: =SUMPRODUCT(K5:K23,J5:J23)+K24 -> 0 | M25: =SUM(M6:M24) -> 0 | N25: Total | P25: =SUM(P6:P23) -> 0 | Q25: =SUMPRODUCT(Q5:Q24,O5:O24) -> 0 | R25: =SUM(R6:R23) -> 0
A26: BOQ # | B26: BOQ Description | C26: Unit | D26: Rate | E26: For the day | F26: Proj Qty | G26: Proj Amnt | H26: Ach Qty | I26: Ach Amnt | J26: % Ach Wrt Pro | N26: B.Catering/Admin: | O26: Rate | P26: Nos | Q26: For the day | R26: Total Amount
A27: 2.1.5(i) | B27: Clear site of all trees less than 300mm | C27: Sq.m | I27: =H27*D27 -> 0 | J27: =IFERROR(H27/F27,"") | N27: Admin/ Catering Charges | P27: =P25 -> 0 | Q27: =SUM(Q5:Q24) -> 0 | R27: =O27*P27 -> 0
A28: 2.2.5(viii) | B28: Removal and disposal of bituminous pavement | C28: Cum | I28: =H28*D28 -> 0 | J28: =IFERROR(H28/F28,"") | R28: =O28*Q28 -> 0
A29: 2.3.6(i) | B29: Unclassified excavation | C29: Cum | I29: =H29*D29 -> 0 | J29: =IFERROR(H29/F29,"") | N29: Total | Q29: =Q27*O27 -> 0 | R29: =SUM(R27:R28) -> 0
A30: 2.4.6(i)a1 | B30: Borrow excavation to embankment-Extraction and screening | C30: Cum | I30: =H30*D30 -> 0 | J30: =IFERROR(H30/F30,"") | N30: C.Machinery:
A31: 2.4.6(i)a2 | B31: Borrow excavation to embankment-Transportation | C31: Cum | I31: =H31*D31 -> 0 | J31: =IFERROR(H31/F31,"") | N31: Decsription | O31: Rate per Hr | P31: Nos | Q31: For the day | R31: Total Amount
A32: 2.4.6(i)a2 | B32: Borrow excavation to Embankment-Hauling and compaction | C32: Cum | I32: =H32*D32 -> 0 | J32: =IFERROR(H32/F32,"") | N32: Back Hoe Loader | P32: =SUMPRODUCT(($S$2:$CB$2<=$R$2)*1,($S$4:$CB$4=$S$4)*1,S32:CB32)+SUMPRODUCT(($S$2:$CB$2<=$R$2)*1,($S$4:$CB$4=$T$4)*1,S32:CB32)*0.75 -> 0 | Q32: =SUMPRODUCT(($S$2:$CB$2=$R$2)*1,($S$4:$CB$4=$S$4)*1,S32:CB32)+SUMPRODUCT(($S$2:$CB$2=$R$2)*1,($S$4:$CB$4=$T$4)*1,S32:CB32)*0.75 -> 0 | R32: =O32*P32 -> 0 | S32: =SUMIF('Anbazhagan-TS-1'!$C$9:$C$68,$N32,'Anbazhagan-TS-1'!F$9:F$68) -> 0 | T32: =SUMIF('Anbazhagan-TS-1'!$C$9:$C$68,$N32,'Anbazhagan-TS-1'!G$9:G$68) -> 0 | U32: =SUMIF('Anbazhagan-TS-1'!$C$9:$C$68,$N32,'Anbazhagan-TS-1'!H$9:H$68) -> 0 | V32: =SUMIF('Anbazhagan-TS-1'!$C$9:$C$68,$N32,'Anbazhagan-TS-1'!I$9:I$68) -> 0 | W32: =SUMIF('Anbazhagan-TS-1'!$C$9:$C$68,$N32,'Anbazhagan-TS-1'!J$9:J$68) -> 0 | X32: =SUMIF('Anbazhagan-TS-1'!$C$9:$C$68,$N32,'Anbazhagan-TS-1'!K$9:K$68) -> 0 | Y32: =SUMIF('Anbazhagan-TS-1'!$C$9:$C$68,$N32,'Anbazhagan-TS-1'!L$9:L$68) -> 0 | Z32: =SUMIF('Anbazhagan-TS-1'!$C$9:$C$68,$N32,'Anbazhagan-TS-1'!M$9:M$68) -> 0 | ... CB32: =SUMIF('Anbazhagan-TS-1'!$C$9:$C$68,$N32,'Anbazhagan-TS-1'!BO$9:BO$68) -> 0
A33: 2.6.6(i) | B33: Subgrade preparation in cut | C33: Sqm | I33: =H33*D33 -> 0 | J33: =IFERROR(H33/F33,"") | N33: Back Hoe Loader (Hire) | P33: =SUMPRODUCT(($S$2:$CB$2<=$R$2)*1,($S$4:$CB$4=$S$4)*1,S33:CB33)+SUMPRODUCT(($S$2:$CB$2<=$R$2)*1,($S$4:$CB$4=$T$4)*1,S33:CB33)*0.75 -> 0 | Q33: =SUMPRODUCT(($S$2:$CB$2=$R$2)*1,($S$4:$CB$4=$S$4)*1,S33:CB33)+SUMPRODUCT(($S$2:$CB$2=$R$2)*1,($S$4:$CB$4=$T$4)*1,S33:CB33)*0.75 -> 0 | R33: =O33*P33 -> 0 | S33: =SUMIF('Anbazhagan-TS-1'!$C$9:$C$68,$N33,'Anbazhagan-TS-1'!F$9:F$68) -> 0 | T33: =SUMIF('Anbazhagan-TS-1'!$C$9:$C$68,$N33,'Anbazhagan-TS-1'!G$9:G$68) -> 0 | U33: =SUMIF('Anbazhagan-TS-1'!$C$9:$C$68,$N33,'Anbazhagan-TS-1'!H$9:H$68) -> 0 | V33: =SUMIF('Anbazhagan-TS-1'!$C$9:$C$68,$N33,'Anbazhagan-TS-1'!I$9:I$68) -> 0 | W33: =SUMIF('Anbazhagan-TS-1'!$C$9:$C$68,$N33,'Anbazhagan-TS-1'!J$9:J$68) -> 0 | X33: =SUMIF('Anbazhagan-TS-1'!$C$9:$C$68,$N33,'Anbazhagan-TS-1'!K$9:K$68) -> 0 | Y33: =SUMIF('Anbazhagan-TS-1'!$C$9:$C$68,$N33,'Anbazhagan-TS-1'!L$9:L$68) -> 0 | Z33: =SUMIF('Anbazhagan-TS-1'!$C$9:$C$68,$N33,'Anbazhagan-TS-1'!M$9:M$68) -> 0 | ... CB33: =SUMIF('Anbazhagan-TS-1'!$C$9:$C$68,$N33,'Anbazhagan-TS-1'!BO$9:BO$68) -> 0
A34: 3.2.6(ii)1 | B34: GSB (Class B)-Extraction and Screening | C34: Cum | I34: =H34*D34 -> 0 | J34: =IFERROR(H34/F34,"") | N34: Wheel Loader | P34: =SUMPRODUCT(($S$2:$CB$2<=$R$2)*1,($S$4:$CB$4=$S$4)*1,S34:CB34)+SUMPRODUCT(($S$2:$CB$2<=$R$2)*1,($S$4:$CB$4=$T$4)*1,S34:CB34)*0.75 -> 0 | Q34: =SUMPRODUCT(($S$2:$CB$2=$R$2)*1,($S$4:$CB$4=$S$4)*1,S34:CB34)+SUMPRODUCT(($S$2:$CB$2=$R$2)*1,($S$4:$CB$4=$T$4)*1,S34:CB34)*0.75 -> 0 | R34: =O34*P34 -> 0 | S34: =SUMIF('Anbazhagan-TS-1'!$C$9:$C$68,$N34,'Anbazhagan-TS-1'!F$9:F$68) -> 0 | T34: =SUMIF('Anbazhagan-TS-1'!$C$9:$C$68,$N34,'Anbazhagan-TS-1'!G$9:G$68) -> 0 | U34: =SUMIF('Anbazhagan-TS-1'!$C$9:$C$68,$N34,'Anbazhagan-TS-1'!H$9:H$68) -> 0 | V34: =SUMIF('Anbazhagan-TS-1'!$C$9:$C$68,$N34,'Anbazhagan-TS-1'!I$9:I$68) -> 0 | W34: =SUMIF('Anbazhagan-TS-1'!$C$9:$C$68,$N34,'Anbazhagan-TS-1'!J$9:J$68) -> 0 | X34: =SUMIF('Anbazhagan-TS-1'!$C$9:$C$68,$N34,'Anbazhagan-TS-1'!K$9:K$68) -> 0 | Y34: =SUMIF('Anbazhagan-TS-1'!$C$9:$C$68,$N34,'Anbazhagan-TS-1'!L$9:L$68) -> 0 | Z34: =SUMIF('Anbazhagan-TS-1'!$C$9:$C$68,$N34,'Anbazhagan-TS-1'!M$9:M$68) -> 0 | ... CB34: =SUMIF('Anbazhagan-TS-1'!$C$9:$C$68,$N34,'Anbazhagan-TS-1'!BO$9:BO$68) -> 0
A35: 3.2.6(ii)2 | B35: GSB (Class B)-Transportation | C35: Cum | I35: =H35*D35 -> 0 | J35: =IFERROR(H35/F35,"") | N35: Bull Dozer | P35: =SUMPRODUCT(($S$2:$CB$2<=$R$2)*1,($S$4:$CB$4=$S$4)*1,S35:CB35)+SUMPRODUCT(($S$2:$CB$2<=$R$2)*1,($S$4:$CB$4=$T$4)*1,S35:CB35)*0.75 -> 0 | Q35: =SUMPRODUCT(($S$2:$CB$2=$R$2)*1,($S$4:$CB$4=$S$4)*1,S35:CB35)+SUMPRODUCT(($S$2:$CB$2=$R$2)*1,($S$4:$CB$4=$T$4)*1,S35:CB35)*0.75 -> 0 | R35: =O35*P35 -> 0 | S35: =SUMIF('Anbazhagan-TS-1'!$C$9:$C$68,$N35,'Anbazhagan-TS-1'!F$9:F$68) -> 0 | T35: =SUMIF('Anbazhagan-TS-1'!$C$9:$C$68,$N35,'Anbazhagan-TS-1'!G$9:G$68) -> 0 | U35: =SUMIF('Anbazhagan-TS-1'!$C$9:$C$68,$N35,'Anbazhagan-TS-1'!H$9:H$68) -> 0 | V35: =SUMIF('Anbazhagan-TS-1'!$C$9:$C$68,$N35,'Anbazhagan-TS-1'!I$9:I$68) -> 0 | W35: =SUMIF('Anbazhagan-TS-1'!$C$9:$C$68,$N35,'Anbazhagan-TS-1'!J$9:J$68) -> 0 | X35: =SUMIF('Anbazhagan-TS-1'!$C$9:$C$68,$N35,'Anbazhagan-TS-1'!K$9:K$68) -> 0 | Y35: =SUMIF('Anbazhagan-TS-1'!$C$9:$C$68,$N35,'Anbazhagan-TS-1'!L$9:L$68) -> 0 | Z35: =SUMIF('Anbazhagan-TS-1'!$C$9:$C$68,$N35,'Anbazhagan-TS-1'!M$9:M$68) -> 0 | ... CB35: =SUMIF('Anbazhagan-TS-1'!$C$9:$C$68,$N35,'Anbazhagan-TS-1'!BO$9:BO$68) -> 0
A36: 3.2.6(ii)3 | B36: GSB (Class B)-Hauling and compaction | C36: Cum | I36: =H36*D36 -> 0 | J36: =IFERROR(H36/F36,"") | N36: Excavator | P36: =SUMPRODUCT(($S$2:$CB$2<=$R$2)*1,($S$4:$CB$4=$S$4)*1,S36:CB36)+SUMPRODUCT(($S$2:$CB$2<=$R$2)*1,($S$4:$CB$4=$T$4)*1,S36:CB36)*0.75 -> 0 | Q36: =SUMPRODUCT(($S$2:$CB$2=$R$2)*1,($S$4:$CB$4=$S$4)*1,S36:CB36)+SUMPRODUCT(($S$2:$CB$2=$R$2)*1,($S$4:$CB$4=$T$4)*1,S36:CB36)*0.75 -> 0 | R36: =O36*P36 -> 0 | S36: =SUMIF('Anbazhagan-TS-1'!$C$9:$C$68,$N36,'Anbazhagan-TS-1'!F$9:F$68) -> 0 | T36: =SUMIF('Anbazhagan-TS-1'!$C$9:$C$68,$N36,'Anbazhagan-TS-1'!G$9:G$68) -> 0 | U36: =SUMIF('Anbazhagan-TS-1'!$C$9:$C$68,$N36,'Anbazhagan-TS-1'!H$9:H$68) -> 0 | V36: =SUMIF('Anbazhagan-TS-1'!$C$9:$C$68,$N36,'Anbazhagan-TS-1'!I$9:I$68) -> 0 | W36: =SUMIF('Anbazhagan-TS-1'!$C$9:$C$68,$N36,'Anbazhagan-TS-1'!J$9:J$68) -> 0 | X36: =SUMIF('Anbazhagan-TS-1'!$C$9:$C$68,$N36,'Anbazhagan-TS-1'!K$9:K$68) -> 0 | Y36: =SUMIF('Anbazhagan-TS-1'!$C$9:$C$68,$N36,'Anbazhagan-TS-1'!L$9:L$68) -> 0 | Z36: =SUMIF('Anbazhagan-TS-1'!$C$9:$C$68,$N36,'Anbazhagan-TS-1'!M$9:M$68) -> 0 | ... CB36: =SUMIF('Anbazhagan-TS-1'!$C$9:$C$68,$N36,'Anbazhagan-TS-1'!BO$9:BO$68) -> 0
A37: 3.3.6(ii)1 | B37: ABC (Class A)-Extraction and Screening | C37: Cum | I37: =H37*D37 -> 0 | J37: =IFERROR(H37/F37,"") | N37: Brackish Water Tanker | P37: =SUMPRODUCT(($S$2:$CB$2<=$R$2)*1,($S$4:$CB$4=$S$4)*1,S37:CB37)+SUMPRODUCT(($S$2:$CB$2<=$R$2)*1,($S$4:$CB$4=$T$4)*1,S37:CB37)*0.75 -> 0 | Q37: =SUMPRODUCT(($S$2:$CB$2=$R$2)*1,($S$4:$CB$4=$S$4)*1,S37:CB37)+SUMPRODUCT(($S$2:$CB$2=$R$2)*1,($S$4:$CB$4=$T$4)*1,S37:CB37)*0.75 -> 0 | R37: =O37*P37 -> 0 | S37: =SUMIF('Anbazhagan-TS-1'!$C$9:$C$68,$N37,'Anbazhagan-TS-1'!F$9:F$68) -> 0 | T37: =SUMIF('Anbazhagan-TS-1'!$C$9:$C$68,$N37,'Anbazhagan-TS-1'!G$9:G$68) -> 0 | U37: =SUMIF('Anbazhagan-TS-1'!$C$9:$C$68,$N37,'Anbazhagan-TS-1'!H$9:H$68) -> 0 | V37: =SUMIF('Anbazhagan-TS-1'!$C$9:$C$68,$N37,'Anbazhagan-TS-1'!I$9:I$68) -> 0 | W37: =SUMIF('Anbazhagan-TS-1'!$C$9:$C$68,$N37,'Anbazhagan-TS-1'!J$9:J$68) -> 0 | X37: =SUMIF('Anbazhagan-TS-1'!$C$9:$C$68,$N37,'Anbazhagan-TS-1'!K$9:K$68) -> 0 | Y37: =SUMIF('Anbazhagan-TS-1'!$C$9:$C$68,$N37,'Anbazhagan-TS-1'!L$9:L$68) -> 0 | Z37: =SUMIF('Anbazhagan-TS-1'!$C$9:$C$68,$N37,'Anbazhagan-TS-1'!M$9:M$68) -> 0 | ... CB37: =SUMIF('Anbazhagan-TS-1'!$C$9:$C$68,$N37,'Anbazhagan-TS-1'!BO$9:BO$68) -> 0
A38: 3.3.6(ii)2 | B38: ABC (Class A)-Crushing | C38: Cum | I38: =H38*D38 -> 0 | J38: =IFERROR(H38/F38,"") | N38: Trailer Tipper | P38: =SUMPRODUCT(($S$2:$CB$2<=$R$2)*1,($S$4:$CB$4=$S$4)*1,S38:CB38)+SUMPRODUCT(($S$2:$CB$2<=$R$2)*1,($S$4:$CB$4=$T$4)*1,S38:CB38)*0.75 -> 0 | Q38: =SUMPRODUCT(($S$2:$CB$2=$R$2)*1,($S$4:$CB$4=$S$4)*1,S38:CB38)+SUMPRODUCT(($S$2:$CB$2=$R$2)*1,($S$4:$CB$4=$T$4)*1,S38:CB38)*0.75 -> 0 | R38: =O38*P38 -> 0 | S38: =SUMIF('Anbazhagan-TS-1'!$C$9:$C$68,$N38,'Anbazhagan-TS-1'!F$9:F$68) -> 0 | T38: =SUMIF('Anbazhagan-TS-1'!$C$9:$C$68,$N38,'Anbazhagan-TS-1'!G$9:G$68) -> 0 | U38: =SUMIF('Anbazhagan-TS-1'!$C$9:$C$68,$N38,'Anbazhagan-TS-1'!H$9:H$68) -> 0 | V38: =SUMIF('Anbazhagan-TS-1'!$C$9:$C$68,$N38,'Anbazhagan-TS-1'!I$9:I$68) -> 0 | W38: =SUMIF('Anbazhagan-TS-1'!$C$9:$C$68,$N38,'Anbazhagan-TS-1'!J$9:J$68) -> 0 | X38: =SUMIF('Anbazhagan-TS-1'!$C$9:$C$68,$N38,'Anbazhagan-TS-1'!K$9:K$68) -> 0 | Y38: =SUMIF('Anbazhagan-TS-1'!$C$9:$C$68,$N38,'Anbazhagan-TS-1'!L$9:L$68) -> 0 | Z38: =SUMIF('Anbazhagan-TS-1'!$C$9:$C$68,$N38,'Anbazhagan-TS-1'!M$9:M$68) -> 0 | ... CB38: =SUMIF('Anbazhagan-TS-1'!$C$9:$C$68,$N38,'Anbazhagan-TS-1'!BO$9:BO$68) -> 0
A39: 3.3.6(ii)3 | B39: ABC (Class A)-Production, Hauling and Compaction | C39: Cum | I39: =H39*D39 -> 0 | J39: =IFERROR(H39/F39,"") | N39: Tipper | P39: =SUMPRODUCT(($S$2:$CB$2<=$R$2)*1,($S$4:$CB$4=$S$4)*1,S39:CB39)+SUMPRODUCT(($S$2:$CB$2<=$R$2)*1,($S$4:$CB$4=$T$4)*1,S39:CB39)*0.75 -> 0 | Q39: =SUMPRODUCT(($S$2:$CB$2=$R$2)*1,($S$4:$CB$4=$S$4)*1,S39:CB39)+SUMPRODUCT(($S$2:$CB$2=$R$2)*1,($S$4:$CB$4=$T$4)*1,S39:CB39)*0.75 -> 0 | R39: =O39*P39 -> 0 | S39: =SUMIF('Anbazhagan-TS-1'!$C$9:$C$68,$N39,'Anbazhagan-TS-1'!F$9:F$68) -> 0 | T39: =SUMIF('Anbazhagan-TS-1'!$C$9:$C$68,$N39,'Anbazhagan-TS-1'!G$9:G$68) -> 0 | U39: =SUMIF('Anbazhagan-TS-1'!$C$9:$C$68,$N39,'Anbazhagan-TS-1'!H$9:H$68) -> 0 | V39: =SUMIF('Anbazhagan-TS-1'!$C$9:$C$68,$N39,'Anbazhagan-TS-1'!I$9:I$68) -> 0 | W39: =SUMIF('Anbazhagan-TS-1'!$C$9:$C$68,$N39,'Anbazhagan-TS-1'!J$9:J$68) -> 0 | X39: =SUMIF('Anbazhagan-TS-1'!$C$9:$C$68,$N39,'Anbazhagan-TS-1'!K$9:K$68) -> 0 | Y39: =SUMIF('Anbazhagan-TS-1'!$C$9:$C$68,$N39,'Anbazhagan-TS-1'!L$9:L$68) -> 0 | Z39: =SUMIF('Anbazhagan-TS-1'!$C$9:$C$68,$N39,'Anbazhagan-TS-1'!M$9:M$68) -> 0 | ... CB39: =SUMIF('Anbazhagan-TS-1'!$C$9:$C$68,$N39,'Anbazhagan-TS-1'!BO$9:BO$68) -> 0
A40: 4.2.8(i) | B40: Bituminous prime coat | C40: Kg | I40: =H40*D40 -> 0 | J40: =IFERROR(H40/F40,"") | N40: Trailer High Bed | P40: =SUMPRODUCT(($S$2:$CB$2<=$R$2)*1,($S$4:$CB$4=$S$4)*1,S40:CB40)+SUMPRODUCT(($S$2:$CB$2<=$R$2)*1,($S$4:$CB$4=$T$4)*1,S40:CB40)*0.75 -> 0 | Q40: =SUMPRODUCT(($S$2:$CB$2=$R$2)*1,($S$4:$CB$4=$S$4)*1,S40:CB40)+SUMPRODUCT(($S$2:$CB$2=$R$2)*1,($S$4:$CB$4=$T$4)*1,S40:CB40)*0.75 -> 0 | R40: =O40*P40 -> 0 | S40: =SUMIF('Anbazhagan-TS-1'!$C$9:$C$68,$N40,'Anbazhagan-TS-1'!F$9:F$68) -> 0 | T40: =SUMIF('Anbazhagan-TS-1'!$C$9:$C$68,$N40,'Anbazhagan-TS-1'!G$9:G$68) -> 0 | U40: =SUMIF('Anbazhagan-TS-1'!$C$9:$C$68,$N40,'Anbazhagan-TS-1'!H$9:H$68) -> 0 | V40: =SUMIF('Anbazhagan-TS-1'!$C$9:$C$68,$N40,'Anbazhagan-TS-1'!I$9:I$68) -> 0 | W40: =SUMIF('Anbazhagan-TS-1'!$C$9:$C$68,$N40,'Anbazhagan-TS-1'!J$9:J$68) -> 0 | X40: =SUMIF('Anbazhagan-TS-1'!$C$9:$C$68,$N40,'Anbazhagan-TS-1'!K$9:K$68) -> 0 | Y40: =SUMIF('Anbazhagan-TS-1'!$C$9:$C$68,$N40,'Anbazhagan-TS-1'!L$9:L$68) -> 0 | Z40: =SUMIF('Anbazhagan-TS-1'!$C$9:$C$68,$N40,'Anbazhagan-TS-1'!M$9:M$68) -> 0 | ... CB40: =SUMIF('Anbazhagan-TS-1'!$C$9:$C$68,$N40,'Anbazhagan-TS-1'!BO$9:BO$68) -> 0
A41: 4.2.8(ii) | B41: Bituminous tack coat | C41: Kg | I41: =H41*D41 -> 0 | J41: =IFERROR(H41/F41,"") | N41: Grader | P41: =SUMPRODUCT(($S$2:$CB$2<=$R$2)*1,($S$4:$CB$4=$S$4)*1,S41:CB41)+SUMPRODUCT(($S$2:$CB$2<=$R$2)*1,($S$4:$CB$4=$T$4)*1,S41:CB41)*0.75 -> 0 | Q41: =SUMPRODUCT(($S$2:$CB$2=$R$2)*1,($S$4:$CB$4=$S$4)*1,S41:CB41)+SUMPRODUCT(($S$2:$CB$2=$R$2)*1,($S$4:$CB$4=$T$4)*1,S41:CB41)*0.75 -> 0 | R41: =O41*P41 -> 0 | S41: =SUMIF('Anbazhagan-TS-1'!$C$9:$C$68,$N41,'Anbazhagan-TS-1'!F$9:F$68) -> 0 | T41: =SUMIF('Anbazhagan-TS-1'!$C$9:$C$68,$N41,'Anbazhagan-TS-1'!G$9:G$68) -> 0 | U41: =SUMIF('Anbazhagan-TS-1'!$C$9:$C$68,$N41,'Anbazhagan-TS-1'!H$9:H$68) -> 0 | V41: =SUMIF('Anbazhagan-TS-1'!$C$9:$C$68,$N41,'Anbazhagan-TS-1'!I$9:I$68) -> 0 | W41: =SUMIF('Anbazhagan-TS-1'!$C$9:$C$68,$N41,'Anbazhagan-TS-1'!J$9:J$68) -> 0 | X41: =SUMIF('Anbazhagan-TS-1'!$C$9:$C$68,$N41,'Anbazhagan-TS-1'!K$9:K$68) -> 0 | Y41: =SUMIF('Anbazhagan-TS-1'!$C$9:$C$68,$N41,'Anbazhagan-TS-1'!L$9:L$68) -> 0 | Z41: =SUMIF('Anbazhagan-TS-1'!$C$9:$C$68,$N41,'Anbazhagan-TS-1'!M$9:M$68) -> 0 | ... CB41: =SUMIF('Anbazhagan-TS-1'!$C$9:$C$68,$N41,'Anbazhagan-TS-1'!BO$9:BO$68) -> 0
A42: 4.4.14(i) | B42: BBC - Production, Laying and Compaction (Class B) | C42: Cum | I42: =H42*D42 -> 0 | J42: =IFERROR(H42/F42,"") | N42: Cargo With L/E | P42: =SUMPRODUCT(($S$2:$CB$2<=$R$2)*1,($S$4:$CB$4=$S$4)*1,S42:CB42)+SUMPRODUCT(($S$2:$CB$2<=$R$2)*1,($S$4:$CB$4=$T$4)*1,S42:CB42)*0.75 -> 0 | Q42: =SUMPRODUCT(($S$2:$CB$2=$R$2)*1,($S$4:$CB$4=$S$4)*1,S42:CB42)+SUMPRODUCT(($S$2:$CB$2=$R$2)*1,($S$4:$CB$4=$T$4)*1,S42:CB42)*0.75 -> 0 | R42: =O42*P42 -> 0 | S42: =SUMIF('Anbazhagan-TS-1'!$C$9:$C$68,$N42,'Anbazhagan-TS-1'!F$9:F$68) -> 0 | T42: =SUMIF('Anbazhagan-TS-1'!$C$9:$C$68,$N42,'Anbazhagan-TS-1'!G$9:G$68) -> 0 | U42: =SUMIF('Anbazhagan-TS-1'!$C$9:$C$68,$N42,'Anbazhagan-TS-1'!H$9:H$68) -> 0 | V42: =SUMIF('Anbazhagan-TS-1'!$C$9:$C$68,$N42,'Anbazhagan-TS-1'!I$9:I$68) -> 0 | W42: =SUMIF('Anbazhagan-TS-1'!$C$9:$C$68,$N42,'Anbazhagan-TS-1'!J$9:J$68) -> 0 | X42: =SUMIF('Anbazhagan-TS-1'!$C$9:$C$68,$N42,'Anbazhagan-TS-1'!K$9:K$68) -> 0 | Y42: =SUMIF('Anbazhagan-TS-1'!$C$9:$C$68,$N42,'Anbazhagan-TS-1'!L$9:L$68) -> 0 | Z42: =SUMIF('Anbazhagan-TS-1'!$C$9:$C$68,$N42,'Anbazhagan-TS-1'!M$9:M$68) -> 0 | ... CB42: =SUMIF('Anbazhagan-TS-1'!$C$9:$C$68,$N42,'Anbazhagan-TS-1'!BO$9:BO$68) -> 0
A43: 4.5.14(ii) | B43: BWC - Production, laying and Compaction (Class B) | C43: Cum | I43: =H43*D43 -> 0 | J43: =IFERROR(H43/F43,"") | N43: Vibratory Roller | P43: =SUMPRODUCT(($S$2:$CB$2<=$R$2)*1,($S$4:$CB$4=$S$4)*1,S43:CB43)+SUMPRODUCT(($S$2:$CB$2<=$R$2)*1,($S$4:$CB$4=$T$4)*1,S43:CB43)*0.75 -> 0 | Q43: =SUMPRODUCT(($S$2:$CB$2=$R$2)*1,($S$4:$CB$4=$S$4)*1,S43:CB43)+SUMPRODUCT(($S$2:$CB$2=$R$2)*1,($S$4:$CB$4=$T$4)*1,S43:CB43)*0.75 -> 0 | R43: =O43*P43 -> 0 | S43: =SUMIF('Anbazhagan-TS-1'!$C$9:$C$68,$N43,'Anbazhagan-TS-1'!F$9:F$68) -> 0 | T43: =SUMIF('Anbazhagan-TS-1'!$C$9:$C$68,$N43,'Anbazhagan-TS-1'!G$9:G$68) -> 0 | U43: =SUMIF('Anbazhagan-TS-1'!$C$9:$C$68,$N43,'Anbazhagan-TS-1'!H$9:H$68) -> 0 | V43: =SUMIF('Anbazhagan-TS-1'!$C$9:$C$68,$N43,'Anbazhagan-TS-1'!I$9:I$68) -> 0 | W43: =SUMIF('Anbazhagan-TS-1'!$C$9:$C$68,$N43,'Anbazhagan-TS-1'!J$9:J$68) -> 0 | X43: =SUMIF('Anbazhagan-TS-1'!$C$9:$C$68,$N43,'Anbazhagan-TS-1'!K$9:K$68) -> 0 | Y43: =SUMIF('Anbazhagan-TS-1'!$C$9:$C$68,$N43,'Anbazhagan-TS-1'!L$9:L$68) -> 0 | Z43: =SUMIF('Anbazhagan-TS-1'!$C$9:$C$68,$N43,'Anbazhagan-TS-1'!M$9:M$68) -> 0 | ... CB43: =SUMIF('Anbazhagan-TS-1'!$C$9:$C$68,$N43,'Anbazhagan-TS-1'!BO$9:BO$68) -> 0
... A53: 2.4.6(i)a2-1 | B53: Borrow excavation to Embankment-Hauling and compaction | C53: Cum | I53: =H53*D53 -> 0 | J53: =IFERROR(H53/F53,"") | N53: Generator upto 150 to 250 kva | P53: =SUMPRODUCT(($S$2:$CB$2<=$R$2)*1,($S$4:$CB$4=$S$4)*1,S53:CB53)+SUMPRODUCT(($S$2:$CB$2<=$R$2)*1,($S$4:$CB$4=$T$4)*1,S53:CB53)*0.75 -> 0 | Q53: =SUMPRODUCT(($S$2:$CB$2=$R$2)*1,($S$4:$CB$4=$S$4)*1,S53:CB53)+SUMPRODUCT(($S$2:$CB$2=$R$2)*1,($S$4:$CB$4=$T$4)*1,S53:CB53)*0.75 -> 0 | R53: =O53*P53 -> 0 | S53: =SUMIF('Anbazhagan-TS-1'!$C$9:$C$68,$N53,'Anbazhagan-TS-1'!F$9:F$68) -> 0 | T53: =SUMIF('Anbazhagan-TS-1'!$C$9:$C$68,$N53,'Anbazhagan-TS-1'!G$9:G$68) -> 0 | U53: =SUMIF('Anbazhagan-TS-1'!$C$9:$C$68,$N53,'Anbazhagan-TS-1'!H$9:H$68) -> 0 | V53: =SUMIF('Anbazhagan-TS-1'!$C$9:$C$68,$N53,'Anbazhagan-TS-1'!I$9:I$68) -> 0 | W53: =SUMIF('Anbazhagan-TS-1'!$C$9:$C$68,$N53,'Anbazhagan-TS-1'!J$9:J$68) -> 0 | X53: =SUMIF('Anbazhagan-TS-1'!$C$9:$C$68,$N53,'Anbazhagan-TS-1'!K$9:K$68) -> 0 | Y53: =SUMIF('Anbazhagan-TS-1'!$C$9:$C$68,$N53,'Anbazhagan-TS-1'!L$9:L$68) -> 0 | Z53: =SUMIF('Anbazhagan-TS-1'!$C$9:$C$68,$N53,'Anbazhagan-TS-1'!M$9:M$68) -> 0 | ... CB53: =SUMIF('Anbazhagan-TS-1'!$C$9:$C$68,$N53,'Anbazhagan-TS-1'!BO$9:BO$68) -> 0
A54: 5.1.7(i)d-1 | B54: Concrete (class30/20), for Bridge foundation, abutments, pier heads,return walls transition slab etc | C54: cu.m | I54: =H54*D54 -> 0 | N54: Generator 500 kva | P54: =SUMPRODUCT(($S$2:$CB$2<=$R$2)*1,($S$4:$CB$4=$S$4)*1,S54:CB54)+SUMPRODUCT(($S$2:$CB$2<=$R$2)*1,($S$4:$CB$4=$T$4)*1,S54:CB54)*0.75 -> 0 | Q54: =SUMPRODUCT(($S$2:$CB$2=$R$2)*1,($S$4:$CB$4=$S$4)*1,S54:CB54)+SUMPRODUCT(($S$2:$CB$2=$R$2)*1,($S$4:$CB$4=$T$4)*1,S54:CB54)*0.75 -> 0 | R54: =O54*P54 -> 0 | S54: =SUMIF('Anbazhagan-TS-1'!$C$9:$C$68,$N54,'Anbazhagan-TS-1'!F$9:F$68) -> 0 | T54: =SUMIF('Anbazhagan-TS-1'!$C$9:$C$68,$N54,'Anbazhagan-TS-1'!G$9:G$68) -> 0 | U54: =SUMIF('Anbazhagan-TS-1'!$C$9:$C$68,$N54,'Anbazhagan-TS-1'!H$9:H$68) -> 0 | V54: =SUMIF('Anbazhagan-TS-1'!$C$9:$C$68,$N54,'Anbazhagan-TS-1'!I$9:I$68) -> 0 | W54: =SUMIF('Anbazhagan-TS-1'!$C$9:$C$68,$N54,'Anbazhagan-TS-1'!J$9:J$68) -> 0 | X54: =SUMIF('Anbazhagan-TS-1'!$C$9:$C$68,$N54,'Anbazhagan-TS-1'!K$9:K$68) -> 0 | Y54: =SUMIF('Anbazhagan-TS-1'!$C$9:$C$68,$N54,'Anbazhagan-TS-1'!L$9:L$68) -> 0 | Z54: =SUMIF('Anbazhagan-TS-1'!$C$9:$C$68,$N54,'Anbazhagan-TS-1'!M$9:M$68) -> 0 | ... CB54: =SUMIF('Anbazhagan-TS-1'!$C$9:$C$68,$N54,'Anbazhagan-TS-1'!BO$9:BO$68) -> 0
A55: 8.2.6(i)c | B55: Storm Sewer, HDPE Pipe (diameter 450mm) including concrete surrounding | C55: lin.m. | I55: =H55*D55 -> 0 | N55: Tandem Roller | P55: =SUMPRODUCT(($S$2:$CB$2<=$R$2)*1,($S$4:$CB$4=$S$4)*1,S55:CB55)+SUMPRODUCT(($S$2:$CB$2<=$R$2)*1,($S$4:$CB$4=$T$4)*1,S55:CB55)*0.75 -> 0 | Q55: =SUMPRODUCT(($S$2:$CB$2=$R$2)*1,($S$4:$CB$4=$S$4)*1,S55:CB55)+SUMPRODUCT(($S$2:$CB$2=$R$2)*1,($S$4:$CB$4=$T$4)*1,S55:CB55)*0.75 -> 0 | R55: =O55*P55 -> 0 | S55: =SUMIF('Anbazhagan-TS-1'!$C$9:$C$68,$N55,'Anbazhagan-TS-1'!F$9:F$68) -> 0 | T55: =SUMIF('Anbazhagan-TS-1'!$C$9:$C$68,$N55,'Anbazhagan-TS-1'!G$9:G$68) -> 0 | U55: =SUMIF('Anbazhagan-TS-1'!$C$9:$C$68,$N55,'Anbazhagan-TS-1'!H$9:H$68) -> 0 | V55: =SUMIF('Anbazhagan-TS-1'!$C$9:$C$68,$N55,'Anbazhagan-TS-1'!I$9:I$68) -> 0 | W55: =SUMIF('Anbazhagan-TS-1'!$C$9:$C$68,$N55,'Anbazhagan-TS-1'!J$9:J$68) -> 0 | X55: =SUMIF('Anbazhagan-TS-1'!$C$9:$C$68,$N55,'Anbazhagan-TS-1'!K$9:K$68) -> 0 | Y55: =SUMIF('Anbazhagan-TS-1'!$C$9:$C$68,$N55,'Anbazhagan-TS-1'!L$9:L$68) -> 0 | Z55: =SUMIF('Anbazhagan-TS-1'!$C$9:$C$68,$N55,'Anbazhagan-TS-1'!M$9:M$68) -> 0 | ... CB55: =SUMIF('Anbazhagan-TS-1'!$C$9:$C$68,$N55,'Anbazhagan-TS-1'!BO$9:BO$68) -> 0
A56: 2.3.6(i)a | B56: Unclassified excavation | C56: Cum | I56: =H56*D56 -> 0 | N56: Ptr | P56: =SUMPRODUCT(($S$2:$CB$2<=$R$2)*1,($S$4:$CB$4=$S$4)*1,S56:CB56)+SUMPRODUCT(($S$2:$CB$2<=$R$2)*1,($S$4:$CB$4=$T$4)*1,S56:CB56)*0.75 -> 0 | Q56: =SUMPRODUCT(($S$2:$CB$2=$R$2)*1,($S$4:$CB$4=$S$4)*1,S56:CB56)+SUMPRODUCT(($S$2:$CB$2=$R$2)*1,($S$4:$CB$4=$T$4)*1,S56:CB56)*0.75 -> 0 | R56: =O56*P56 -> 0 | S56: =SUMIF('Anbazhagan-TS-1'!$C$9:$C$68,$N56,'Anbazhagan-TS-1'!F$9:F$68) -> 0 | T56: =SUMIF('Anbazhagan-TS-1'!$C$9:$C$68,$N56,'Anbazhagan-TS-1'!G$9:G$68) -> 0 | U56: =SUMIF('Anbazhagan-TS-1'!$C$9:$C$68,$N56,'Anbazhagan-TS-1'!H$9:H$68) -> 0 | V56: =SUMIF('Anbazhagan-TS-1'!$C$9:$C$68,$N56,'Anbazhagan-TS-1'!I$9:I$68) -> 0 | W56: =SUMIF('Anbazhagan-TS-1'!$C$9:$C$68,$N56,'Anbazhagan-TS-1'!J$9:J$68) -> 0 | X56: =SUMIF('Anbazhagan-TS-1'!$C$9:$C$68,$N56,'Anbazhagan-TS-1'!K$9:K$68) -> 0 | Y56: =SUMIF('Anbazhagan-TS-1'!$C$9:$C$68,$N56,'Anbazhagan-TS-1'!L$9:L$68) -> 0 | Z56: =SUMIF('Anbazhagan-TS-1'!$C$9:$C$68,$N56,'Anbazhagan-TS-1'!M$9:M$68) -> 0 | ... CB56: =SUMIF('Anbazhagan-TS-1'!$C$9:$C$68,$N56,'Anbazhagan-TS-1'!BO$9:BO$68) -> 0
A57: 2.2.5(xviii) | B57: Removal of drainage protection works in mortared rip-rap,loose riprap,gabion etc. to any thickness at Culverts, embankments,channel, floodways etc | C57: Cum | I57: =H57*D57 -> 0 | N57: Mini Tandem Roller | P57: =SUMPRODUCT(($S$2:$CB$2<=$R$2)*1,($S$4:$CB$4=$S$4)*1,S57:CB57)+SUMPRODUCT(($S$2:$CB$2<=$R$2)*1,($S$4:$CB$4=$T$4)*1,S57:CB57)*0.75 -> 0 | Q57: =SUMPRODUCT(($S$2:$CB$2=$R$2)*1,($S$4:$CB$4=$S$4)*1,S57:CB57)+SUMPRODUCT(($S$2:$CB$2=$R$2)*1,($S$4:$CB$4=$T$4)*1,S57:CB57)*0.75 -> 0 | R57: =O57*P57 -> 0 | S57: =SUMIF('Anbazhagan-TS-1'!$C$9:$C$68,$N57,'Anbazhagan-TS-1'!F$9:F$68) -> 0 | T57: =SUMIF('Anbazhagan-TS-1'!$C$9:$C$68,$N57,'Anbazhagan-TS-1'!G$9:G$68) -> 0 | U57: =SUMIF('Anbazhagan-TS-1'!$C$9:$C$68,$N57,'Anbazhagan-TS-1'!H$9:H$68) -> 0 | V57: =SUMIF('Anbazhagan-TS-1'!$C$9:$C$68,$N57,'Anbazhagan-TS-1'!I$9:I$68) -> 0 | W57: =SUMIF('Anbazhagan-TS-1'!$C$9:$C$68,$N57,'Anbazhagan-TS-1'!J$9:J$68) -> 0 | X57: =SUMIF('Anbazhagan-TS-1'!$C$9:$C$68,$N57,'Anbazhagan-TS-1'!K$9:K$68) -> 0 | Y57: =SUMIF('Anbazhagan-TS-1'!$C$9:$C$68,$N57,'Anbazhagan-TS-1'!L$9:L$68) -> 0 | Z57: =SUMIF('Anbazhagan-TS-1'!$C$9:$C$68,$N57,'Anbazhagan-TS-1'!M$9:M$68) -> 0 | ... CB57: =SUMIF('Anbazhagan-TS-1'!$C$9:$C$68,$N57,'Anbazhagan-TS-1'!BO$9:BO$68) -> 0
N58: Paver Asphalt | P58: =SUMPRODUCT(($S$2:$CB$2<=$R$2)*1,($S$4:$CB$4=$S$4)*1,S58:CB58)+SUMPRODUCT(($S$2:$CB$2<=$R$2)*1,($S$4:$CB$4=$T$4)*1,S58:CB58)*0.75 -> 0 | Q58: =SUMPRODUCT(($S$2:$CB$2=$R$2)*1,($S$4:$CB$4=$S$4)*1,S58:CB58)+SUMPRODUCT(($S$2:$CB$2=$R$2)*1,($S$4:$CB$4=$T$4)*1,S58:CB58)*0.75 -> 0 | R58: =O58*P58 -> 0 | S58: =SUMIF('Anbazhagan-TS-1'!$C$9:$C$68,$N58,'Anbazhagan-TS-1'!F$9:F$68) -> 0 | T58: =SUMIF('Anbazhagan-TS-1'!$C$9:$C$68,$N58,'Anbazhagan-TS-1'!G$9:G$68) -> 0 | U58: =SUMIF('Anbazhagan-TS-1'!$C$9:$C$68,$N58,'Anbazhagan-TS-1'!H$9:H$68) -> 0 | V58: =SUMIF('Anbazhagan-TS-1'!$C$9:$C$68,$N58,'Anbazhagan-TS-1'!I$9:I$68) -> 0 | W58: =SUMIF('Anbazhagan-TS-1'!$C$9:$C$68,$N58,'Anbazhagan-TS-1'!J$9:J$68) -> 0 | X58: =SUMIF('Anbazhagan-TS-1'!$C$9:$C$68,$N58,'Anbazhagan-TS-1'!K$9:K$68) -> 0 | Y58: =SUMIF('Anbazhagan-TS-1'!$C$9:$C$68,$N58,'Anbazhagan-TS-1'!L$9:L$68) -> 0 | Z58: =SUMIF('Anbazhagan-TS-1'!$C$9:$C$68,$N58,'Anbazhagan-TS-1'!M$9:M$68) -> 0 | ... CB58: =SUMIF('Anbazhagan-TS-1'!$C$9:$C$68,$N58,'Anbazhagan-TS-1'!BO$9:BO$68) -> 0
P59: =SUMPRODUCT(($S$2:$CB$2<=$R$2)*1,($S$4:$CB$4=$S$4)*1,S59:CB59)+SUMPRODUCT(($S$2:$CB$2<=$R$2)*1,($S$4:$CB$4=$T$4)*1,S59:CB59)*0.75 -> 0 | Q59: =SUMPRODUCT(($S$2:$CB$2=$R$2)*1,($S$4:$CB$4=$S$4)*1,S59:CB59)+SUMPRODUCT(($S$2:$CB$2=$R$2)*1,($S$4:$CB$4=$T$4)*1,S59:CB59)*0.75 -> 0 | R59: =O59*P59 -> 0 | S59: =SUMIF('Anbazhagan-TS-1'!$C$9:$C$68,$N59,'Anbazhagan-TS-1'!F$9:F$68) -> 0 | T59: =SUMIF('Anbazhagan-TS-1'!$C$9:$C$68,$N59,'Anbazhagan-TS-1'!G$9:G$68) -> 0 | U59: =SUMIF('Anbazhagan-TS-1'!$C$9:$C$68,$N59,'Anbazhagan-TS-1'!H$9:H$68) -> 0 | V59: =SUMIF('Anbazhagan-TS-1'!$C$9:$C$68,$N59,'Anbazhagan-TS-1'!I$9:I$68) -> 0 | W59: =SUMIF('Anbazhagan-TS-1'!$C$9:$C$68,$N59,'Anbazhagan-TS-1'!J$9:J$68) -> 0 | X59: =SUMIF('Anbazhagan-TS-1'!$C$9:$C$68,$N59,'Anbazhagan-TS-1'!K$9:K$68) -> 0 | Y59: =SUMIF('Anbazhagan-TS-1'!$C$9:$C$68,$N59,'Anbazhagan-TS-1'!L$9:L$68) -> 0 | Z59: =SUMIF('Anbazhagan-TS-1'!$C$9:$C$68,$N59,'Anbazhagan-TS-1'!M$9:M$68) -> 0 | ... CB59: =SUMIF('Anbazhagan-TS-1'!$C$9:$C$68,$N59,'Anbazhagan-TS-1'!BO$9:BO$68) -> 0
B60: Total | E60: =SUMPRODUCT(E26:E59,D26:D59) -> 0 | G60: =SUM(G27:G59) -> 0 | I60: =SUM(I27:I59) -> 0 | N60: Air Compressor | P60: =SUMPRODUCT(($S$2:$CB$2<=$R$2)*1,($S$4:$CB$4=$S$4)*1,S60:CB60)+SUMPRODUCT(($S$2:$CB$2<=$R$2)*1,($S$4:$CB$4=$T$4)*1,S60:CB60)*0.75 -> 0 | Q60: =SUMPRODUCT(($S$2:$CB$2=$R$2)*1,($S$4:$CB$4=$S$4)*1,S60:CB60)+SUMPRODUCT(($S$2:$CB$2=$R$2)*1,($S$4:$CB$4=$T$4)*1,S60:CB60)*0.75 -> 0 | R60: =O60*P60 -> 0 | S60: =SUMIF('Anbazhagan-TS-1'!$C$9:$C$68,$N60,'Anbazhagan-TS-1'!F$9:F$68) -> 0 | T60: =SUMIF('Anbazhagan-TS-1'!$C$9:$C$68,$N60,'Anbazhagan-TS-1'!G$9:G$68) -> 0 | U60: =SUMIF('Anbazhagan-TS-1'!$C$9:$C$68,$N60,'Anbazhagan-TS-1'!H$9:H$68) -> 0 | V60: =SUMIF('Anbazhagan-TS-1'!$C$9:$C$68,$N60,'Anbazhagan-TS-1'!I$9:I$68) -> 0 | W60: =SUMIF('Anbazhagan-TS-1'!$C$9:$C$68,$N60,'Anbazhagan-TS-1'!J$9:J$68) -> 0 | X60: =SUMIF('Anbazhagan-TS-1'!$C$9:$C$68,$N60,'Anbazhagan-TS-1'!K$9:K$68) -> 0 | Y60: =SUMIF('Anbazhagan-TS-1'!$C$9:$C$68,$N60,'Anbazhagan-TS-1'!L$9:L$68) -> 0 | Z60: =SUMIF('Anbazhagan-TS-1'!$C$9:$C$68,$N60,'Anbazhagan-TS-1'!M$9:M$68) -> 0 | ... CB60: =SUMIF('Anbazhagan-TS-1'!$C$9:$C$68,$N60,'Anbazhagan-TS-1'!BO$9:BO$68) -> 0
B61: Resources | C61: Amount | E61: Amount | F61: =IF(E60=#REF!,"Tally","No") -> #REF! | N61: Weigh Batcher | P61: =SUMPRODUCT(($S$2:$CB$2<=$R$2)*1,($S$4:$CB$4=$S$4)*1,S61:CB61)+SUMPRODUCT(($S$2:$CB$2<=$R$2)*1,($S$4:$CB$4=$T$4)*1,S61:CB61)*0.75 -> 0 | Q61: =SUMPRODUCT(($S$2:$CB$2=$R$2)*1,($S$4:$CB$4=$S$4)*1,S61:CB61)+SUMPRODUCT(($S$2:$CB$2=$R$2)*1,($S$4:$CB$4=$T$4)*1,S61:CB61)*0.75 -> 0 | R61: =O61*P61 -> 0 | S61: =SUMIF('Anbazhagan-TS-1'!$C$9:$C$68,$N61,'Anbazhagan-TS-1'!F$9:F$68) -> 0 | T61: =SUMIF('Anbazhagan-TS-1'!$C$9:$C$68,$N61,'Anbazhagan-TS-1'!G$9:G$68) -> 0 | U61: =SUMIF('Anbazhagan-TS-1'!$C$9:$C$68,$N61,'Anbazhagan-TS-1'!H$9:H$68) -> 0 | V61: =SUMIF('Anbazhagan-TS-1'!$C$9:$C$68,$N61,'Anbazhagan-TS-1'!I$9:I$68) -> 0 | W61: =SUMIF('Anbazhagan-TS-1'!$C$9:$C$68,$N61,'Anbazhagan-TS-1'!J$9:J$68) -> 0 | X61: =SUMIF('Anbazhagan-TS-1'!$C$9:$C$68,$N61,'Anbazhagan-TS-1'!K$9:K$68) -> 0 | Y61: =SUMIF('Anbazhagan-TS-1'!$C$9:$C$68,$N61,'Anbazhagan-TS-1'!L$9:L$68) -> 0 | Z61: =SUMIF('Anbazhagan-TS-1'!$C$9:$C$68,$N61,'Anbazhagan-TS-1'!M$9:M$68) -> 0 | ... CB61: =SUMIF('Anbazhagan-TS-1'!$C$9:$C$68,$N61,'Anbazhagan-TS-1'!BO$9:BO$68) -> 0
B62: A.Man Power: | C62: =R25 -> 0 | E62: =Q25 -> 0 | N62: 3 Ton Canter | P62: =SUMPRODUCT(($S$2:$CB$2<=$R$2)*1,($S$4:$CB$4=$S$4)*1,S62:CB62)+SUMPRODUCT(($S$2:$CB$2<=$R$2)*1,($S$4:$CB$4=$T$4)*1,S62:CB62)*0.75 -> 0 | Q62: =SUMPRODUCT(($S$2:$CB$2=$R$2)*1,($S$4:$CB$4=$S$4)*1,S62:CB62)+SUMPRODUCT(($S$2:$CB$2=$R$2)*1,($S$4:$CB$4=$T$4)*1,S62:CB62)*0.75 -> 0 | R62: =O62*P62 -> 0 | S62: =SUMIF('Anbazhagan-TS-1'!$C$9:$C$68,$N62,'Anbazhagan-TS-1'!F$9:F$68) -> 0 | T62: =SUMIF('Anbazhagan-TS-1'!$C$9:$C$68,$N62,'Anbazhagan-TS-1'!G$9:G$68) -> 0 | U62: =SUMIF('Anbazhagan-TS-1'!$C$9:$C$68,$N62,'Anbazhagan-TS-1'!H$9:H$68) -> 0 | V62: =SUMIF('Anbazhagan-TS-1'!$C$9:$C$68,$N62,'Anbazhagan-TS-1'!I$9:I$68) -> 0 | W62: =SUMIF('Anbazhagan-TS-1'!$C$9:$C$68,$N62,'Anbazhagan-TS-1'!J$9:J$68) -> 0 | X62: =SUMIF('Anbazhagan-TS-1'!$C$9:$C$68,$N62,'Anbazhagan-TS-1'!K$9:K$68) -> 0 | Y62: =SUMIF('Anbazhagan-TS-1'!$C$9:$C$68,$N62,'Anbazhagan-TS-1'!L$9:L$68) -> 0 | Z62: =SUMIF('Anbazhagan-TS-1'!$C$9:$C$68,$N62,'Anbazhagan-TS-1'!M$9:M$68) -> 0 | ... CB62: =SUMIF('Anbazhagan-TS-1'!$C$9:$C$68,$N62,'Anbazhagan-TS-1'!BO$9:BO$68) -> 0
B63: B.Catering/Admin: | C63: =R29 -> 0 | E63: =Q29 -> 0 | N63: Low bed trailer | P63: =SUMPRODUCT(($S$2:$CB$2<=$R$2)*1,($S$4:$CB$4=$S$4)*1,S63:CB63)+SUMPRODUCT(($S$2:$CB$2<=$R$2)*1,($S$4:$CB$4=$T$4)*1,S63:CB63)*0.75 -> 0 | Q63: =SUMPRODUCT(($S$2:$CB$2=$R$2)*1,($S$4:$CB$4=$S$4)*1,S63:CB63)+SUMPRODUCT(($S$2:$CB$2=$R$2)*1,($S$4:$CB$4=$T$4)*1,S63:CB63)*0.75 -> 0 | R63: =O63*P63 -> 0 | S63: =SUMIF('Anbazhagan-TS-1'!$C$9:$C$68,$N63,'Anbazhagan-TS-1'!F$9:F$68) -> 0 | T63: =SUMIF('Anbazhagan-TS-1'!$C$9:$C$68,$N63,'Anbazhagan-TS-1'!G$9:G$68) -> 0 | U63: =SUMIF('Anbazhagan-TS-1'!$C$9:$C$68,$N63,'Anbazhagan-TS-1'!H$9:H$68) -> 0 | V63: =SUMIF('Anbazhagan-TS-1'!$C$9:$C$68,$N63,'Anbazhagan-TS-1'!I$9:I$68) -> 0 | W63: =SUMIF('Anbazhagan-TS-1'!$C$9:$C$68,$N63,'Anbazhagan-TS-1'!J$9:J$68) -> 0 | X63: =SUMIF('Anbazhagan-TS-1'!$C$9:$C$68,$N63,'Anbazhagan-TS-1'!K$9:K$68) -> 0 | Y63: =SUMIF('Anbazhagan-TS-1'!$C$9:$C$68,$N63,'Anbazhagan-TS-1'!L$9:L$68) -> 0 | Z63: =SUMIF('Anbazhagan-TS-1'!$C$9:$C$68,$N63,'Anbazhagan-TS-1'!M$9:M$68) -> 0 | ... CB63: =SUMIF('Anbazhagan-TS-1'!$C$9:$C$68,$N63,'Anbazhagan-TS-1'!BO$9:BO$68) -> 0
B64: C.Machinery: | C64: =R66 -> 0 | E64: =Q66 -> 0 | H64: Projection amount | I64: =G60 -> 0 | K64: 0 | N64: Asphalt cutter | P64: =SUMPRODUCT(($S$2:$CB$2<=$R$2)*1,($S$4:$CB$4=$S$4)*1,S64:CB64)+SUMPRODUCT(($S$2:$CB$2<=$R$2)*1,($S$4:$CB$4=$T$4)*1,S64:CB64)*0.75 -> 0 | Q64: =SUMPRODUCT(($S$2:$CB$2=$R$2)*1,($S$4:$CB$4=$S$4)*1,S64:CB64)+SUMPRODUCT(($S$2:$CB$2=$R$2)*1,($S$4:$CB$4=$T$4)*1,S64:CB64)*0.75 -> 0 | R64: =O64*P64 -> 0 | S64: =SUMIF('Anbazhagan-TS-1'!$C$9:$C$68,$N64,'Anbazhagan-TS-1'!F$9:F$68) -> 0 | T64: =SUMIF('Anbazhagan-TS-1'!$C$9:$C$68,$N64,'Anbazhagan-TS-1'!G$9:G$68) -> 0 | U64: =SUMIF('Anbazhagan-TS-1'!$C$9:$C$68,$N64,'Anbazhagan-TS-1'!H$9:H$68) -> 0 | V64: =SUMIF('Anbazhagan-TS-1'!$C$9:$C$68,$N64,'Anbazhagan-TS-1'!I$9:I$68) -> 0 | W64: =SUMIF('Anbazhagan-TS-1'!$C$9:$C$68,$N64,'Anbazhagan-TS-1'!J$9:J$68) -> 0 | X64: =SUMIF('Anbazhagan-TS-1'!$C$9:$C$68,$N64,'Anbazhagan-TS-1'!K$9:K$68) -> 0 | Y64: =SUMIF('Anbazhagan-TS-1'!$C$9:$C$68,$N64,'Anbazhagan-TS-1'!L$9:L$68) -> 0 | Z64: =SUMIF('Anbazhagan-TS-1'!$C$9:$C$68,$N64,'Anbazhagan-TS-1'!M$9:M$68) -> 0 | ... CB64: =SUMIF('Anbazhagan-TS-1'!$C$9:$C$68,$N64,'Anbazhagan-TS-1'!BO$9:BO$68) -> 0
B65: D.Fuel Charge | C65: =R69 -> 0 | E65: =Q69 -> 0 | H65: Total Income | I65: =I60 -> 0 | K65: =E60 -> 0
B66: E.Material | C66: =G25 -> 0 | E66: =E25 -> 0 | H66: Total Expenses | I66: =C68 -> 0 | K66: =E68 -> 0 | N66: Total | Q66: =SUMPRODUCT(Q31:Q65,O31:O65) -> 0 | R66: =SUM(R32:R65) -> 0 | S66: =SUMIF(#REF!,$N66,#REF!) -> #REF!
B67: F.SubContractor | C67: =M25 -> 0 | E67: =K25 -> 0 | H67: Contribution | I67: =I65-I66 -> 0 | K67: =K65-K66 -> 0 | N67: D.Fuel Charge
B68: Total | C68: =SUM(C62:C67)+G24 -> 0 | E68: =SUM(E62:E67)+E69 -> 0 | H68: % Contribution | I68: =IFERROR(I67/I65,"") | J68: =IF(I67>=1,"Profit","Loss") -> Loss | K68: =IFERROR(K67/K65,"") | L68: =IF(K67>=1,"Profit","Loss") -> Loss | N68: Decsription | O68: Rate | P68: Avg % | Q68: For the day | R68: Total Amount
B69: G. General Expenses | E69: =E24*D24 -> 0 | N69: Fuel | Q69: =Q66*P69 -> 0 | R69: =R66*P69 -> 0
S76: #REF! | U76: #REF! | W76: #REF! | AA76: #REF! | AC76: #REF! | AE76: #REF! | AG76: #REF! | AI76: #REF! | AK76: #REF! | AM76: #REF! | AO76: #REF! | AQ76: #REF! | AS76: #REF! | AU76: #REF! | AW76: #REF! | AY76: #REF!
S77: 126 | T77: 0 | U77: 0 | V77: 0 | W77: 0 | X77: 0 | AA77: 0 | AB77: 0 | AC77: 0 | AD77: 0 | AE77: 0 | AF77: 0 | AG77: 0 | AH77: 0 | AI77: 0 | AJ77: 0 | AK77: 0 | AL77: 0 | AM77: 0 | AN77: 0 | AO77: 0 | AP77: 0 | AQ77: 0 | AR77: 0 | AS77: 0 | AT77: 0 | AU77: 0 | AV77: 0 | AW77: 0 | AX77: 0 | AY77: 234 | AZ77: 18 | BA77: 158 | BB77: 18 | BC77: 104 | BD77: #REF! | BE77: 140 | BF77: #REF! | BG77: 126 | BH77: 126 | BI77: 126
S78: =S77-S76 -> #REF! | T78: =T77-T76 -> 0 | U78: =U77-U76 -> #REF! | V78: =V77-V76 -> 0 | W78: =W77-W76 -> #REF! | X78: =X77-X76 -> 0 | AA78: =AA77-AA76 -> #REF! | AB78: =AB77-AB76 -> 0 | AC78: =AC77-AC76 -> #REF! | AD78: =AD77-AD76 -> 0 | AE78: =AE77-AE76 -> #REF! | AF78: =AF77-AF76 -> 0 | AG78: =AG77-AG76 -> #REF! | AH78: =AH77-AH76 -> 0 | ... BG78: =BG77-BG76 -> 126
N84: 1 | O84: =N84+1 -> 2 | P84: =O84+1 -> 3 | Q84: =P84+1 -> 4 | R84: =Q84+1 -> 5 | S84: =R84+1 -> 6 | T84: =S84+1 -> 7 | U84: =T84+1 -> 8 | V84: =U84+1 -> 9 | ... CB84: =CA84+1 -> 67

Sheet PRE
N1: ='Summary-Financial (NEW)'!AE3 -> 29 | S1: =S2 -> 42948 | U1: =S1+1 -> 42949 | W1: =U1+1 -> 42950 | Y1: =W1+1 -> 42951 | AA1: =Y1+1 -> 42952 | AC1: =AA1+1 -> 42953 | AE1: =AC1+1 -> 42954 | AG1: =AE1+1 -> 42955 | AI1: =AG1+1 -> 42956 | AK1: =AI1+1 -> 42957 | AM1: =AK1+1 -> 42958 | AO1: =AM1+1 -> 42959 | AQ1: =AO1+1 -> 42960 | AS1: =AQ1+1 -> 42961 | AU1: =AS1+1 -> 42962 | AW1: =AU1+1 -> 42963 | AY1: =AW1+1 -> 42964 | BA1: =AY1+1 -> 42965 | BC1: =BA1+1 -> 42966 | BE1: =BC1+1 -> 42967 | BG1: =BE1+1 -> 42968 | BI1: =BG1+1 -> 42969 | BK1: =BI1+1 -> 42970 | BM1: =BK1+1 -> 42971 | BO1: =BM1+1 -> 42972 | BQ1: =BO1+1 -> 42973 | BS1: =BQ1+1 -> 42974 | BU1: =BS1+1 -> 42975 | BW1: =BU1+1 -> 42976 | BY1: =BW1+1 -> 42977 | CA1: =BY1+1 -> 42978
A2: =#REF! -> #REF! | B2: 6155_Dualization of Barka Nakhal Road | F2: Costing Report | M2: Total Days | N2: =N3 -> 25 | Q2: Upto | R2: ='Summary-Financial'!AB2 -> xxxx | S2: 42948 | T2: =S2 -> 42948 | U2: =S2+1 -> 42949 | V2: =T2+1 -> 42949 | W2: =U2+1 -> 42950 | X2: =V2+1 -> 42950 | Y2: =W2+1 -> 42951 | Z2: =X2+1 -> 42951 | AA2: =Y2+1 -> 42952 | AB2: =Z2+1 -> 42952 | ... CB2: =BZ2+1 -> 42978
B3: Project Manager : Mohsin | M3: Worked days | N3: ='Summary-Financial (NEW)'!AF2 -> 25 | O3: ='Summary-Financial (NEW)'!AI2 -> 31
B4: E.Material | H4: F.SubContractor | N4: A.Man Power: | S4: Day | T4: Night | U4: Day | V4: Night | W4: Day | X4: Night | Y4: Day | Z4: Night | AA4: Day | AB4: Night | AC4: Day | AD4: Night | AE4: Day | AF4: Night | AG4: Day | AH4: Night | AI4: Day | AJ4: Night | AK4: Day | AL4: Night | AM4: Day | AN4: Night | AO4: Day | AP4: Night | AQ4: Day | AR4: Night | AS4: Day | AT4: Night | AU4: Day | AV4: Night | AW4: Day | AX4: Night | AY4: Day | AZ4: Night | BA4: Day | BB4: Night | BC4: Day | BD4: Night | BE4: Day | BF4: Night | BG4: Day | BH4: Night | BI4: Day | BJ4: Night | BK4: Day | BL4: Night | BM4: Day | BN4: Night | BO4: Day | BP4: Night | BQ4: Day | BR4: Night | BS4: Day | BT4: Night | BU4: Day | BV4: Night | BW4: Day | BX4: Night | BY4: Day | BZ4: Night | CA4: Day | CB4: Night
A5: BOQ # | B5: Decsription | C5: Unit | D5: Rate | E5: For the day | F5: Quantity | G5: Total Amount | H5: Decsription | I5: Unit | J5: Rate | K5: For the day | L5: Quantity | M5: Total Amount | N5: Decsription | O5: Rate | P5: Nos | Q5: For the day | R5: Total Amount
G6: =D6*F6 -> 0 | N6: Helper E | Q6: =SUMPRODUCT(($S$2:$CB$2=$R$2)*1,($S$4:$CB$4=$S$4)*1,S6:CB6)+SUMPRODUCT(($S$2:$CB$2=$R$2)*1,($S$4:$CB$4=$T$4)*1,S6:CB6) -> #REF! | R6: =O6*P6 -> 0 | S6: =SUMIF(#REF!,$N6,#REF!) -> #REF! | T6: =SUMIF(#REF!,$N6,#REF!) -> #REF! | U6: =SUMIF(#REF!,$N6,#REF!) -> #REF! | V6: =SUMIF(#REF!,$N6,#REF!) -> #REF! | W6: =SUMIF(#REF!,$N6,#REF!) -> #REF! | X6: =SUMIF(#REF!,$N6,#REF!) -> #REF! | Y6: =SUMIF(#REF!,$N6,#REF!) -> #REF! | Z6: =SUMIF(#REF!,$N6,#REF!) -> #REF! | ... CB6: =SUMIF(#REF!,$N6,#REF!) -> #REF!
G7: =D7*F7 -> 0 | M7: =L7*J7 -> 0 | N7: Steel Fixer E | Q7: =SUMPRODUCT(($S$2:$CB$2=$R$2)*1,($S$4:$CB$4=$S$4)*1,S7:CB7)+SUMPRODUCT(($S$2:$CB$2=$R$2)*1,($S$4:$CB$4=$T$4)*1,S7:CB7) -> #REF! | R7: =O7*P7 -> 0 | S7: =SUMIF(#REF!,$N7,#REF!) -> #REF! | T7: =SUMIF(#REF!,$N7,#REF!) -> #REF! | U7: =SUMIF(#REF!,$N7,#REF!) -> #REF! | V7: =SUMIF(#REF!,$N7,#REF!) -> #REF! | W7: =SUMIF(#REF!,$N7,#REF!) -> #REF! | X7: =SUMIF(#REF!,$N7,#REF!) -> #REF! | Y7: =SUMIF(#REF!,$N7,#REF!) -> #REF! | Z7: =SUMIF(#REF!,$N7,#REF!) -> #REF! | ... CB7: =SUMIF(#REF!,$N7,#REF!) -> #REF!
G8: =D8*F8 -> 0 | M8: =L8*J8 -> 0 | N8: Mason | Q8: =SUMPRODUCT(($S$2:$CB$2=$R$2)*1,($S$4:$CB$4=$S$4)*1,S8:CB8)+SUMPRODUCT(($S$2:$CB$2=$R$2)*1,($S$4:$CB$4=$T$4)*1,S8:CB8) -> #REF! | R8: =O8*P8 -> 0 | S8: =SUMIF(#REF!,$N8,#REF!) -> #REF! | T8: =SUMIF(#REF!,$N8,#REF!) -> #REF! | U8: =SUMIF(#REF!,$N8,#REF!) -> #REF! | V8: =SUMIF(#REF!,$N8,#REF!) -> #REF! | W8: =SUMIF(#REF!,$N8,#REF!) -> #REF! | X8: =SUMIF(#REF!,$N8,#REF!) -> #REF! | Y8: =SUMIF(#REF!,$N8,#REF!) -> #REF! | Z8: =SUMIF(#REF!,$N8,#REF!) -> #REF! | ... CB8: =SUMIF(#REF!,$N8,#REF!) -> #REF!
G9: =D9*F9 -> 0 | M9: =L9*J9 -> 0 | N9: Electrician | Q9: =SUMPRODUCT(($S$2:$CB$2=$R$2)*1,($S$4:$CB$4=$S$4)*1,S9:CB9)+SUMPRODUCT(($S$2:$CB$2=$R$2)*1,($S$4:$CB$4=$T$4)*1,S9:CB9) -> #REF! | R9: =O9*P9 -> 0 | S9: =SUMIF(#REF!,$N9,#REF!) -> #REF! | T9: =SUMIF(#REF!,$N9,#REF!) -> #REF! | U9: =SUMIF(#REF!,$N9,#REF!) -> #REF! | V9: =SUMIF(#REF!,$N9,#REF!) -> #REF! | W9: =SUMIF(#REF!,$N9,#REF!) -> #REF! | X9: =SUMIF(#REF!,$N9,#REF!) -> #REF! | Y9: =SUMIF(#REF!,$N9,#REF!) -> #REF! | Z9: =SUMIF(#REF!,$N9,#REF!) -> #REF! | ... CB9: =SUMIF(#REF!,$N9,#REF!) -> #REF!
G10: =D10*F10 -> 0 | M10: =L10*J10 -> 0 | N10: Carpenter E | Q10: =SUMPRODUCT(($S$2:$CB$2=$R$2)*1,($S$4:$CB$4=$S$4)*1,S10:CB10)+SUMPRODUCT(($S$2:$CB$2=$R$2)*1,($S$4:$CB$4=$T$4)*1,S10:CB10) -> #REF! | R10: =O10*P10 -> 0 | S10: =SUMIF(#REF!,$N10,#REF!) -> #REF! | T10: =SUMIF(#REF!,$N10,#REF!) -> #REF! | U10: =SUMIF(#REF!,$N10,#REF!) -> #REF! | V10: =SUMIF(#REF!,$N10,#REF!) -> #REF! | W10: =SUMIF(#REF!,$N10,#REF!) -> #REF! | X10: =SUMIF(#REF!,$N10,#REF!) -> #REF! | Y10: =SUMIF(#REF!,$N10,#REF!) -> #REF! | Z10: =SUMIF(#REF!,$N10,#REF!) -> #REF! | ... CB10: =SUMIF(#REF!,$N10,#REF!) -> #REF!
B11: From Store | C11: LS | D11: 1 | G11: =D11*F11 -> 0 | L11: =H38 -> 0 | M11: =L11*J11 -> 0 | N11: Welder | Q11: =SUMPRODUCT(($S$2:$CB$2=$R$2)*1,($S$4:$CB$4=$S$4)*1,S11:CB11)+SUMPRODUCT(($S$2:$CB$2=$R$2)*1,($S$4:$CB$4=$T$4)*1,S11:CB11) -> #REF! | R11: =O11*P11 -> 0 | S11: =SUMIF(#REF!,$N11,#REF!) -> #REF! | T11: =SUMIF(#REF!,$N11,#REF!) -> #REF! | U11: =SUMIF(#REF!,$N11,#REF!) -> #REF! | V11: =SUMIF(#REF!,$N11,#REF!) -> #REF! | W11: =SUMIF(#REF!,$N11,#REF!) -> #REF! | X11: =SUMIF(#REF!,$N11,#REF!) -> #REF! | Y11: =SUMIF(#REF!,$N11,#REF!) -> #REF! | Z11: =SUMIF(#REF!,$N11,#REF!) -> #REF! | ... CB11: =SUMIF(#REF!,$N11,#REF!) -> #REF!
N12: Mechanic | Q12: =SUMPRODUCT(($S$2:$CB$2=$R$2)*1,($S$4:$CB$4=$S$4)*1,S12:CB12)+SUMPRODUCT(($S$2:$CB$2=$R$2)*1,($S$4:$CB$4=$T$4)*1,S12:CB12) -> #REF! | R12: =O12*P12 -> 0 | S12: =SUMIF(#REF!,$N12,#REF!) -> #REF! | T12: =SUMIF(#REF!,$N12,#REF!) -> #REF! | U12: =SUMIF(#REF!,$N12,#REF!) -> #REF! | V12: =SUMIF(#REF!,$N12,#REF!) -> #REF! | W12: =SUMIF(#REF!,$N12,#REF!) -> #REF! | X12: =SUMIF(#REF!,$N12,#REF!) -> #REF! | Y12: =SUMIF(#REF!,$N12,#REF!) -> #REF! | Z12: =SUMIF(#REF!,$N12,#REF!) -> #REF! | ... CB12: =SUMIF(#REF!,$N12,#REF!) -> #REF!
N13: Plumber | Q13: =SUMPRODUCT(($S$2:$CB$2=$R$2)*1,($S$4:$CB$4=$S$4)*1,S13:CB13)+SUMPRODUCT(($S$2:$CB$2=$R$2)*1,($S$4:$CB$4=$T$4)*1,S13:CB13) -> #REF! | R13: =O13*P13 -> 0 | S13: =SUMIF(#REF!,$N13,#REF!) -> #REF! | T13: =SUMIF(#REF!,$N13,#REF!) -> #REF! | U13: =SUMIF(#REF!,$N13,#REF!) -> #REF! | V13: =SUMIF(#REF!,$N13,#REF!) -> #REF! | W13: =SUMIF(#REF!,$N13,#REF!) -> #REF! | X13: =SUMIF(#REF!,$N13,#REF!) -> #REF! | Y13: =SUMIF(#REF!,$N13,#REF!) -> #REF! | Z13: =SUMIF(#REF!,$N13,#REF!) -> #REF! | ... CB13: =SUMIF(#REF!,$N13,#REF!) -> #REF!
G14: =D14*F14 -> 0 | N14: Watchman | Q14: =SUMPRODUCT(($S$2:$CB$2=$R$2)*1,($S$4:$CB$4=$S$4)*1,S14:CB14)+SUMPRODUCT(($S$2:$CB$2=$R$2)*1,($S$4:$CB$4=$T$4)*1,S14:CB14) -> #REF! | R14: =O14*P14 -> 0 | S14: =SUMIF(#REF!,$N14,#REF!) -> #REF! | T14: =SUMIF(#REF!,$N14,#REF!) -> #REF! | U14: =SUMIF(#REF!,$N14,#REF!) -> #REF! | V14: =SUMIF(#REF!,$N14,#REF!) -> #REF! | W14: =SUMIF(#REF!,$N14,#REF!) -> #REF! | X14: =SUMIF(#REF!,$N14,#REF!) -> #REF! | Y14: =SUMIF(#REF!,$N14,#REF!) -> #REF! | Z14: =SUMIF(#REF!,$N14,#REF!) -> #REF! | ... CB14: =SUMIF(#REF!,$N14,#REF!) -> #REF!
F15: 0 | G15: =D15*F15 -> 0 | N15: Ldd Nat. | Q15: =SUMPRODUCT(($S$2:$CB$2=$R$2)*1,($S$4:$CB$4=$S$4)*1,S15:CB15)+SUMPRODUCT(($S$2:$CB$2=$R$2)*1,($S$4:$CB$4=$T$4)*1,S15:CB15) -> #REF! | R15: =O15*P15 -> 0 | S15: =SUMIF(#REF!,$N15,#REF!) -> #REF! | T15: =SUMIF(#REF!,$N15,#REF!) -> #REF! | U15: =SUMIF(#REF!,$N15,#REF!) -> #REF! | V15: =SUMIF(#REF!,$N15,#REF!) -> #REF! | W15: =SUMIF(#REF!,$N15,#REF!) -> #REF! | X15: =SUMIF(#REF!,$N15,#REF!) -> #REF! | Y15: =SUMIF(#REF!,$N15,#REF!) -> #REF! | Z15: =SUMIF(#REF!,$N15,#REF!) -> #REF! | ... CB15: =SUMIF(#REF!,$N15,#REF!) -> #REF!
N16: Hdd Exp. | Q16: =SUMPRODUCT(($S$2:$CB$2=$R$2)*1,($S$4:$CB$4=$S$4)*1,S16:CB16)+SUMPRODUCT(($S$2:$CB$2=$R$2)*1,($S$4:$CB$4=$T$4)*1,S16:CB16) -> #REF! | R16: =O16*P16 -> 0 | S16: =SUMIF(#REF!,$N16,#REF!) -> #REF! | T16: =SUMIF(#REF!,$N16,#REF!) -> #REF! | U16: =SUMIF(#REF!,$N16,#REF!) -> #REF! | V16: =SUMIF(#REF!,$N16,#REF!) -> #REF! | W16: =SUMIF(#REF!,$N16,#REF!) -> #REF! | X16: =SUMIF(#REF!,$N16,#REF!) -> #REF! | Y16: =SUMIF(#REF!,$N16,#REF!) -> #REF! | Z16: =SUMIF(#REF!,$N16,#REF!) -> #REF! | ... CB16: =SUMIF(#REF!,$N16,#REF!) -> #REF!
N17: Hdd Nat. | Q17: =SUMPRODUCT(($S$2:$CB$2=$R$2)*1,($S$4:$CB$4=$S$4)*1,S17:CB17)+SUMPRODUCT(($S$2:$CB$2=$R$2)*1,($S$4:$CB$4=$T$4)*1,S17:CB17) -> #REF! | R17: =O17*P17 -> 0 | S17: =SUMIF(#REF!,$N17,#REF!) -> #REF! | T17: =SUMIF(#REF!,$N17,#REF!) -> #REF! | U17: =SUMIF(#REF!,$N17,#REF!) -> #REF! | V17: =SUMIF(#REF!,$N17,#REF!) -> #REF! | W17: =SUMIF(#REF!,$N17,#REF!) -> #REF! | X17: =SUMIF(#REF!,$N17,#REF!) -> #REF! | Y17: =SUMIF(#REF!,$N17,#REF!) -> #REF! | Z17: =SUMIF(#REF!,$N17,#REF!) -> #REF! | ... CB17: =SUMIF(#REF!,$N17,#REF!) -> #REF!
N18: Optr Exp. | Q18: =SUMPRODUCT(($S$2:$CB$2=$R$2)*1,($S$4:$CB$4=$S$4)*1,S18:CB18)+SUMPRODUCT(($S$2:$CB$2=$R$2)*1,($S$4:$CB$4=$T$4)*1,S18:CB18) -> #REF! | R18: =O18*P18 -> 0 | S18: =SUMIF(#REF!,$N18,#REF!) -> #REF! | T18: =SUMIF(#REF!,$N18,#REF!) -> #REF! | U18: =SUMIF(#REF!,$N18,#REF!) -> #REF! | V18: =SUMIF(#REF!,$N18,#REF!) -> #REF! | W18: =SUMIF(#REF!,$N18,#REF!) -> #REF! | X18: =SUMIF(#REF!,$N18,#REF!) -> #REF! | Y18: =SUMIF(#REF!,$N18,#REF!) -> #REF! | Z18: =SUMIF(#REF!,$N18,#REF!) -> #REF! | ... CB18: =SUMIF(#REF!,$N18,#REF!) -> #REF!
N19: Optr Nat. | Q19: =SUMPRODUCT(($S$2:$CB$2=$R$2)*1,($S$4:$CB$4=$S$4)*1,S19:CB19)+SUMPRODUCT(($S$2:$CB$2=$R$2)*1,($S$4:$CB$4=$T$4)*1,S19:CB19) -> #REF! | R19: =O19*P19 -> 0 | S19: =SUMIF(#REF!,$N19,#REF!) -> #REF! | T19: =SUMIF(#REF!,$N19,#REF!) -> #REF! | U19: =SUMIF(#REF!,$N19,#REF!) -> #REF! | V19: =SUMIF(#REF!,$N19,#REF!) -> #REF! | W19: =SUMIF(#REF!,$N19,#REF!) -> #REF! | X19: =SUMIF(#REF!,$N19,#REF!) -> #REF! | Y19: =SUMIF(#REF!,$N19,#REF!) -> #REF! | Z19: =SUMIF(#REF!,$N19,#REF!) -> #REF! | ... CB19: =SUMIF(#REF!,$N19,#REF!) -> #REF!
F20: 0 | G20: =D20*F20 -> 0 | S20: =SUMIF(#REF!,$N20,#REF!) -> #REF! | T20: =SUMIF(#REF!,$N20,#REF!) -> #REF! | U20: =SUMIF(#REF!,$N20,#REF!) -> #REF! | V20: =SUMIF(#REF!,$N20,#REF!) -> #REF! | W20: =SUMIF(#REF!,$N20,#REF!) -> #REF! | X20: =SUMIF(#REF!,$N20,#REF!) -> #REF! | Y20: =SUMIF(#REF!,$N20,#REF!) -> #REF! | Z20: =SUMIF(#REF!,$N20,#REF!) -> #REF! | ... CB20: =SUMIF(#REF!,$N20,#REF!) -> #REF!
B21: Unit Over Heads | C21: LS | E21: =E69*D21 -> 0 | F21: =I69 -> 0 | G21: =D21*F21 -> 0 | N21: Staff | Q21: =SUMPRODUCT(($S$2:$CB$2=$R$2)*1,($S$4:$CB$4=$S$4)*1,S21:CB21)+SUMPRODUCT(($S$2:$CB$2=$R$2)*1,($S$4:$CB$4=$T$4)*1,S21:CB21) -> 0 | R21: =O21*P21 -> 0 | S21: 78 | U21: 78 | W21: 78 | Y21: 78 | AA21: 78
B22: Total | E22: =SUMPRODUCT(D6:D20,E6:E20)+E21 -> 0 | G22: =SUM(G6:G15) -> 0 | H22: Total | K22: =SUMPRODUCT(J6:J21,K6:K21) -> 0 | M22: =SUM(M6:M20) -> 0 | N22: Total | P22: =SUM(P6:P21) -> 0 | Q22: =SUMPRODUCT(Q6:Q21,O6:O21) -> #REF! | R22: =SUM(R6:R21) -> 0
A23: BOQ # | B23: BOQ Description | C23: Unit | D23: Rate | E23: For the day | F23: Plan Qty | G23: Plan amount | H23: Ach Qty | I23: Ach Amnt | J23: % Ach Wrt Pro | N23: B.Catering/Admin: | O23: Rate | P23: Nos | Q23: For the day | R23: Total Amount
B24: Electricity charges | C24: Month | D24: 1 | G24: =+F24*D24 -> 0 | J24: =IFERROR(H24/F24,"") | N24: Admin/ Catering Charges | P24: =P22 -> 0 | Q24: =SUM(Q6:Q21) -> #REF! | R24: =P24*O24 -> 0
B25: Water & Sewage Charges | C25: Month | D25: 1 | G25: =+F25*D25 -> 0 | J25: =IFERROR(H25/F25,"") | R25: =O25*Q25 -> 0
B26: Rent Land & Office , Accommodation | C26: Month | D26: 1 | G26: =+F26*D26 -> 0 | J26: =IFERROR(H26/F26,"") | N26: Total | Q26: =Q24*O24 -> #REF! | R26: =SUM(R24:R25) -> 0
B27: Staff Welfare | C27: Month | D27: 1 | G27: =+F27*D27 -> 0 | J27: =IFERROR(H27/F27,"") | N27: C.Machinery:
B28: Safety Expenses | C28: Month | D28: 1 | G28: =+F28*D28 -> 0 | J28: =IFERROR(H28/F28,"") | N28: Decsription | O28: Rate per Hr | P28: Nos | Q28: For the day | R28: Total Amount
B29: Medical Expenses | C29: Month | D29: 1 | G29: =+F29*D29 -> 0 | J29: =IFERROR(H29/F29,"") | N29: Heavy Bus | Q29: =SUMPRODUCT(($S$2:$CB$2=$R$2)*1,($S$4:$CB$4=$S$4)*1,S29:CB29)+SUMPRODUCT(($S$2:$CB$2=$R$2)*1,($S$4:$CB$4=$T$4)*1,S29:CB29)*0.75 -> #REF! | R29: =O29*P29 -> 0 | S29: =SUMIF(#REF!,$N29,#REF!) -> #REF! | T29: =SUMIF(#REF!,$N29,#REF!) -> #REF! | U29: =SUMIF(#REF!,$N29,#REF!) -> #REF! | V29: =SUMIF(#REF!,$N29,#REF!) -> #REF! | W29: =SUMIF(#REF!,$N29,#REF!) -> #REF! | X29: =SUMIF(#REF!,$N29,#REF!) -> #REF! | Y29: =SUMIF(#REF!,$N29,#REF!) -> #REF! | Z29: =SUMIF(#REF!,$N29,#REF!) -> #REF! | ... CB29: =SUMIF(#REF!,$N29,#REF!) -> #REF!
B30: Printing & Stationary | C30: Month | D30: 1 | G30: =+F30*D30 -> 0 | J30: =IFERROR(H30/F30,"") | N30: Potable Water Tanker | Q30: =SUMPRODUCT(($S$2:$CB$2=$R$2)*1,($S$4:$CB$4=$S$4)*1,S30:CB30)+SUMPRODUCT(($S$2:$CB$2=$R$2)*1,($S$4:$CB$4=$T$4)*1,S30:CB30)*0.75 -> #REF! | R30: =O30*P30 -> 0 | S30: =SUMIF(#REF!,$N30,#REF!) -> #REF! | T30: =SUMIF(#REF!,$N30,#REF!) -> #REF! | U30: =SUMIF(#REF!,$N30,#REF!) -> #REF! | V30: =SUMIF(#REF!,$N30,#REF!) -> #REF! | W30: =SUMIF(#REF!,$N30,#REF!) -> #REF! | X30: =SUMIF(#REF!,$N30,#REF!) -> #REF! | Y30: =SUMIF(#REF!,$N30,#REF!) -> #REF! | Z30: =SUMIF(#REF!,$N30,#REF!) -> #REF! | ... CB30: =SUMIF(#REF!,$N30,#REF!) -> #REF!
B31: Communication Expenses | C31: Month | D31: 1 | G31: =+F31*D31 -> 0 | J31: =IFERROR(H31/F31,"") | N31: Sewage Tanker | Q31: =SUMPRODUCT(($S$2:$CB$2=$R$2)*1,($S$4:$CB$4=$S$4)*1,S31:CB31)+SUMPRODUCT(($S$2:$CB$2=$R$2)*1,($S$4:$CB$4=$T$4)*1,S31:CB31)*0.75 -> #REF! | R31: =O31*P31 -> 0 | S31: =SUMIF(#REF!,$N31,#REF!) -> #REF! | T31: =SUMIF(#REF!,$N31,#REF!) -> #REF! | U31: =SUMIF(#REF!,$N31,#REF!) -> #REF! | V31: =SUMIF(#REF!,$N31,#REF!) -> #REF! | W31: =SUMIF(#REF!,$N31,#REF!) -> #REF! | X31: =SUMIF(#REF!,$N31,#REF!) -> #REF! | Y31: =SUMIF(#REF!,$N31,#REF!) -> #REF! | Z31: =SUMIF(#REF!,$N31,#REF!) -> #REF! | ... CB31: =SUMIF(#REF!,$N31,#REF!) -> #REF!
B32: Business Promotion | C32: Month | D32: 1 | G32: =+F32*D32 -> 0 | J32: =IFERROR(H32/F32,"") | N32: Fuel Tanker | Q32: =SUMPRODUCT(($S$2:$CB$2=$R$2)*1,($S$4:$CB$4=$S$4)*1,S32:CB32)+SUMPRODUCT(($S$2:$CB$2=$R$2)*1,($S$4:$CB$4=$T$4)*1,S32:CB32)*0.75 -> #REF! | R32: =O32*P32 -> 0 | S32: =SUMIF(#REF!,$N32,#REF!) -> #REF! | T32: =SUMIF(#REF!,$N32,#REF!) -> #REF! | U32: =SUMIF(#REF!,$N32,#REF!) -> #REF! | V32: =SUMIF(#REF!,$N32,#REF!) -> #REF! | W32: =SUMIF(#REF!,$N32,#REF!) -> #REF! | X32: =SUMIF(#REF!,$N32,#REF!) -> #REF! | Y32: =SUMIF(#REF!,$N32,#REF!) -> #REF! | Z32: =SUMIF(#REF!,$N32,#REF!) -> #REF! | ... CB32: =SUMIF(#REF!,$N32,#REF!) -> #REF!
B33: Travel & Conveyance | C33: Month | D33: 1 | G33: =+F33*D33 -> 0 | J33: =IFERROR(H33/F33,"") | N33: Fork Lift | Q33: =SUMPRODUCT(($S$2:$CB$2=$R$2)*1,($S$4:$CB$4=$S$4)*1,S33:CB33)+SUMPRODUCT(($S$2:$CB$2=$R$2)*1,($S$4:$CB$4=$T$4)*1,S33:CB33)*0.75 -> #REF! | R33: =O33*P33 -> 0 | S33: =SUMIF(#REF!,$N33,#REF!) -> #REF! | T33: =SUMIF(#REF!,$N33,#REF!) -> #REF! | U33: =SUMIF(#REF!,$N33,#REF!) -> #REF! | V33: =SUMIF(#REF!,$N33,#REF!) -> #REF! | W33: =SUMIF(#REF!,$N33,#REF!) -> #REF! | X33: =SUMIF(#REF!,$N33,#REF!) -> #REF! | Y33: =SUMIF(#REF!,$N33,#REF!) -> #REF! | Z33: =SUMIF(#REF!,$N33,#REF!) -> #REF! | ... CB33: =SUMIF(#REF!,$N33,#REF!) -> #REF!
B34: Legal & Professional Charges | C34: Month | D34: 1 | G34: =+F34*D34 -> 0 | J34: =IFERROR(H34/F34,"") | N34: 3 Ton Canter | Q34: =SUMPRODUCT(($S$2:$CB$2=$R$2)*1,($S$4:$CB$4=$S$4)*1,S34:CB34)+SUMPRODUCT(($S$2:$CB$2=$R$2)*1,($S$4:$CB$4=$T$4)*1,S34:CB34)*0.75 -> #REF! | R34: =O34*P34 -> 0 | S34: =SUMIF(#REF!,$N34,#REF!) -> #REF! | T34: =SUMIF(#REF!,$N34,#REF!) -> #REF! | U34: =SUMIF(#REF!,$N34,#REF!) -> #REF! | V34: =SUMIF(#REF!,$N34,#REF!) -> #REF! | W34: =SUMIF(#REF!,$N34,#REF!) -> #REF! | X34: =SUMIF(#REF!,$N34,#REF!) -> #REF! | Y34: =SUMIF(#REF!,$N34,#REF!) -> #REF! | Z34: =SUMIF(#REF!,$N34,#REF!) -> #REF! | ... CB34: =SUMIF(#REF!,$N34,#REF!) -> #REF!
B35: Consultant Overtime | C35: Month | D35: 1 | G35: =+F35*D35 -> 0 | J35: =IFERROR(H35/F35,"") | N35: Mini Bus | Q35: =SUMPRODUCT(($S$2:$CB$2=$R$2)*1,($S$4:$CB$4=$S$4)*1,S35:CB35)+SUMPRODUCT(($S$2:$CB$2=$R$2)*1,($S$4:$CB$4=$T$4)*1,S35:CB35)*0.75 -> #REF! | R35: =O35*P35 -> 0 | S35: =SUMIF(#REF!,$N35,#REF!) -> #REF! | T35: =SUMIF(#REF!,$N35,#REF!) -> #REF! | U35: =SUMIF(#REF!,$N35,#REF!) -> #REF! | V35: =SUMIF(#REF!,$N35,#REF!) -> #REF! | W35: =SUMIF(#REF!,$N35,#REF!) -> #REF! | X35: =SUMIF(#REF!,$N35,#REF!) -> #REF! | Y35: =SUMIF(#REF!,$N35,#REF!) -> #REF! | Z35: =SUMIF(#REF!,$N35,#REF!) -> #REF! | ... CB35: =SUMIF(#REF!,$N35,#REF!) -> #REF!
B36: Repairs & Maintainence | C36: Month | D36: 1 | G36: =+F36*D36 -> 0 | J36: =IFERROR(H36/F36,"") | N36: Station Wagon | Q36: =SUMPRODUCT(($S$2:$CB$2=$R$2)*1,($S$4:$CB$4=$S$4)*1,S36:CB36)+SUMPRODUCT(($S$2:$CB$2=$R$2)*1,($S$4:$CB$4=$T$4)*1,S36:CB36)*0.75 -> #REF! | R36: =O36*P36 -> 0 | S36: =SUMIF(#REF!,$N36,#REF!) -> #REF! | T36: =SUMIF(#REF!,$N36,#REF!) -> #REF! | U36: =SUMIF(#REF!,$N36,#REF!) -> #REF! | V36: =SUMIF(#REF!,$N36,#REF!) -> #REF! | W36: =SUMIF(#REF!,$N36,#REF!) -> #REF! | X36: =SUMIF(#REF!,$N36,#REF!) -> #REF! | Y36: =SUMIF(#REF!,$N36,#REF!) -> #REF! | Z36: =SUMIF(#REF!,$N36,#REF!) -> #REF! | ... CB36: =SUMIF(#REF!,$N36,#REF!) -> #REF!
B37: Lab Testing Charges | C37: Month | D37: 1 | G37: =+F37*D37 -> 0 | J37: =IFERROR(H37/F37,"") | N37: Saloon Car | Q37: =SUMPRODUCT(($S$2:$CB$2=$R$2)*1,($S$4:$CB$4=$S$4)*1,S37:CB37)+SUMPRODUCT(($S$2:$CB$2=$R$2)*1,($S$4:$CB$4=$T$4)*1,S37:CB37)*0.75 -> #REF! | R37: =O37*P37 -> 0 | S37: =SUMIF(#REF!,$N37,#REF!) -> #REF! | T37: =SUMIF(#REF!,$N37,#REF!) -> #REF! | U37: =SUMIF(#REF!,$N37,#REF!) -> #REF! | V37: =SUMIF(#REF!,$N37,#REF!) -> #REF! | W37: =SUMIF(#REF!,$N37,#REF!) -> #REF! | X37: =SUMIF(#REF!,$N37,#REF!) -> #REF! | Y37: =SUMIF(#REF!,$N37,#REF!) -> #REF! | Z37: =SUMIF(#REF!,$N37,#REF!) -> #REF! | ... CB37: =SUMIF(#REF!,$N37,#REF!) -> #REF!
B38: Other Miscellaneous Exps. | C38: Month | D38: 1 | G38: =+F38*D38 -> 0 | J38: =IFERROR(H38/F38,"") | N38: Ambulance | Q38: =SUMPRODUCT(($S$2:$CB$2=$R$2)*1,($S$4:$CB$4=$S$4)*1,S38:CB38)+SUMPRODUCT(($S$2:$CB$2=$R$2)*1,($S$4:$CB$4=$T$4)*1,S38:CB38)*0.75 -> #REF! | R38: =O38*P38 -> 0 | S38: =SUMIF(#REF!,$N38,#REF!) -> #REF! | T38: =SUMIF(#REF!,$N38,#REF!) -> #REF! | U38: =SUMIF(#REF!,$N38,#REF!) -> #REF! | V38: =SUMIF(#REF!,$N38,#REF!) -> #REF! | W38: =SUMIF(#REF!,$N38,#REF!) -> #REF! | X38: =SUMIF(#REF!,$N38,#REF!) -> #REF! | Y38: =SUMIF(#REF!,$N38,#REF!) -> #REF! | Z38: =SUMIF(#REF!,$N38,#REF!) -> #REF! | ... CB38: =SUMIF(#REF!,$N38,#REF!) -> #REF!
G39: =+F39*D39 -> 0 | J39: =IFERROR(H39/F39,"") | N39: Pickup | Q39: =SUMPRODUCT(($S$2:$CB$2=$R$2)*1,($S$4:$CB$4=$S$4)*1,S39:CB39)+SUMPRODUCT(($S$2:$CB$2=$R$2)*1,($S$4:$CB$4=$T$4)*1,S39:CB39)*0.75 -> #REF! | R39: =O39*P39 -> 0 | S39: =SUMIF(#REF!,$N39,#REF!) -> #REF! | T39: =SUMIF(#REF!,$N39,#REF!) -> #REF! | U39: =SUMIF(#REF!,$N39,#REF!) -> #REF! | V39: =SUMIF(#REF!,$N39,#REF!) -> #REF! | W39: =SUMIF(#REF!,$N39,#REF!) -> #REF! | X39: =SUMIF(#REF!,$N39,#REF!) -> #REF! | Y39: =SUMIF(#REF!,$N39,#REF!) -> #REF! | Z39: =SUMIF(#REF!,$N39,#REF!) -> #REF! | ... CB39: =SUMIF(#REF!,$N39,#REF!) -> #REF!
B40: Depreciation - Equips. & Furnitures | C40: LS | D40: 1 | G40: =+F40*D40 -> 0 | J40: =IFERROR(H40/F40,"") | N40: Dewatering Pump | Q40: =SUMPRODUCT(($S$2:$CB$2=$R$2)*1,($S$4:$CB$4=$S$4)*1,S40:CB40)+SUMPRODUCT(($S$2:$CB$2=$R$2)*1,($S$4:$CB$4=$T$4)*1,S40:CB40)*0.75 -> #REF! | R40: =O40*P40 -> 0 | S40: =SUMIF(#REF!,$N40,#REF!) -> #REF! | T40: =SUMIF(#REF!,$N40,#REF!) -> #REF! | U40: =SUMIF(#REF!,$N40,#REF!) -> #REF! | V40: =SUMIF(#REF!,$N40,#REF!) -> #REF! | W40: =SUMIF(#REF!,$N40,#REF!) -> #REF! | X40: =SUMIF(#REF!,$N40,#REF!) -> #REF! | Y40: =SUMIF(#REF!,$N40,#REF!) -> #REF! | Z40: =SUMIF(#REF!,$N40,#REF!) -> #REF! | ... CB40: =SUMIF(#REF!,$N40,#REF!) -> #REF!
G41: =+F41*D41 -> 0 | J41: =IFERROR(H41/F41,"") | N41: Generator 1000 kva | Q41: =SUMPRODUCT(($S$2:$CB$2=$R$2)*1,($S$4:$CB$4=$S$4)*1,S41:CB41)+SUMPRODUCT(($S$2:$CB$2=$R$2)*1,($S$4:$CB$4=$T$4)*1,S41:CB41)*0.75 -> #REF! | R41: =O41*P41 -> 0 | S41: =SUMIF(#REF!,$N41,#REF!) -> #REF! | T41: =SUMIF(#REF!,$N41,#REF!) -> #REF! | U41: =SUMIF(#REF!,$N41,#REF!) -> #REF! | V41: =SUMIF(#REF!,$N41,#REF!) -> #REF! | W41: =SUMIF(#REF!,$N41,#REF!) -> #REF! | X41: =SUMIF(#REF!,$N41,#REF!) -> #REF! | Y41: =SUMIF(#REF!,$N41,#REF!) -> #REF! | Z41: =SUMIF(#REF!,$N41,#REF!) -> #REF! | ... CB41: =SUMIF(#REF!,$N41,#REF!) -> #REF!
B42: Insurance Charges (0.015% of CV) | C42: Month | D42: 1 | G42: =+F42*D42 -> 0 | J42: =IFERROR(H42/F42,"") | N42: Generator upto 30 kva | Q42: =SUMPRODUCT(($S$2:$CB$2=$R$2)*1,($S$4:$CB$4=$S$4)*1,S42:CB42)+SUMPRODUCT(($S$2:$CB$2=$R$2)*1,($S$4:$CB$4=$T$4)*1,S42:CB42)*0.75 -> #REF! | R42: =O42*P42 -> 0 | S42: =SUMIF(#REF!,$N42,#REF!) -> #REF! | T42: =SUMIF(#REF!,$N42,#REF!) -> #REF! | U42: =SUMIF(#REF!,$N42,#REF!) -> #REF! | V42: =SUMIF(#REF!,$N42,#REF!) -> #REF! | W42: =SUMIF(#REF!,$N42,#REF!) -> #REF! | X42: =SUMIF(#REF!,$N42,#REF!) -> #REF! | Y42: =SUMIF(#REF!,$N42,#REF!) -> #REF! | Z42: =SUMIF(#REF!,$N42,#REF!) -> #REF! | ... CB42: =SUMIF(#REF!,$N42,#REF!) -> #REF!
B43: Bank Charges (0.01% of CV) | C43: Month | D43: 1 | G43: =+F43*D43 -> 0 | J43: =IFERROR(H43/F43,"") | N43: Generator upto 50 to 100 kva | Q43: =SUMPRODUCT(($S$2:$CB$2=$R$2)*1,($S$4:$CB$4=$S$4)*1,S43:CB43)+SUMPRODUCT(($S$2:$CB$2=$R$2)*1,($S$4:$CB$4=$T$4)*1,S43:CB43)*0.75 -> #REF! | R43: =O43*P43 -> 0 | S43: =SUMIF(#REF!,$N43,#REF!) -> #REF! | T43: =SUMIF(#REF!,$N43,#REF!) -> #REF! | U43: =SUMIF(#REF!,$N43,#REF!) -> #REF! | V43: =SUMIF(#REF!,$N43,#REF!) -> #REF! | W43: =SUMIF(#REF!,$N43,#REF!) -> #REF! | X43: =SUMIF(#REF!,$N43,#REF!) -> #REF! | Y43: =SUMIF(#REF!,$N43,#REF!) -> #REF! | Z43: =SUMIF(#REF!,$N43,#REF!) -> #REF! | ... CB43: =SUMIF(#REF!,$N43,#REF!) -> #REF!
J44: =IFERROR(H44/F44,"") | N44: Generator upto 150 to 250 kva | Q44: =SUMPRODUCT(($S$2:$CB$2=$R$2)*1,($S$4:$CB$4=$S$4)*1,S44:CB44)+SUMPRODUCT(($S$2:$CB$2=$R$2)*1,($S$4:$CB$4=$T$4)*1,S44:CB44)*0.75 -> #REF! | R44: =O44*P44 -> 0 | S44: =SUMIF(#REF!,$N44,#REF!) -> #REF! | T44: =SUMIF(#REF!,$N44,#REF!) -> #REF! | U44: =SUMIF(#REF!,$N44,#REF!) -> #REF! | V44: =SUMIF(#REF!,$N44,#REF!) -> #REF! | W44: =SUMIF(#REF!,$N44,#REF!) -> #REF! | X44: =SUMIF(#REF!,$N44,#REF!) -> #REF! | Y44: =SUMIF(#REF!,$N44,#REF!) -> #REF! | Z44: =SUMIF(#REF!,$N44,#REF!) -> #REF! | ... CB44: =SUMIF(#REF!,$N44,#REF!) -> #REF!
B45: Contingency | C45: Month | D45: 1 | J45: =IFERROR(H45/F45,"") | N45: Generator 500 kva | Q45: =SUMPRODUCT(($S$2:$CB$2=$R$2)*1,($S$4:$CB$4=$S$4)*1,S45:CB45)+SUMPRODUCT(($S$2:$CB$2=$R$2)*1,($S$4:$CB$4=$T$4)*1,S45:CB45)*0.75 -> #REF! | R45: =O45*P45 -> 0 | S45: =SUMIF(#REF!,$N45,#REF!) -> #REF! | T45: =SUMIF(#REF!,$N45,#REF!) -> #REF! | U45: =SUMIF(#REF!,$N45,#REF!) -> #REF! | V45: =SUMIF(#REF!,$N45,#REF!) -> #REF! | W45: =SUMIF(#REF!,$N45,#REF!) -> #REF! | X45: =SUMIF(#REF!,$N45,#REF!) -> #REF! | Y45: =SUMIF(#REF!,$N45,#REF!) -> #REF! | Z45: =SUMIF(#REF!,$N45,#REF!) -> #REF! | ... CB45: =SUMIF(#REF!,$N45,#REF!) -> #REF!
B46: Accomodation Charges | C46: Month | D46: 1 | G46: =+F46*D46 -> 0 | J46: =IFERROR(H46/F46,"") | N46: Welding Generator | Q46: =SUMPRODUCT(($S$2:$CB$2=$R$2)*1,($S$4:$CB$4=$S$4)*1,S46:CB46)+SUMPRODUCT(($S$2:$CB$2=$R$2)*1,($S$4:$CB$4=$T$4)*1,S46:CB46)*0.75 -> #REF! | R46: =O46*P46 -> 0 | S46: =SUMIF(#REF!,$N46,#REF!) -> #REF! | T46: =SUMIF(#REF!,$N46,#REF!) -> #REF! | U46: =SUMIF(#REF!,$N46,#REF!) -> #REF! | V46: =SUMIF(#REF!,$N46,#REF!) -> #REF! | W46: =SUMIF(#REF!,$N46,#REF!) -> #REF! | X46: =SUMIF(#REF!,$N46,#REF!) -> #REF! | Y46: =SUMIF(#REF!,$N46,#REF!) -> #REF! | Z46: =SUMIF(#REF!,$N46,#REF!) -> #REF! | ... CB46: =SUMIF(#REF!,$N46,#REF!) -> #REF!
J47: =IFERROR(H47/F47,"") | N47: Air Compressor | Q47: =SUMPRODUCT(($S$2:$CB$2=$R$2)*1,($S$4:$CB$4=$S$4)*1,S47:CB47)+SUMPRODUCT(($S$2:$CB$2=$R$2)*1,($S$4:$CB$4=$T$4)*1,S47:CB47)*0.75 -> #REF! | R47: =O47*P47 -> 0 | S47: =SUMIF(#REF!,$N47,#REF!) -> #REF! | T47: =SUMIF(#REF!,$N47,#REF!) -> #REF! | U47: =SUMIF(#REF!,$N47,#REF!) -> #REF! | V47: =SUMIF(#REF!,$N47,#REF!) -> #REF! | W47: =SUMIF(#REF!,$N47,#REF!) -> #REF! | X47: =SUMIF(#REF!,$N47,#REF!) -> #REF! | Y47: =SUMIF(#REF!,$N47,#REF!) -> #REF! | Z47: =SUMIF(#REF!,$N47,#REF!) -> #REF! | ... CB47: =SUMIF(#REF!,$N47,#REF!) -> #REF!
J48: =IFERROR(H48/F48,"") | N48: Wheel Loader | Q48: =SUMPRODUCT(($S$2:$CB$2=$R$2)*1,($S$4:$CB$4=$S$4)*1,S48:CB48)+SUMPRODUCT(($S$2:$CB$2=$R$2)*1,($S$4:$CB$4=$T$4)*1,S48:CB48)*0.75 -> #REF! | R48: =O48*P48 -> 0 | S48: =SUMIF(#REF!,$N48,#REF!) -> #REF! | T48: =SUMIF(#REF!,$N48,#REF!) -> #REF! | U48: =SUMIF(#REF!,$N48,#REF!) -> #REF! | V48: =SUMIF(#REF!,$N48,#REF!) -> #REF! | W48: =SUMIF(#REF!,$N48,#REF!) -> #REF! | X48: =SUMIF(#REF!,$N48,#REF!) -> #REF! | Y48: =SUMIF(#REF!,$N48,#REF!) -> #REF! | Z48: =SUMIF(#REF!,$N48,#REF!) -> #REF! | ... CB48: =SUMIF(#REF!,$N48,#REF!) -> #REF!
J49: =IFERROR(H49/F49,"") | N49: Low bed trailer | Q49: =SUMPRODUCT(($S$2:$CB$2=$R$2)*1,($S$4:$CB$4=$S$4)*1,S49:CB49)+SUMPRODUCT(($S$2:$CB$2=$R$2)*1,($S$4:$CB$4=$T$4)*1,S49:CB49)*0.75 -> #REF! | R49: =O49*P49 -> 0 | S49: =SUMIF(#REF!,$N49,#REF!) -> #REF! | T49: =SUMIF(#REF!,$N49,#REF!) -> #REF! | U49: =SUMIF(#REF!,$N49,#REF!) -> #REF! | V49: =SUMIF(#REF!,$N49,#REF!) -> #REF! | W49: =SUMIF(#REF!,$N49,#REF!) -> #REF! | X49: =SUMIF(#REF!,$N49,#REF!) -> #REF! | Y49: =SUMIF(#REF!,$N49,#REF!) -> #REF! | Z49: =SUMIF(#REF!,$N49,#REF!) -> #REF! | ... CB49: =SUMIF(#REF!,$N49,#REF!) -> #REF!
J50: =IFERROR(H50/F50,"") | N50: Tipper | Q50: =SUMPRODUCT(($S$2:$CB$2=$R$2)*1,($S$4:$CB$4=$S$4)*1,S50:CB50)+SUMPRODUCT(($S$2:$CB$2=$R$2)*1,($S$4:$CB$4=$T$4)*1,S50:CB50)*0.75 -> #REF! | R50: =O50*P50 -> 0 | S50: =SUMIF(#REF!,$N50,#REF!) -> #REF! | T50: =SUMIF(#REF!,$N50,#REF!) -> #REF! | U50: =SUMIF(#REF!,$N50,#REF!) -> #REF! | V50: =SUMIF(#REF!,$N50,#REF!) -> #REF! | W50: =SUMIF(#REF!,$N50,#REF!) -> #REF! | X50: =SUMIF(#REF!,$N50,#REF!) -> #REF! | Y50: =SUMIF(#REF!,$N50,#REF!) -> #REF! | Z50: =SUMIF(#REF!,$N50,#REF!) -> #REF! | ... CB50: =SUMIF(#REF!,$N50,#REF!) -> #REF!
J51: =IFERROR(H51/F51,"") | N51: Tower Light | Q51: =SUMPRODUCT(($S$2:$CB$2=$R$2)*1,($S$4:$CB$4=$S$4)*1,S51:CB51)+SUMPRODUCT(($S$2:$CB$2=$R$2)*1,($S$4:$CB$4=$T$4)*1,S51:CB51)*0.75 -> #REF! | R51: =O51*P51 -> 0 | S51: =SUMIF(#REF!,$N51,#REF!) -> #REF! | T51: =SUMIF(#REF!,$N51,#REF!) -> #REF! | U51: =SUMIF(#REF!,$N51,#REF!) -> #REF! | V51: =SUMIF(#REF!,$N51,#REF!) -> #REF! | W51: =SUMIF(#REF!,$N51,#REF!) -> #REF! | X51: =SUMIF(#REF!,$N51,#REF!) -> #REF! | Y51: =SUMIF(#REF!,$N51,#REF!) -> #REF! | Z51: =SUMIF(#REF!,$N51,#REF!) -> #REF! | ... CB51: =SUMIF(#REF!,$N51,#REF!) -> #REF!
J52: =IFERROR(H52/F52,"") | N52: Dumper | Q52: =SUMPRODUCT(($S$2:$CB$2=$R$2)*1,($S$4:$CB$4=$S$4)*1,S52:CB52)+SUMPRODUCT(($S$2:$CB$2=$R$2)*1,($S$4:$CB$4=$T$4)*1,S52:CB52)*0.75 -> #REF! | R52: =O52*P52 -> 0 | S52: =SUMIF(#REF!,$N52,#REF!) -> #REF! | T52: =SUMIF(#REF!,$N52,#REF!) -> #REF! | U52: =SUMIF(#REF!,$N52,#REF!) -> #REF! | V52: =SUMIF(#REF!,$N52,#REF!) -> #REF! | W52: =SUMIF(#REF!,$N52,#REF!) -> #REF! | X52: =SUMIF(#REF!,$N52,#REF!) -> #REF! | Y52: =SUMIF(#REF!,$N52,#REF!) -> #REF! | Z52: =SUMIF(#REF!,$N52,#REF!) -> #REF! | ... CB52: =SUMIF(#REF!,$N52,#REF!) -> #REF!
J53: =IFERROR(H53/F53,"") | S53: =SUMIF(#REF!,$N53,#REF!) -> #REF! | T53: =SUMIF(#REF!,$N53,#REF!) -> #REF! | U53: =SUMIF(#REF!,$N53,#REF!) -> #REF! | V53: =SUMIF(#REF!,$N53,#REF!) -> #REF! | W53: =SUMIF(#REF!,$N53,#REF!) -> #REF! | X53: =SUMIF(#REF!,$N53,#REF!) -> #REF! | Y53: =SUMIF(#REF!,$N53,#REF!) -> #REF! | Z53: =SUMIF(#REF!,$N53,#REF!) -> #REF! | ... CB53: =SUMIF(#REF!,$N53,#REF!) -> #REF!
J54: =IFERROR(H54/F54,"") | S54: =SUMIF(#REF!,$N54,#REF!) -> #REF! | T54: =SUMIF(#REF!,$N54,#REF!) -> #REF! | U54: =SUMIF(#REF!,$N54,#REF!) -> #REF! | V54: =SUMIF(#REF!,$N54,#REF!) -> #REF! | W54: =SUMIF(#REF!,$N54,#REF!) -> #REF! | X54: =SUMIF(#REF!,$N54,#REF!) -> #REF! | Y54: =SUMIF(#REF!,$N54,#REF!) -> #REF! | Z54: =SUMIF(#REF!,$N54,#REF!) -> #REF! | ... CB54: =SUMIF(#REF!,$N54,#REF!) -> #REF!
J55: =IFERROR(H55/F55,"") | S55: =SUMIF(#REF!,$N55,#REF!) -> #REF! | T55: =SUMIF(#REF!,$N55,#REF!) -> #REF! | U55: =SUMIF(#REF!,$N55,#REF!) -> #REF! | V55: =SUMIF(#REF!,$N55,#REF!) -> #REF! | W55: =SUMIF(#REF!,$N55,#REF!) -> #REF! | X55: =SUMIF(#REF!,$N55,#REF!) -> #REF! | Y55: =SUMIF(#REF!,$N55,#REF!) -> #REF! | Z55: =SUMIF(#REF!,$N55,#REF!) -> #REF! | ... CB55: =SUMIF(#REF!,$N55,#REF!) -> #REF!
J56: =IFERROR(H56/F56,"") | S56: =SUMIF(#REF!,$N56,#REF!) -> #REF! | T56: =SUMIF(#REF!,$N56,#REF!) -> #REF! | U56: =SUMIF(#REF!,$N56,#REF!) -> #REF! | V56: =SUMIF(#REF!,$N56,#REF!) -> #REF! | W56: =SUMIF(#REF!,$N56,#REF!) -> #REF! | X56: =SUMIF(#REF!,$N56,#REF!) -> #REF! | Y56: =SUMIF(#REF!,$N56,#REF!) -> #REF! | Z56: =SUMIF(#REF!,$N56,#REF!) -> #REF! | ... CB56: =SUMIF(#REF!,$N56,#REF!) -> #REF!
J57: =IFERROR(H57/F57,"") | S57: =SUMIF(#REF!,$N57,#REF!) -> #REF! | T57: =SUMIF(#REF!,$N57,#REF!) -> #REF! | U57: =SUMIF(#REF!,$N57,#REF!) -> #REF! | V57: =SUMIF(#REF!,$N57,#REF!) -> #REF! | W57: =SUMIF(#REF!,$N57,#REF!) -> #REF! | X57: =SUMIF(#REF!,$N57,#REF!) -> #REF! | Y57: =SUMIF(#REF!,$N57,#REF!) -> #REF! | Z57: =SUMIF(#REF!,$N57,#REF!) -> #REF! | ... CB57: =SUMIF(#REF!,$N57,#REF!) -> #REF!
J58: =IFERROR(H58/F58,"") | S58: =SUMIF(#REF!,$N58,#REF!) -> #REF! | T58: =SUMIF(#REF!,$N58,#REF!) -> #REF! | U58: =SUMIF(#REF!,$N58,#REF!) -> #REF! | V58: =SUMIF(#REF!,$N58,#REF!) -> #REF! | W58: =SUMIF(#REF!,$N58,#REF!) -> #REF! | X58: =SUMIF(#REF!,$N58,#REF!) -> #REF! | Y58: =SUMIF(#REF!,$N58,#REF!) -> #REF! | Z58: =SUMIF(#REF!,$N58,#REF!) -> #REF! | ... CB58: =SUMIF(#REF!,$N58,#REF!) -> #REF!
J59: =IFERROR(H59/F59,"") | S59: =SUMIF(#REF!,$N59,#REF!) -> #REF! | T59: =SUMIF(#REF!,$N59,#REF!) -> #REF! | U59: =SUMIF(#REF!,$N59,#REF!) -> #REF! | V59: =SUMIF(#REF!,$N59,#REF!) -> #REF! | W59: =SUMIF(#REF!,$N59,#REF!) -> #REF! | X59: =SUMIF(#REF!,$N59,#REF!) -> #REF! | Y59: =SUMIF(#REF!,$N59,#REF!) -> #REF! | Z59: =SUMIF(#REF!,$N59,#REF!) -> #REF! | ... CB59: =SUMIF(#REF!,$N59,#REF!) -> #REF!
J60: =IFERROR(H60/F60,"") | S60: =SUMIF(#REF!,$N60,#REF!) -> #REF! | T60: =SUMIF(#REF!,$N60,#REF!) -> #REF! | U60: =SUMIF(#REF!,$N60,#REF!) -> #REF! | V60: =SUMIF(#REF!,$N60,#REF!) -> #REF! | W60: =SUMIF(#REF!,$N60,#REF!) -> #REF! | X60: =SUMIF(#REF!,$N60,#REF!) -> #REF! | Y60: =SUMIF(#REF!,$N60,#REF!) -> #REF! | Z60: =SUMIF(#REF!,$N60,#REF!) -> #REF! | ... CB60: =SUMIF(#REF!,$N60,#REF!) -> #REF!
J61: =IFERROR(H61/F61,"") | S61: =SUMIF(#REF!,$N61,#REF!) -> #REF! | T61: =SUMIF(#REF!,$N61,#REF!) -> #REF! | U61: =SUMIF(#REF!,$N61,#REF!) -> #REF! | V61: =SUMIF(#REF!,$N61,#REF!) -> #REF! | W61: =SUMIF(#REF!,$N61,#REF!) -> #REF! | X61: =SUMIF(#REF!,$N61,#REF!) -> #REF! | Y61: =SUMIF(#REF!,$N61,#REF!) -> #REF! | Z61: =SUMIF(#REF!,$N61,#REF!) -> #REF! | ... CB61: =SUMIF(#REF!,$N61,#REF!) -> #REF!
J62: =IFERROR(H62/F62,"") | S62: =SUMIF(#REF!,$N62,#REF!) -> #REF! | T62: =SUMIF(#REF!,$N62,#REF!) -> #REF! | U62: =SUMIF(#REF!,$N62,#REF!) -> #REF! | V62: =SUMIF(#REF!,$N62,#REF!) -> #REF! | W62: =SUMIF(#REF!,$N62,#REF!) -> #REF! | X62: =SUMIF(#REF!,$N62,#REF!) -> #REF! | Y62: =SUMIF(#REF!,$N62,#REF!) -> #REF! | Z62: =SUMIF(#REF!,$N62,#REF!) -> #REF! | ... CB62: =SUMIF(#REF!,$N62,#REF!) -> #REF!
J63: =IFERROR(H63/F63,"") | S63: =SUMIF(#REF!,$N63,#REF!) -> #REF! | T63: =SUMIF(#REF!,$N63,#REF!) -> #REF! | U63: =SUMIF(#REF!,$N63,#REF!) -> #REF! | V63: =SUMIF(#REF!,$N63,#REF!) -> #REF! | W63: =SUMIF(#REF!,$N63,#REF!) -> #REF! | X63: =SUMIF(#REF!,$N63,#REF!) -> #REF! | Y63: =SUMIF(#REF!,$N63,#REF!) -> #REF! | Z63: =SUMIF(#REF!,$N63,#REF!) -> #REF! | ... CB63: =SUMIF(#REF!,$N63,#REF!) -> #REF!
J64: =IFERROR(H64/F64,"") | S64: =SUMIF(#REF!,$N64,#REF!) -> #REF! | T64: =SUMIF(#REF!,$N64,#REF!) -> #REF! | U64: =SUMIF(#REF!,$N64,#REF!) -> #REF! | V64: =SUMIF(#REF!,$N64,#REF!) -> #REF! | W64: =SUMIF(#REF!,$N64,#REF!) -> #REF! | X64: =SUMIF(#REF!,$N64,#REF!) -> #REF! | Y64: =SUMIF(#REF!,$N64,#REF!) -> #REF! | Z64: =SUMIF(#REF!,$N64,#REF!) -> #REF! | ... CB64: =SUMIF(#REF!,$N64,#REF!) -> #REF!
J65: =IFERROR(H65/F65,"") | S65: =SUMIF(#REF!,$N65,#REF!) -> #REF! | T65: =SUMIF(#REF!,$N65,#REF!) -> #REF! | U65: =SUMIF(#REF!,$N65,#REF!) -> #REF! | V65: =SUMIF(#REF!,$N65,#REF!) -> #REF! | W65: =SUMIF(#REF!,$N65,#REF!) -> #REF! | X65: =SUMIF(#REF!,$N65,#REF!) -> #REF! | Y65: =SUMIF(#REF!,$N65,#REF!) -> #REF! | Z65: =SUMIF(#REF!,$N65,#REF!) -> #REF! | ... CB65: =SUMIF(#REF!,$N65,#REF!) -> #REF!
G66: =F66*D66 -> 0 | I66: =H66*D66 -> 0 | J66: =IFERROR(H66/F66,"") | S66: =SUMIF(#REF!,$N66,#REF!) -> #REF! | T66: =SUMIF(#REF!,$N66,#REF!) -> #REF! | U66: =SUMIF(#REF!,$N66,#REF!) -> #REF! | V66: =SUMIF(#REF!,$N66,#REF!) -> #REF! | W66: =SUMIF(#REF!,$N66,#REF!) -> #REF! | X66: =SUMIF(#REF!,$N66,#REF!) -> #REF! | Y66: =SUMIF(#REF!,$N66,#REF!) -> #REF! | Z66: =SUMIF(#REF!,$N66,#REF!) -> #REF! | ... CB66: =SUMIF(#REF!,$N66,#REF!) -> #REF!
J67: =IFERROR(H67/F67,"") | S67: =SUMIF(#REF!,$N67,#REF!) -> #REF! | T67: =SUMIF(#REF!,$N67,#REF!) -> #REF! | U67: =SUMIF(#REF!,$N67,#REF!) -> #REF! | V67: =SUMIF(#REF!,$N67,#REF!) -> #REF! | W67: =SUMIF(#REF!,$N67,#REF!) -> #REF! | X67: =SUMIF(#REF!,$N67,#REF!) -> #REF! | Y67: =SUMIF(#REF!,$N67,#REF!) -> #REF! | Z67: =SUMIF(#REF!,$N67,#REF!) -> #REF! | ... CB67: =SUMIF(#REF!,$N67,#REF!) -> #REF!
J68: =IFERROR(H68/F68,"") | S68: =SUMIF(#REF!,$N68,#REF!) -> #REF! | T68: =SUMIF(#REF!,$N68,#REF!) -> #REF! | U68: =SUMIF(#REF!,$N68,#REF!) -> #REF! | V68: =SUMIF(#REF!,$N68,#REF!) -> #REF! | W68: =SUMIF(#REF!,$N68,#REF!) -> #REF! | X68: =SUMIF(#REF!,$N68,#REF!) -> #REF! | Y68: =SUMIF(#REF!,$N68,#REF!) -> #REF! | Z68: =SUMIF(#REF!,$N68,#REF!) -> #REF! | ... CB68: =SUMIF(#REF!,$N68,#REF!) -> #REF!
B69: Total | E69: =SUMPRODUCT(E24:E68,D24:D68) -> 0 | G69: =SUM(G24:G68) -> 0 | I69: =SUM(G24:G45) -> 0 | S69: =SUMIF(#REF!,$N69,#REF!) -> #REF! | T69: =SUMIF(#REF!,$N69,#REF!) -> #REF! | U69: =SUMIF(#REF!,$N69,#REF!) -> #REF! | V69: =SUMIF(#REF!,$N69,#REF!) -> #REF! | W69: =SUMIF(#REF!,$N69,#REF!) -> #REF! | X69: =SUMIF(#REF!,$N69,#REF!) -> #REF! | Y69: =SUMIF(#REF!,$N69,#REF!) -> #REF! | Z69: =SUMIF(#REF!,$N69,#REF!) -> #REF! | ... CB69: =SUMIF(#REF!,$N69,#REF!) -> #REF!
B70: Resources | C70: Amount | E70: Amount | S70: =SUMIF(#REF!,$N70,#REF!) -> #REF! | T70: =SUMIF(#REF!,$N70,#REF!) -> #REF! | U70: =SUMIF(#REF!,$N70,#REF!) -> #REF! | V70: =SUMIF(#REF!,$N70,#REF!) -> #REF! | W70: =SUMIF(#REF!,$N70,#REF!) -> #REF! | X70: =SUMIF(#REF!,$N70,#REF!) -> #REF! | Y70: =SUMIF(#REF!,$N70,#REF!) -> #REF! | Z70: =SUMIF(#REF!,$N70,#REF!) -> #REF! | ... CB70: =SUMIF(#REF!,$N70,#REF!) -> #REF!
B71: A.Man Power: | C71: =R22 -> 0 | E71: =Q22 -> #REF! | S71: =SUMIF(#REF!,$N71,#REF!) -> #REF! | T71: =SUMIF(#REF!,$N71,#REF!) -> #REF! | U71: =SUMIF(#REF!,$N71,#REF!) -> #REF! | V71: =SUMIF(#REF!,$N71,#REF!) -> #REF! | W71: =SUMIF(#REF!,$N71,#REF!) -> #REF! | X71: =SUMIF(#REF!,$N71,#REF!) -> #REF! | Y71: =SUMIF(#REF!,$N71,#REF!) -> #REF! | Z71: =SUMIF(#REF!,$N71,#REF!) -> #REF! | ... CB71: =SUMIF(#REF!,$N71,#REF!) -> #REF!
B72: B.Catering/Admin: | C72: =R26 -> 0 | E72: =Q26 -> #REF! | K72: For the day | S72: =SUMIF(#REF!,$N72,#REF!) -> #REF! | T72: =SUMIF(#REF!,$N72,#REF!) -> #REF! | U72: =SUMIF(#REF!,$N72,#REF!) -> #REF! | V72: =SUMIF(#REF!,$N72,#REF!) -> #REF! | W72: =SUMIF(#REF!,$N72,#REF!) -> #REF! | X72: =SUMIF(#REF!,$N72,#REF!) -> #REF! | Y72: =SUMIF(#REF!,$N72,#REF!) -> #REF! | Z72: =SUMIF(#REF!,$N72,#REF!) -> #REF! | ... CB72: =SUMIF(#REF!,$N72,#REF!) -> #REF!
B73: C.Machinery: | C73: =R75 -> 0 | E73: =Q75 -> #REF! | H73: Projection amount | I73: =DPR!H13 -> 0 | S73: =SUMIF(#REF!,$N73,#REF!) -> #REF! | T73: =SUMIF(#REF!,$N73,#REF!) -> #REF! | U73: =SUMIF(#REF!,$N73,#REF!) -> #REF! | V73: =SUMIF(#REF!,$N73,#REF!) -> #REF! | W73: =SUMIF(#REF!,$N73,#REF!) -> #REF! | X73: =SUMIF(#REF!,$N73,#REF!) -> #REF! | Y73: =SUMIF(#REF!,$N73,#REF!) -> #REF! | Z73: =SUMIF(#REF!,$N73,#REF!) -> #REF! | ... CB73: =SUMIF(#REF!,$N73,#REF!) -> #REF!
B74: D.Fuel Charge | C74: =R79 -> 0 | E74: =Q79 -> #REF! | H74: Total Income | I74: =DPR!H13/30*N2 -> 0 | K74: =I74/N2 -> 0 | S74: =SUMIF(#REF!,$N74,#REF!) -> #REF! | T74: =SUMIF(#REF!,$N74,#REF!) -> #REF! | U74: =SUMIF(#REF!,$N74,#REF!) -> #REF! | V74: =SUMIF(#REF!,$N74,#REF!) -> #REF! | W74: =SUMIF(#REF!,$N74,#REF!) -> #REF! | X74: =SUMIF(#REF!,$N74,#REF!) -> #REF! | Y74: =SUMIF(#REF!,$N74,#REF!) -> #REF! | Z74: =SUMIF(#REF!,$N74,#REF!) -> #REF! | ... CB74: =SUMIF(#REF!,$N74,#REF!) -> #REF!
B75: E.Material | C75: =G22 -> 0 | E75: =E22 -> 0 | H75: Total Expenses | I75: =C78 -> 0 | K75: =E78 -> #REF! | N75: Total | Q75: =SUMPRODUCT(Q28:Q74,O28:O74) -> #REF! | R75: =SUM(R29:R74) -> 0
B76: F.SubContractor | C76: =M22 -> 0 | E76: =K22 -> 0 | H76: Contribution | I76: =I74-I75 -> 0 | K76: =K74-K75 -> #REF! | N76: D.Fuel Charge
B77: G. General Expenses | C77: =G69+G21 -> 0 | E77: =E69+(E21*D21) -> 0
B78: Total | C78: =SUM(C71:C77) -> 0 | E78: =SUM(E71:E77) -> #REF! | H78: % Contribution | I78: =IFERROR(I76/I74,"") | J78: =IF(I76>=1,"Profit","Loss") -> Loss | K78: =IFERROR(K76/K74,"") | L78: =IF(K76>=1,"Profit","Loss") -> #REF! | N78: Decsription | O78: Rate | P78: Avg % | Q78: For the day | R78: Total Amount
N79: Fuel | P79: ='Summary-Financial'!AG1 -> 0.4911 | Q79: =Q75*P79 -> #REF! | R79: =R75*P79 -> 0
E81: =E35*D35 -> 0
I83: 65645
I84: =I83-I69 -> 65645
M85: =7065-5143 -> 1922 | N85: 1 | O85: =N85+1 -> 2 | P85: =O85+1 -> 3 | Q85: =P85+1 -> 4 | R85: =Q85+1 -> 5 | S85: =R85+1 -> 6 | T85: =S85+1 -> 7 | U85: =T85+1 -> 8 | V85: =U85+1 -> 9 | ... CB85: =CA85+1 -> 67
L87: =3%*K74 -> 0
L88: =3%*K75 -> #REF!

Sheet MP & Eqpt Summary 1
C1: =SUMPRODUCT(--(#REF!='MP & Eqpt Summary 1'!E1),#REF!*1) -> #REF! | E1: ='MP & Eqpt Summary'!G1 -> xxxx | F1: Major Equipment deployment
C2: SL No | D2: Description | E2: Rate | F2: xxxx | G2: xxxx | H2: xxxx | I2: xxxx | J2: xxxx | K2: xxxx | L2: xxxx | M2: xxxx | N2: xxxx | O2: xxxx | P2: xxxx | Q2: xxxx | R2: xxxx | S2: xxxx | T2: xxxx | U2: xxxx | V2: xxxx | W2: xxxx | X2: xxxx | Z2: Total | AA2: Available @ site | AB2: Variation | AC2: Prelims | AD2: Iftikhar | AE2: Gopi | AF2: Anil PP | AG2: Koshy | AH2: Total | AI2: DCR | AK2: ACT | AL2: CHECK | AQ2: Gopi
A3: GRAD | B3: GRAD | C3: 1 | D3: Grader | F3: =IFERROR(VLOOKUP(D3,#REF!,'MP & Eqpt Summary 1'!$C$1,FALSE),0) -> 0 | G3: =IFERROR(VLOOKUP(D3,#REF!,'MP & Eqpt Summary 1'!$C$1,FALSE),0) -> 0 | H3: =IFERROR(VLOOKUP(D3,#REF!,'MP & Eqpt Summary 1'!$C$1,FALSE),0) -> 0 | I3: =IFERROR(VLOOKUP(D3,#REF!,'MP & Eqpt Summary 1'!$C$1,FALSE),0) -> 0 | J3: =IFERROR(VLOOKUP(D3,#REF!,'MP & Eqpt Summary 1'!$C$1,FALSE),0) -> 0 | K3: =IFERROR(VLOOKUP(D3,#REF!,'MP & Eqpt Summary 1'!$C$1,FALSE),0) -> 0 | L3: =IFERROR(VLOOKUP(D3,#REF!,'MP & Eqpt Summary 1'!$C$1,FALSE),0) -> 0 | M3: =IFERROR(VLOOKUP(D3,#REF!,'MP & Eqpt Summary 1'!$C$1,FALSE),0) -> 0 | N3: =IFERROR(VLOOKUP($D3,#REF!,'MP & Eqpt Summary 1'!$C$1,FALSE),0) -> 0 | O3: =IFERROR(VLOOKUP(D3,#REF!,'MP & Eqpt Summary 1'!$C$1,FALSE),0) -> 0 | P3: =IFERROR(VLOOKUP(D3,#REF!,'MP & Eqpt Summary 1'!$C$1,FALSE),0) -> 0 | Q3: =IFERROR(VLOOKUP(D3,#REF!,'MP & Eqpt Summary 1'!$C$1,FALSE),0) -> 0 | R3: =IFERROR(VLOOKUP(D3,#REF!,'MP & Eqpt Summary 1'!$C$1,FALSE),0) -> 0 | S3: =IFERROR(VLOOKUP(D3,#REF!,'MP & Eqpt Summary 1'!$C$1,FALSE),0) -> 0 | T3: =IFERROR(VLOOKUP(D3,#REF!,'MP & Eqpt Summary 1'!$C$1,FALSE),0) -> 0 | U3: =IFERROR(VLOOKUP(D3,#REF!,'MP & Eqpt Summary 1'!$C$1,FALSE),0) -> 0 | V3: =IFERROR(VLOOKUP(D3,#REF!,'MP & Eqpt Summary 1'!$C$1,FALSE),0) -> 0 | W3: =IFERROR(VLOOKUP(D3,#REF!,'MP & Eqpt Summary 1'!$C$1,FALSE),0) -> 0 | X3: =IFERROR(VLOOKUP(D3,#REF!,'MP & Eqpt Summary 1'!$C$1,FALSE),0) -> 0 | Z3: =SUM(F3:Y3) -> 0 | AB3: =AA3-Z3 -> 0 | AC3: =IFERROR(VLOOKUP(D3,#REF!,2,FALSE),0)+IFERROR(VLOOKUP(D3,#REF!,3,FALSE),0) -> 0 | AD3: =IFERROR(VLOOKUP(D3,#REF!,2,FALSE),0)+IFERROR(VLOOKUP(D3,#REF!,3,FALSE),0) -> 0 | AE3: 0 | AF3: =IFERROR(VLOOKUP(D3,#REF!,2,FALSE),0)+IFERROR(VLOOKUP(D3,#REF!,3,FALSE),0) -> 0 | AG3: =IFERROR(VLOOKUP(D3,#REF!,2,FALSE),0)+IFERROR(VLOOKUP(D3,#REF!,3,FALSE),0) -> 0 | AH3: =SUM(AC3:AG3) -> 0 | AI3: =AH3*E3 -> 0 | AJ3: 63.5 | AK3: =AJ3*E3 -> 0 | AL3: =AI3-AK3 -> 0 | AM3: #VALUE! | AN3: #VALUE! | AO3: =SUM(AM3:AN3) -> #VALUE! | AP3: =AO3-AM3 -> #VALUE!
A4: VIBR | B4: VIBR | C4: =C3+1 -> 2 | D4: Vibratory Roller | F4: =IFERROR(VLOOKUP(D4,#REF!,'MP & Eqpt Summary 1'!$C$1,FALSE),0) -> 0 | G4: =IFERROR(VLOOKUP(D4,#REF!,'MP & Eqpt Summary 1'!$C$1,FALSE),0) -> 0 | H4: =IFERROR(VLOOKUP(D4,#REF!,'MP & Eqpt Summary 1'!$C$1,FALSE),0) -> 0 | I4: =IFERROR(VLOOKUP(D4,#REF!,'MP & Eqpt Summary 1'!$C$1,FALSE),0) -> 0 | J4: =IFERROR(VLOOKUP(D4,#REF!,'MP & Eqpt Summary 1'!$C$1,FALSE),0) -> 0 | K4: =IFERROR(VLOOKUP(D4,#REF!,'MP & Eqpt Summary 1'!$C$1,FALSE),0) -> 0 | L4: =IFERROR(VLOOKUP(D4,#REF!,'MP & Eqpt Summary 1'!$C$1,FALSE),0) -> 0 | M4: =IFERROR(VLOOKUP(D4,#REF!,'MP & Eqpt Summary 1'!$C$1,FALSE),0) -> 0 | N4: =IFERROR(VLOOKUP($D4,#REF!,'MP & Eqpt Summary 1'!$C$1,FALSE),0) -> 0 | O4: =IFERROR(VLOOKUP(D4,#REF!,'MP & Eqpt Summary 1'!$C$1,FALSE),0) -> 0 | P4: =IFERROR(VLOOKUP(D4,#REF!,'MP & Eqpt Summary 1'!$C$1,FALSE),0) -> 0 | Q4: =IFERROR(VLOOKUP(D4,#REF!,'MP & Eqpt Summary 1'!$C$1,FALSE),0) -> 0 | R4: =IFERROR(VLOOKUP(D4,#REF!,'MP & Eqpt Summary 1'!$C$1,FALSE),0) -> 0 | S4: =IFERROR(VLOOKUP(D4,#REF!,'MP & Eqpt Summary 1'!$C$1,FALSE),0) -> 0 | T4: =IFERROR(VLOOKUP(D4,#REF!,'MP & Eqpt Summary 1'!$C$1,FALSE),0) -> 0 | U4: =IFERROR(VLOOKUP(D4,#REF!,'MP & Eqpt Summary 1'!$C$1,FALSE),0) -> 0 | V4: =IFERROR(VLOOKUP(D4,#REF!,'MP & Eqpt Summary 1'!$C$1,FALSE),0) -> 0 | W4: =IFERROR(VLOOKUP(D4,#REF!,'MP & Eqpt Summary 1'!$C$1,FALSE),0) -> 0 | X4: =IFERROR(VLOOKUP(D4,#REF!,'MP & Eqpt Summary 1'!$C$1,FALSE),0) -> 0 | Z4: =SUM(F4:Y4) -> 0 | AB4: =AA4-Z4 -> 0 | AC4: =IFERROR(VLOOKUP(D4,#REF!,2,FALSE),0)+IFERROR(VLOOKUP(D4,#REF!,3,FALSE),0) -> 0 | AD4: =IFERROR(VLOOKUP(D4,#REF!,2,FALSE),0)+IFERROR(VLOOKUP(D4,#REF!,3,FALSE),0) -> 0 | AE4: 0 | AF4: =IFERROR(VLOOKUP(D4,#REF!,2,FALSE),0)+IFERROR(VLOOKUP(D4,#REF!,3,FALSE),0) -> 0 | AG4: =IFERROR(VLOOKUP(D4,#REF!,2,FALSE),0)+IFERROR(VLOOKUP(D4,#REF!,3,FALSE),0) -> 0 | AH4: =SUM(AC4:AG4) -> 0 | AI4: =AH4*E4 -> 0 | AJ4: 86.5 | AK4: =AJ4*E4 -> 0 | AL4: =AI4-AK4 -> 0 | AM4: #VALUE! | AN4: #VALUE! | AO4: =SUM(AM4:AN4) -> #VALUE! | AP4: =AO4-AM4 -> #VALUE!
A5: DOZ | B5: DOZ | C5: =C4+1 -> 3 | D5: Bull Dozer | F5: =IFERROR(VLOOKUP(D5,#REF!,'MP & Eqpt Summary 1'!$C$1,FALSE),0) -> 0 | G5: =IFERROR(VLOOKUP(D5,#REF!,'MP & Eqpt Summary 1'!$C$1,FALSE),0) -> 0 | H5: =IFERROR(VLOOKUP(D5,#REF!,'MP & Eqpt Summary 1'!$C$1,FALSE),0) -> 0 | I5: =IFERROR(VLOOKUP(D5,#REF!,'MP & Eqpt Summary 1'!$C$1,FALSE),0) -> 0 | J5: =IFERROR(VLOOKUP(D5,#REF!,'MP & Eqpt Summary 1'!$C$1,FALSE),0) -> 0 | K5: =IFERROR(VLOOKUP(D5,#REF!,'MP & Eqpt Summary 1'!$C$1,FALSE),0) -> 0 | L5: =IFERROR(VLOOKUP(D5,#REF!,'MP & Eqpt Summary 1'!$C$1,FALSE),0) -> 0 | M5: =IFERROR(VLOOKUP(D5,#REF!,'MP & Eqpt Summary 1'!$C$1,FALSE),0) -> 0 | N5: =IFERROR(VLOOKUP($D5,#REF!,'MP & Eqpt Summary 1'!$C$1,FALSE),0) -> 0 | O5: =IFERROR(VLOOKUP(D5,#REF!,'MP & Eqpt Summary 1'!$C$1,FALSE),0) -> 0 | P5: =IFERROR(VLOOKUP(D5,#REF!,'MP & Eqpt Summary 1'!$C$1,FALSE),0) -> 0 | Q5: =IFERROR(VLOOKUP(D5,#REF!,'MP & Eqpt Summary 1'!$C$1,FALSE),0) -> 0 | R5: =IFERROR(VLOOKUP(D5,#REF!,'MP & Eqpt Summary 1'!$C$1,FALSE),0) -> 0 | S5: =IFERROR(VLOOKUP(D5,#REF!,'MP & Eqpt Summary 1'!$C$1,FALSE),0) -> 0 | T5: =IFERROR(VLOOKUP(D5,#REF!,'MP & Eqpt Summary 1'!$C$1,FALSE),0) -> 0 | U5: =IFERROR(VLOOKUP(D5,#REF!,'MP & Eqpt Summary 1'!$C$1,FALSE),0) -> 0 | V5: =IFERROR(VLOOKUP(D5,#REF!,'MP & Eqpt Summary 1'!$C$1,FALSE),0) -> 0 | W5: =IFERROR(VLOOKUP(D5,#REF!,'MP & Eqpt Summary 1'!$C$1,FALSE),0) -> 0 | X5: =IFERROR(VLOOKUP(D5,#REF!,'MP & Eqpt Summary 1'!$C$1,FALSE),0) -> 0 | Z5: =SUM(F5:Y5) -> 0 | AB5: =AA5-Z5 -> 0 | AC5: =IFERROR(VLOOKUP(D5,#REF!,2,FALSE),0)+IFERROR(VLOOKUP(D5,#REF!,3,FALSE),0) -> 0 | AD5: =IFERROR(VLOOKUP(D5,#REF!,2,FALSE),0)+IFERROR(VLOOKUP(D5,#REF!,3,FALSE),0) -> 0 | AE5: 0 | AF5: =IFERROR(VLOOKUP(D5,#REF!,2,FALSE),0)+IFERROR(VLOOKUP(D5,#REF!,3,FALSE),0) -> 0 | AG5: =IFERROR(VLOOKUP(D5,#REF!,2,FALSE),0)+IFERROR(VLOOKUP(D5,#REF!,3,FALSE),0) -> 0 | AH5: =SUM(AC5:AG5) -> 0 | AI5: =AH5*E5 -> 0 | AJ5: 47.55 | AK5: =AJ5*E5 -> 0 | AL5: =AI5-AK5 -> 0 | AM5: #VALUE! | AN5: #VALUE! | AO5: =SUM(AM5:AN5) -> #VALUE! | AP5: =AO5-AM5 -> #VALUE!
A6: SVL | B6: SVL | C6: =C5+1 -> 4 | D6: Wheel Loader | F6: =IFERROR(VLOOKUP(D6,#REF!,'MP & Eqpt Summary 1'!$C$1,FALSE),0) -> 0 | G6: =IFERROR(VLOOKUP(D6,#REF!,'MP & Eqpt Summary 1'!$C$1,FALSE),0) -> 0 | H6: =IFERROR(VLOOKUP(D6,#REF!,'MP & Eqpt Summary 1'!$C$1,FALSE),0) -> 0 | I6: =IFERROR(VLOOKUP(D6,#REF!,'MP & Eqpt Summary 1'!$C$1,FALSE),0) -> 0 | J6: =IFERROR(VLOOKUP(D6,#REF!,'MP & Eqpt Summary 1'!$C$1,FALSE),0) -> 0 | K6: =IFERROR(VLOOKUP(D6,#REF!,'MP & Eqpt Summary 1'!$C$1,FALSE),0) -> 0 | L6: =IFERROR(VLOOKUP(D6,#REF!,'MP & Eqpt Summary 1'!$C$1,FALSE),0) -> 0 | M6: =IFERROR(VLOOKUP(D6,#REF!,'MP & Eqpt Summary 1'!$C$1,FALSE),0) -> 0 | N6: =IFERROR(VLOOKUP($D6,#REF!,'MP & Eqpt Summary 1'!$C$1,FALSE),0) -> 0 | O6: =IFERROR(VLOOKUP(D6,#REF!,'MP & Eqpt Summary 1'!$C$1,FALSE),0) -> 0 | P6: =IFERROR(VLOOKUP(D6,#REF!,'MP & Eqpt Summary 1'!$C$1,FALSE),0) -> 0 | Q6: =IFERROR(VLOOKUP(D6,#REF!,'MP & Eqpt Summary 1'!$C$1,FALSE),0) -> 0 | R6: =IFERROR(VLOOKUP(D6,#REF!,'MP & Eqpt Summary 1'!$C$1,FALSE),0) -> 0 | S6: =IFERROR(VLOOKUP(D6,#REF!,'MP & Eqpt Summary 1'!$C$1,FALSE),0) -> 0 | T6: =IFERROR(VLOOKUP(D6,#REF!,'MP & Eqpt Summary 1'!$C$1,FALSE),0) -> 0 | U6: =IFERROR(VLOOKUP(D6,#REF!,'MP & Eqpt Summary 1'!$C$1,FALSE),0) -> 0 | V6: =IFERROR(VLOOKUP(D6,#REF!,'MP & Eqpt Summary 1'!$C$1,FALSE),0) -> 0 | W6: =IFERROR(VLOOKUP(D6,#REF!,'MP & Eqpt Summary 1'!$C$1,FALSE),0) -> 0 | X6: =IFERROR(VLOOKUP(D6,#REF!,'MP & Eqpt Summary 1'!$C$1,FALSE),0) -> 0 | Z6: =SUM(F6:Y6) -> 0 | AB6: =AA6-Z6 -> 0 | AC6: =IFERROR(VLOOKUP(D6,#REF!,2,FALSE),0)+IFERROR(VLOOKUP(D6,#REF!,3,FALSE),0) -> 0 | AD6: =IFERROR(VLOOKUP(D6,#REF!,2,FALSE),0)+IFERROR(VLOOKUP(D6,#REF!,3,FALSE),0) -> 0 | AE6: 0 | AF6: =IFERROR(VLOOKUP(D6,#REF!,2,FALSE),0)+IFERROR(VLOOKUP(D6,#REF!,3,FALSE),0) -> 0 | AG6: =IFERROR(VLOOKUP(D6,#REF!,2,FALSE),0)+IFERROR(VLOOKUP(D6,#REF!,3,FALSE),0) -> 0 | AH6: =SUM(AC6:AG6) -> 0 | AI6: =AH6*E6 -> 0 | AJ6: 123.5 | AK6: =AJ6*E6 -> 0 | AL6: =AI6-AK6 -> 0 | AM6: #VALUE! | AN6: #VALUE! | AO6: =SUM(AM6:AN6) -> #VALUE! | AP6: =AO6-AM6 -> #VALUE!
A7: SVL1 | B7: SVL1 | C7: =C6+1 -> 5 | D7: Wheel Loader (980) | F7: =IFERROR(VLOOKUP(D7,#REF!,'MP & Eqpt Summary 1'!$C$1,FALSE),0) -> 0 | G7: =IFERROR(VLOOKUP(D7,#REF!,'MP & Eqpt Summary 1'!$C$1,FALSE),0) -> 0 | H7: =IFERROR(VLOOKUP(D7,#REF!,'MP & Eqpt Summary 1'!$C$1,FALSE),0) -> 0 | I7: =IFERROR(VLOOKUP(D7,#REF!,'MP & Eqpt Summary 1'!$C$1,FALSE),0) -> 0 | J7: =IFERROR(VLOOKUP(D7,#REF!,'MP & Eqpt Summary 1'!$C$1,FALSE),0) -> 0 | K7: =IFERROR(VLOOKUP(D7,#REF!,'MP & Eqpt Summary 1'!$C$1,FALSE),0) -> 0 | L7: =IFERROR(VLOOKUP(D7,#REF!,'MP & Eqpt Summary 1'!$C$1,FALSE),0) -> 0 | M7: =IFERROR(VLOOKUP(D7,#REF!,'MP & Eqpt Summary 1'!$C$1,FALSE),0) -> 0 | N7: =IFERROR(VLOOKUP($D7,#REF!,'MP & Eqpt Summary 1'!$C$1,FALSE),0) -> 0 | O7: =IFERROR(VLOOKUP(D7,#REF!,'MP & Eqpt Summary 1'!$C$1,FALSE),0) -> 0 | P7: =IFERROR(VLOOKUP(D7,#REF!,'MP & Eqpt Summary 1'!$C$1,FALSE),0) -> 0 | Q7: =IFERROR(VLOOKUP(D7,#REF!,'MP & Eqpt Summary 1'!$C$1,FALSE),0) -> 0 | R7: =IFERROR(VLOOKUP(D7,#REF!,'MP & Eqpt Summary 1'!$C$1,FALSE),0) -> 0 | S7: =IFERROR(VLOOKUP(D7,#REF!,'MP & Eqpt Summary 1'!$C$1,FALSE),0) -> 0 | T7: =IFERROR(VLOOKUP(D7,#REF!,'MP & Eqpt Summary 1'!$C$1,FALSE),0) -> 0 | U7: =IFERROR(VLOOKUP(D7,#REF!,'MP & Eqpt Summary 1'!$C$1,FALSE),0) -> 0 | V7: =IFERROR(VLOOKUP(D7,#REF!,'MP & Eqpt Summary 1'!$C$1,FALSE),0) -> 0 | W7: =IFERROR(VLOOKUP(D7,#REF!,'MP & Eqpt Summary 1'!$C$1,FALSE),0) -> 0 | X7: =IFERROR(VLOOKUP(D7,#REF!,'MP & Eqpt Summary 1'!$C$1,FALSE),0) -> 0 | Z7: =SUM(F7:Y7) -> 0 | AB7: =AA7-Z7 -> 0
A8: JCB | B8: JCB | C8: =C7+1 -> 6 | D8: Back Hoe Loader | F8: =IFERROR(VLOOKUP(D8,#REF!,'MP & Eqpt Summary 1'!$C$1,FALSE),0) -> 0 | G8: =IFERROR(VLOOKUP(D8,#REF!,'MP & Eqpt Summary 1'!$C$1,FALSE),0) -> 0 | H8: =IFERROR(VLOOKUP(D8,#REF!,'MP & Eqpt Summary 1'!$C$1,FALSE),0) -> 0 | I8: =IFERROR(VLOOKUP(D8,#REF!,'MP & Eqpt Summary 1'!$C$1,FALSE),0) -> 0 | J8: =IFERROR(VLOOKUP(D8,#REF!,'MP & Eqpt Summary 1'!$C$1,FALSE),0) -> 0 | K8: =IFERROR(VLOOKUP(D8,#REF!,'MP & Eqpt Summary 1'!$C$1,FALSE),0) -> 0 | L8: =IFERROR(VLOOKUP(D8,#REF!,'MP & Eqpt Summary 1'!$C$1,FALSE),0) -> 0 | M8: =IFERROR(VLOOKUP(D8,#REF!,'MP & Eqpt Summary 1'!$C$1,FALSE),0) -> 0 | N8: =IFERROR(VLOOKUP($D8,#REF!,'MP & Eqpt Summary 1'!$C$1,FALSE),0) -> 0 | O8: =IFERROR(VLOOKUP(D8,#REF!,'MP & Eqpt Summary 1'!$C$1,FALSE),0) -> 0 | P8: =IFERROR(VLOOKUP(D8,#REF!,'MP & Eqpt Summary 1'!$C$1,FALSE),0) -> 0 | Q8: =IFERROR(VLOOKUP(D8,#REF!,'MP & Eqpt Summary 1'!$C$1,FALSE),0) -> 0 | R8: =IFERROR(VLOOKUP(D8,#REF!,'MP & Eqpt Summary 1'!$C$1,FALSE),0) -> 0 | S8: =IFERROR(VLOOKUP(D8,#REF!,'MP & Eqpt Summary 1'!$C$1,FALSE),0) -> 0 | T8: =IFERROR(VLOOKUP(D8,#REF!,'MP & Eqpt Summary 1'!$C$1,FALSE),0) -> 0 | U8: =IFERROR(VLOOKUP(D8,#REF!,'MP & Eqpt Summary 1'!$C$1,FALSE),0) -> 0 | V8: =IFERROR(VLOOKUP(D8,#REF!,'MP & Eqpt Summary 1'!$C$1,FALSE),0) -> 0 | W8: =IFERROR(VLOOKUP(D8,#REF!,'MP & Eqpt Summary 1'!$C$1,FALSE),0) -> 0 | X8: =IFERROR(VLOOKUP(D8,#REF!,'MP & Eqpt Summary 1'!$C$1,FALSE),0) -> 0 | Z8: =SUM(F8:Y8) -> 0 | AB8: =AA8-Z8 -> 0 | AC8: =IFERROR(VLOOKUP(D8,#REF!,2,FALSE),0)+IFERROR(VLOOKUP(D8,#REF!,3,FALSE),0) -> 0 | AD8: =IFERROR(VLOOKUP(D8,#REF!,2,FALSE),0)+IFERROR(VLOOKUP(D8,#REF!,3,FALSE),0) -> 0 | AE8: 0 | AF8: =IFERROR(VLOOKUP(D8,#REF!,2,FALSE),0)+IFERROR(VLOOKUP(D8,#REF!,3,FALSE),0) -> 0 | AG8: =IFERROR(VLOOKUP(D8,#REF!,2,FALSE),0)+IFERROR(VLOOKUP(D8,#REF!,3,FALSE),0) -> 0 | AH8: =SUM(AC8:AG8) -> 0 | AI8: =AH8*E8 -> 0 | AJ8: 47 | AK8: =AJ8*E8 -> 0 | AL8: =AI8-AK8 -> 0 | AM8: #VALUE! | AN8: #VALUE! | AO8: =SUM(AM8:AN8) -> #VALUE! | AP8: =AO8-AM8 -> #VALUE!
A9: JCB-H | B9: JCB-H | C9: =C8+1 -> 7 | D9: Back Hoe Loader (Hire) | F9: =IFERROR(VLOOKUP(D9,#REF!,'MP & Eqpt Summary 1'!$C$1,FALSE),0) -> 0 | G9: =IFERROR(VLOOKUP(D9,#REF!,'MP & Eqpt Summary 1'!$C$1,FALSE),0) -> 0 | H9: =IFERROR(VLOOKUP(D9,#REF!,'MP & Eqpt Summary 1'!$C$1,FALSE),0) -> 0 | I9: =IFERROR(VLOOKUP(D9,#REF!,'MP & Eqpt Summary 1'!$C$1,FALSE),0) -> 0 | J9: =IFERROR(VLOOKUP(D9,#REF!,'MP & Eqpt Summary 1'!$C$1,FALSE),0) -> 0 | K9: =IFERROR(VLOOKUP(D9,#REF!,'MP & Eqpt Summary 1'!$C$1,FALSE),0) -> 0 | L9: =IFERROR(VLOOKUP(D9,#REF!,'MP & Eqpt Summary 1'!$C$1,FALSE),0) -> 0 | M9: =IFERROR(VLOOKUP(D9,#REF!,'MP & Eqpt Summary 1'!$C$1,FALSE),0) -> 0 | N9: =IFERROR(VLOOKUP($D9,#REF!,'MP & Eqpt Summary 1'!$C$1,FALSE),0) -> 0 | O9: =IFERROR(VLOOKUP(D9,#REF!,'MP & Eqpt Summary 1'!$C$1,FALSE),0) -> 0 | P9: =IFERROR(VLOOKUP(D9,#REF!,'MP & Eqpt Summary 1'!$C$1,FALSE),0) -> 0 | Q9: =IFERROR(VLOOKUP(D9,#REF!,'MP & Eqpt Summary 1'!$C$1,FALSE),0) -> 0 | R9: =IFERROR(VLOOKUP(D9,#REF!,'MP & Eqpt Summary 1'!$C$1,FALSE),0) -> 0 | S9: =IFERROR(VLOOKUP(D9,#REF!,'MP & Eqpt Summary 1'!$C$1,FALSE),0) -> 0 | T9: =IFERROR(VLOOKUP(D9,#REF!,'MP & Eqpt Summary 1'!$C$1,FALSE),0) -> 0 | U9: =IFERROR(VLOOKUP(D9,#REF!,'MP & Eqpt Summary 1'!$C$1,FALSE),0) -> 0 | V9: =IFERROR(VLOOKUP(D9,#REF!,'MP & Eqpt Summary 1'!$C$1,FALSE),0) -> 0 | W9: =IFERROR(VLOOKUP(D9,#REF!,'MP & Eqpt Summary 1'!$C$1,FALSE),0) -> 0 | X9: =IFERROR(VLOOKUP(D9,#REF!,'MP & Eqpt Summary 1'!$C$1,FALSE),0) -> 0 | Z9: =SUM(F9:Y9) -> 0 | AB9: =AA9-Z9 -> 0 | AC9: =IFERROR(VLOOKUP(D9,#REF!,2,FALSE),0)+IFERROR(VLOOKUP(D9,#REF!,3,FALSE),0) -> 0 | AD9: =IFERROR(VLOOKUP(D9,#REF!,2,FALSE),0)+IFERROR(VLOOKUP(D9,#REF!,3,FALSE),0) -> 0 | AE9: 0 | AF9: =IFERROR(VLOOKUP(D9,#REF!,2,FALSE),0)+IFERROR(VLOOKUP(D9,#REF!,3,FALSE),0) -> 0 | AG9: =IFERROR(VLOOKUP(D9,#REF!,2,FALSE),0)+IFERROR(VLOOKUP(D9,#REF!,3,FALSE),0) -> 0 | AH9: =SUM(AC9:AG9) -> 0 | AI9: =AH9*E9 -> 0 | AJ9: 0 | AK9: =AJ9*E9 -> 0 | AL9: =AI9-AK9 -> 0 | AM9: #VALUE! | AN9: #VALUE! | AO9: =SUM(AM9:AN9) -> #VALUE! | AP9: =AO9-AM9 -> #VALUE!
